Workbook

Sheet Start Here
A1: Clinical Roundup | Option C build and scale
A2: MODEL, NOT QUOTE. USD cash planning; US hiring benchmark; 60 months. Blue = editable, green = formula, amber = evidence/quote gap. No PHI or live PoC changes.
A3: ← Start Here
A5: Scenario | B5: Base | D5: Workbook navigation ↓ (also see tabs)
A6: Project start (first day of month) | B6: 46327 | D6: Source refresh and approvals required before commitments.
A7: Enable optional AI (0/1) | B7: 0 | D7: No macros, external workbook links, or network calls in generator.
A8: Enable optional CTMS (0/1) | B8: 0
A9: Mutually exclusive cloud candidate | B9: Azure
A10: Pay founder cash (0/1) | B10: 0
A12: Decision metrics (after Excel recalculation; see snapshot.json for offline results)
A13: 5-year total cash spend | B13: =SUM('Monthly Model'!AC6:AC65) -> 10907250
A14: Year 1 spend / cost-only burn | B14: =SUM('Monthly Model'!AC6:AC17) -> 1027452.6
A15: Peak FTE incl. founder | B15: =MAX('Monthly Model'!I6:I65) -> 12.75
A16: Cash low point with revenue/financing | B16: =MIN('Monthly Model'!AI6:AI65) -> -5465729.5
A17: Maximum financing gap (not sum of deficits) | B17: =MAX('Monthly Model'!AK6:AK65) -> 5465729.5
A18: Cost-only financing gap (zero revenue) | B18: =MAX(0,-MIN('Monthly Model'!AL6:AL65)) -> 6907250.1
A19: Quote/unverified vendor allowance subtotal | B19: =SUM('Monthly Model'!AM6:AM65) -> 428483.56
A20: Unresolved selected catalog line count | B20: =SUM(Nonlabor!N6:N27) -> 9
A21: Unpaid founder opportunity cost (outside spend) | B21: =SUM('Monthly Model'!AO6:AO65) -> 974938.06
A22: Runway: first negative month / >60 / not funded | B22: =IF(AND(INDEX(Assumptions!C6:E6,1,MATCH(B5,Assumptions!C5:E5,0))<=0,'Monthly Model'!AG6<=0,'Monthly Model'!AD6<=0),"Not funded",IF(COUNTIF('Monthly Model'!AI6:AI65,"<0")=0,">60 months",MATCH(1,'Monthly Model'!AR6:AR65,0))) -> 12
A24: Use: 1 choose scenario/start/options; 2 review blue inputs; 3 resolve amber sources; 4 inspect monthly/annual and gates.
A25: No guarantee of PMF, valuation, revenue, compliance or enterprise readiness. Negative cash is not funded.
A26: Baseline = clinical rounding. CTMS requires new study/site workflows, integrations and validation; AI has separate approval gates.
A27: Ranges: low/medium confidence estimates. Cash excludes income/sales taxes, debt interest, equity, depreciation and working-capital delays.
A28: Scenario changes do not prove faster delivery. Gates override calendar; stop before unapproved PHI, AI or research processing.
A31: Assumptions | D31: Five-year cash by category
A32: Sources | D32: Staff cash | E32: =SUM('Monthly Model'!K6:K65) -> 8684588.3
A33: Staffing | D33: Recruiting | E33: =SUM('Monthly Model'!L6:L65) -> 80000
A34: Nonlabor | D34: Equipment | E34: =SUM('Monthly Model'!M6:M65) -> 38250
A35: Requirements | D35: INFRA | E35: =SUM('Monthly Model'!N6:N65) -> 93355.576
A36: Migration WBS | D36: TOOLS | E36: =SUM('Monthly Model'!O6:O65) -> 32053.036
A37: Architecture | D37: LEGAL | E37: =SUM('Monthly Model'!P6:P65) -> 71709.63
A38: Roadmap | D38: SECURITY | E38: =SUM('Monthly Model'!Q6:Q65) -> 95564.445
A39: Risks and Funding | D39: COMPLIANCE | E39: =SUM('Monthly Model'!R6:R65) -> 79637.037
A40: Staff Months | D40: INSURANCE | E40: =SUM('Monthly Model'!S6:S65) -> 63709.63
A41: Monthly Lean | D41: ACCOUNTING | E41: =SUM('Monthly Model'!T6:T65) -> 38225.778
A42: Monthly Base | D42: SUPPORT | E42: =SUM('Monthly Model'!U6:U65) -> 5570.963
A43: Monthly Growth | D43: MARKETING | E43: =SUM('Monthly Model'!V6:V65) -> 132333.17
A44: Monthly Model | D44: ONBOARD | E44: =SUM('Monthly Model'!W6:W65) -> 31962.881
A45: Vendor Months | D45: AI | E45: =SUM('Monthly Model'!X6:X65) -> 0
A46: Annual Summary | D46: CTMS | E46: =SUM('Monthly Model'!Y6:Y65) -> 0
A47: Scenario Comparison | D47: Contingency | E47: =SUM('Monthly Model'!AA6:AA65) -> 1417044.1
A48: Charts | D48: Payment fees | E48: =SUM('Monthly Model'!AB6:AB65) -> 43245.617
D51: Optional staffing is in Staff cash, not in optional vendor-only categories.
D52: WBS assumed person-days use these staffing pools; not additional project labor invoices.

Sheet Assumptions
A1: Editable scenario assumptions
A2: Selected values are formulas; scenario columns are independent assumptions, not total-cost multipliers. Start and switches live on Start Here.
A3: ← Start Here
A5: Key | B5: Assumption | C5: Lean | D5: Base | E5: Growth | F5: Unit | G5: Basis / caveat | H5: Selected
A6: initial_cash | B6: Initial available cash | C6: 500000 | D6: 1000000 | E6: 2000000 | F6: USD | G6: Assumption; not committed financing | H6: =INDEX(C6:E6,1,MATCH('Start Here'!$B$5,$C$5:$E$5,0)) -> 1000000
A7: financing_month | B7: Proposed financing month | C7: 13 | D7: 13 | E7: 10 | F7: month | G7: One hypothetical event; no valuation implied | H7: =INDEX(C7:E7,1,MATCH('Start Here'!$B$5,$C$5:$E$5,0)) -> 13
A8: financing_amount | B8: Proposed financing cash | C8: 1000000 | D8: 3000000 | E8: 6000000 | F8: USD | G8: Editable and uncommitted; set to zero for no financing | H8: =INDEX(C8:E8,1,MATCH('Start Here'!$B$5,$C$5:$E$5,0)) -> 3000000
A9: inflation | B9: Annual non-labor inflation | C9: 0.03 | D9: 0.03 | E9: 0.04 | F9: percent | G9: Planning assumption; annual step from project start | H9: =INDEX(C9:E9,1,MATCH('Start Here'!$B$5,$C$5:$E$5,0)) -> 0.03
A10: salary_growth | B10: Annual salary escalation | C10: 0.03 | D10: 0.04 | E10: 0.05 | F10: percent | G10: Planning assumption, not wage forecast | H10: =INDEX(C10:E10,1,MATCH('Start Here'!$B$5,$C$5:$E$5,0)) -> 0.04
A11: burden | B11: Employer burden as fraction of WAGES | C11: 0.4 | D11: 0.4 | E11: 0.4 | F11: percent | G11: Selected allowance, includes payroll tax/benefits; never percent of total compensation | H11: =INDEX(C11:E11,1,MATCH('Start Here'!$B$5,$C$5:$E$5,0)) -> 0.4
A12: contingency | B12: Contingency on labor + vendor cash | C12: 0.1 | D12: 0.15 | E12: 0.2 | F12: percent | G12: Applied once; excludes founder unpaid opportunity cost and payment fees | H12: =INDEX(C12:E12,1,MATCH('Start Here'!$B$5,$C$5:$E$5,0)) -> 0.15
A13: launch | B13: First revenue month (gated assumption) | C13: 16 | D13: 13 | E13: 12 | F13: month | G13: Not authorization for customer PHI pilot | H13: =INDEX(C13:E13,1,MATCH('Start Here'!$B$5,$C$5:$E$5,0)) -> 13
A14: new_customers | B14: New customers per month at launch | C14: 0.5 | D14: 1 | E14: 2 | F14: customers/month | G14: Expected-value cohorts, fractional customers allowed | H14: =INDEX(C14:E14,1,MATCH('Start Here'!$B$5,$C$5:$E$5,0)) -> 1
A15: customer_growth | B15: Annual growth in new customer cohorts | C15: 0.25 | D15: 0.5 | E15: 0.7 | F15: percent | G15: Unproven acquisition assumption; not market data | H15: =INDEX(C15:E15,1,MATCH('Start Here'!$B$5,$C$5:$E$5,0)) -> 0.5
A16: churn | B16: Monthly customer churn | C16: 0.015 | D16: 0.01 | E16: 0.01 | F16: percent | G16: Applied to opening customers; cohorts start billing immediately | H16: =INDEX(C16:E16,1,MATCH('Start Here'!$B$5,$C$5:$E$5,0)) -> 0.01
A17: arpa | B17: Monthly subscription per organization | C17: 500 | D17: 900 | E17: 1400 | F17: USD/customer | G17: Pricing hypothesis, no market validation; no annual prepay | H17: =INDEX(C17:E17,1,MATCH('Start Here'!$B$5,$C$5:$E$5,0)) -> 900
... A30: cadence | B30: Iteration length | C30: 2 | D30: 2 | E30: 2 | F30: weeks | G30: Lightweight delivery assumption, not guarantee | H30: =INDEX(C30:E30,1,MATCH('Start Here'!$B$5,$C$5:$E$5,0)) -> 2

Sheet Sources
A1: Cost catalog and public source register
A2: Research access/attempt date is recorded, not inferred. Unavailable primary pages remain unverified. Selected allowances are not vendor quotes; public wage surveys are not startup hiring rates.
A3: ← Start Here
A5: Source ID | B5: Publisher | C5: Product / role | D5: Exact public URL | E5: Access / attempt | F5: Effective / survey | G5: Currency | H5: Region | I5: Unit | J5: Public benchmark | K5: Selected allowance | L5: Evidence status | M5: Confidence | N5: Rationale | O5: Exclusions | P5: Refresh by
A6: ASSUMPTION | B6: Planning model | C6: Selected allowances and compensation | E6: 2026-10-20 | F6: Model dated 2026-10-20 | G6: USD | H6: US hiring / candidate East US infrastructure | I6: See each cost or assumption row | L6: Planning allowance | M6: Low | N6: Explicit editable judgment, not proprietary spending or vendor quote. US hiring basis is not founder location preference. | O6: Taxes, financing costs, negotiated agreements, current hiring offers | P6: Before budget approval
A7: BLS-DEV | B7: US Bureau of Labor Statistics | C7: Software developers, national median wage | D7: https://www.bls.gov/ooh/computer-and-information-technology/software-developers.htm | E7: 2026-10-20 | F7: May 2024 historical figure supplied in task; newer survey not verified | G7: USD | H7: US national | I7: employee annual wage | J7: 133080 | L7: Unverified | M7: Historical context only | N7: Primary retrieval DNS blocked. $133,080 historical benchmark is not labeled latest or verified here. Selected engineering salaries are separate role assumptions. | O7: Seniority, startup premium, equity, contractor rates, benefits | P7: Before hiring; retrieve latest primary OEWS/OOH
A8: BLS-QA | B8: US Bureau of Labor Statistics | C8: Software QA analysts/testers SOC 15-1253 | D8: https://www.bls.gov/oes/current/oes151253.htm | E8: 2026-10-20 | F8: Survey year unavailable; retrieval blocked | G8: USD | H8: US national | I8: employee annual wage | K8: 110000 | L8: Unverified | M8: Low | N8: No current figure verified. $110,000 is a selected salary assumption, not BLS data. | O8: Seniority, location, benefits, contractor billing | P8: Before hiring
A9: BLS-BENEFITS | B9: US Bureau of Labor Statistics | C9: Employer Costs for Employee Compensation | D9: https://www.bls.gov/charts/employer-costs-for-employee-compensation/costs-per-hour.htm | E9: 2026-10-20 | F9: Reference quarter unverified; retrieval blocked | G9: USD | H9: US; choose private industry consistently | I9: benefits / wages ratio | K9: 0.4 | L9: Unverified | M9: Low | N9: 40% of wages is a selected all-in employer burden allowance. Correct conversion: benefits/wages, or share_of_total/(1-share_of_total). Broad-industry figures are not startup quotes. | O9: Do not add payroll tax again if already in burden; equity and equipment separate | P9: Before budget approval
A10: GITHUB | B10: GitHub | C10: Team (Enterprise alternative not selected) | D10: https://github.com/pricing | E10: 2026-10-20 | F10: Displayed on access date; effective-from date not stated | G10: USD | H10: Public USD display; no regional variation established | I10: user/month | J10: 4 | K10: 4 | L10: Published price | M10: Medium | N10: Primary HTML retrieved: Team $4/user/month; Enterprise starts $21/user/month, NOT charged. Annual-price section says first 12 months. Model holds selected rate with inflation; renewal must be confirmed. | O10: Tax, promotions/renewal changes, Actions overages, security add-ons, Copilot; separate allowance row covers incremental CI/security | P10: Before purchase / annually
A11: AZURE-APP | B11: Microsoft Azure | C11: Linux App Service candidate | D11: https://azure.microsoft.com/en-us/pricing/details/app-service/linux/ | E11: 2026-10-20 | F11: Unverified; primary retrieval DNS blocked | G11: USD | H11: East US modeled candidate | I11: monthly pooled environment allowance | K11: 400 | L11: Quote required | M11: Low | N11: No SKU/meter verified. $400 is explicit dev/stage/prod application allowance, not public retail price. App Service Linux sizing must be quoted. | O11: Exact instance-hours, replicas, reserved discounts and eligibility unresolved | P11: Architecture gate
A12: AZURE-PG | B12: Microsoft Azure | C12: PostgreSQL Flexible Server | D12: https://azure.microsoft.com/en-us/pricing/details/postgresql/flexible-server/ | E12: 2026-10-20 | F12: URL cataloged; price not retrieved or verified | G12: USD | H12: East US modeled candidate | I12: monthly pooled DB allowance | K12: 600 | L12: Quote required | M12: Low | N12: Primary+HA standby production and smaller nonprod modeled; no SKU or meter price verified. Compute/storage/backup and HA quote required. | O12: No assertion that cheap tiers qualify for healthcare; BAA/service eligibility review required | P12: Architecture gate
A13: AZURE-RETAIL | B13: Microsoft Azure | C13: Official Retail Prices API research attempt | D13: https://prices.azure.com/api/retail/prices?currencyCode=%27USD%27&$filter=armRegionName%20eq%20%27eastus%27%20and%20serviceName%20eq%20%27Azure%20App%20Service%27%20and%20priceType%20eq%20%27Consumption%27 | E13: 2026-10-20 | F13: No API response obtained | G13: USD | H13: eastus filter | I13: SKU/meter dependent | L13: Unverified | M13: Unavailable | N13: Exact attempted filter retained; DNS blocked. No meter, unitOfMeasure or effectiveStartDate retrieved. Do not infer current price. | O13: Pagination, tiers, OS and reservation filtering require verification on successful retrieval | P13: Before commitments
A14: AWS | B14: Amazon Web Services | C14: App Runner + RDS PostgreSQL Multi-AZ alternative | D14: https://aws.amazon.com/rds/postgresql/pricing/ | E14: 2026-10-20 | F14: Reference URL only; not fetched | G14: USD | H14: US East modeled alternative; region to select | I14: monthly pooled app/DB allowance | K14: 1100 | L14: Quote required | M14: Low | N14: Mutually exclusive comparison allowance, not AWS retail price. Match HA/nonprod/storage/egress/contract terms before selection. | O14: App Runner pricing separate; bundled number is judgment, no negotiated discounts | P14: Architecture decision
A15: AI-PRICE | B15: OpenAI (candidate only) | C15: Optional GPT-4.1-mini candidate; no provider approved | D15: https://openai.com/api/pricing/ | E15: 2026-10-20 | F15: Unverified; DNS blocked | G15: USD | H15: Provider processing region unresolved | I15: USD/million input or output tokens | L15: Unverified | M15: Low | N15: Model selects provisional 0.40 input / 1.60 output per million tokens solely as editable allowances. NOT verified prices. AI disabled by default; confirm model availability, exact version, rates and tools before enablement. | O15: Tools, caching, fine-tuning, storage, evaluation labor, privacy eligibility and contracts | P15: Before AI gate
A16: AI-PRIVACY | B16: OpenAI (candidate only) | C16: API data controls / provider due diligence | D16: https://platform.openai.com/docs/guides/your-data | E16: 2026-10-20 | F16: Unverified; retrieval blocked | G16: USD | H16: Unresolved | I16: Non-price approval gate | L16: Unverified | M16: Unavailable | N16: No assurance of retention, zero-data-retention eligibility, regional processing, healthcare contractual coverage or allowed endpoints. Specialist approval before any sensitive data. | O16: Provider policy is not application compliance | P16: Before AI gate
A17: BLS-MANAGER | B17: US Bureau of Labor Statistics | C17: Computer/information systems managers SOC 11-3021 | D17: https://www.bls.gov/oes/current/oes113021.htm | E17: 2026-10-20 | F17: Survey year unavailable; DNS blocked | G17: USD | H17: US national | I17: annual wage | L17: Unverified | M17: Low | N17: Potential management proxy; no current amount used. | O17: Founder opportunity cost is selected separately, not a BLS management rate | P17: Before hiring
A18: BLS-PROJECT | B18: US Bureau of Labor Statistics | C18: Project management specialists SOC 13-1082 | D18: https://www.bls.gov/oes/current/oes131082.htm | E18: 2026-10-20 | F18: Survey year unavailable; DNS blocked | G18: USD | H18: US national | I18: annual wage | L18: Unverified | M18: Low | N18: Project management is only a potential product-management proxy; no current amount verified. | O18: Not a startup product leader quote | P18: Before hiring
A19: BLS-DESIGN | B19: US Bureau of Labor Statistics | C19: Web/digital interface designers SOC 15-1255 | D19: https://www.bls.gov/oes/current/oes151255.htm | E19: 2026-10-20 | F19: Survey year unavailable; DNS blocked | G19: USD | H19: US national | I19: annual wage | K19: 130000 | L19: Unverified | M19: Low | N19: Selected annual designer retainer equivalent is an assumption, not BLS rate. | O19: Contractor overhead and agency quotes unresolved | P19: Before hiring
A20: BLS-SUPPORT | B20: US Bureau of Labor Statistics | C20: Customer service representatives SOC 43-4051 | D20: https://www.bls.gov/oes/current/oes434051.htm | E20: 2026-10-20 | F20: Survey year unavailable; DNS blocked | G20: USD | H20: US national | I20: annual wage | K20: 90000 | L20: Unverified | M20: Low | N20: Weak proxy: technical implementation/customer success differs from customer service. Selected salary is independent assumption. | O20: No customer-success market salary asserted | P20: Before hiring

Sheet Staffing
A1: Phased staffing | annual selected salaries and fractional capacity
A2: FTE bands are months 1–6 / 7–15 / 16–30 / 31–60. Headcount slots ≠ FTE or hiring promise. Contractor annual rates are selected retainer equivalents; no employee burden. Founder cash defaults off.
A3: ← Start Here
A5: Scenario | B5: Role ID | C5: Role / responsibility | D5: Engagement | E5: Scope | F5: Start month | G5: End month | H5: FTE M1–6 | I5: FTE M7–15 | J5: FTE M16–30 | K5: FTE M31–60 | L5: Selected annual USD | M5: Benchmark ID | N5: Employer burden / wages | O5: Recruit / added FTE | P5: Equipment / added FTE
A6: Lean | B6: FOUNDER | C6: Founder / product / clinical lead | D6: Founder | E6: Core | F6: 1 | G6: 60 | H6: 0.75 | I6: 0.75 | J6: 0.75 | K6: 0.75 | L6: =Assumptions!$C$26 -> 150000 | M6: ASSUMPTION | N6: 0 | O6: 0 | P6: =Assumptions!$C$28 -> 2500
A7: Lean | B7: LEAD | C7: Tech lead / full stack | D7: Employee | E7: Core | F7: 1 | G7: 60 | H7: 1 | I7: 1 | J7: 1 | K7: 1 | L7: 165000 | M7: BLS-DEV | N7: =Assumptions!$C$11 -> 0.4 | O7: =Assumptions!$C$27 -> 5000 | P7: =Assumptions!$C$28 -> 2500
A8: Lean | B8: BACKEND | C8: Backend / tenant API / data migration | D8: Employee | E8: Core | F8: 4 | G8: 60 | H8: 0.5 | I8: 0.75 | J8: 1 | K8: 1 | L8: 145000 | M8: BLS-DEV | N8: =Assumptions!$C$11 -> 0.4 | O8: =Assumptions!$C$27 -> 5000 | P8: =Assumptions!$C$28 -> 2500
A9: Lean | B9: FRONTEND | C9: Frontend / mobile workflows | D9: Employee | E9: Core | F9: 7 | G9: 60 | H9: 0 | I9: 0.5 | J9: 0.75 | K9: 1 | L9: 140000 | M9: BLS-DEV | N9: =Assumptions!$C$11 -> 0.4 | O9: =Assumptions!$C$27 -> 5000 | P9: =Assumptions!$C$28 -> 2500
A10: Lean | B10: QA | C10: QA automation / migration reconciliation | D10: Employee | E10: Core | F10: 5 | G10: 60 | H10: 0.25 | I10: 0.5 | J10: 0.75 | K10: 1 | L10: 110000 | M10: BLS-QA | N10: =Assumptions!$C$11 -> 0.4 | O10: =Assumptions!$C$27 -> 5000 | P10: =Assumptions!$C$28 -> 2500
A11: Lean | B11: OPS | C11: DevOps / security engineering | D11: Fractional contractor | E11: Core | F11: 2 | G11: 60 | H11: 0.15 | I11: 0.2 | J11: 0.25 | K11: 0.5 | L11: 190000 | M11: BLS-DEV | N11: 0 | O11: 0 | P11: =Assumptions!$C$28 -> 2500
A12: Lean | B12: DESIGN | C12: Product design / accessibility | D12: Fractional contractor | E12: Core | F12: 2 | G12: 24 | H12: 0.15 | I12: 0.15 | J12: 0.1 | K12: 0 | L12: 130000 | M12: ASSUMPTION | N12: 0 | O12: 0 | P12: =Assumptions!$C$28 -> 2500
A13: Lean | B13: VALIDATION | C13: Compliance / legal / validation owner | D13: Fractional contractor | E13: Core | F13: 2 | G13: 60 | H13: 0.1 | I13: 0.15 | J13: 0.15 | K13: 0.2 | L13: 200000 | M13: ASSUMPTION | N13: 0 | O13: 0 | P13: =Assumptions!$C$28 -> 2500
A14: Lean | B14: SUCCESS | C14: Implementation / customer success / support | D14: Employee | E14: Core | F14: 12 | G14: 60 | H14: 0 | I14: 0.25 | J14: 0.5 | K14: 1 | L14: 90000 | M14: ASSUMPTION | N14: =Assumptions!$C$11 -> 0.4 | O14: =Assumptions!$C$27 -> 5000 | P14: =Assumptions!$C$28 -> 2500
A15: Lean | B15: SALES | C15: Sales / partnerships (no commission forecast) | D15: Employee | E15: Core | F15: 25 | G15: 60 | H15: 0 | I15: 0 | J15: 0.25 | K15: 0.5 | L15: 120000 | M15: ASSUMPTION | N15: =Assumptions!$C$11 -> 0.4 | O15: =Assumptions!$C$27 -> 5000 | P15: =Assumptions!$C$28 -> 2500
A16: Lean | B16: AI-ENG | C16: Optional AI / data evaluation engineer | D16: Employee | E16: AI | F16: 19 | G16: 60 | H16: 0 | I16: 0 | J16: 0.5 | K16: 0.5 | L16: 170000 | M16: BLS-DEV | N16: =Assumptions!$C$11 -> 0.4 | O16: =Assumptions!$C$27 -> 5000 | P16: =Assumptions!$C$28 -> 2500
A17: Lean | B17: CTMS-PM | C17: Optional research operations / CTMS domain lead | D17: Fractional contractor | E17: CTMS | F17: 31 | G17: 60 | H17: 0 | I17: 0 | J17: 0 | K17: 0.5 | L17: 180000 | M17: ASSUMPTION | N17: 0 | O17: 0 | P17: =Assumptions!$C$28 -> 2500
A18: Lean | B18: CTMS-ENG | C18: Optional CTMS integrations / research validation | D18: Employee | E18: CTMS | F18: 31 | G18: 60 | H18: 0 | I18: 0 | J18: 0 | K18: 0.5 | L18: 155000 | M18: BLS-DEV | N18: =Assumptions!$C$11 -> 0.4 | O18: =Assumptions!$C$27 -> 5000 | P18: =Assumptions!$C$28 -> 2500
A19: Base | B19: FOUNDER | C19: Founder / product / clinical lead | D19: Founder | E19: Core | F19: 1 | G19: 60 | H19: 1 | I19: 1 | J19: 1 | K19: 1 | L19: =Assumptions!$D$26 -> 180000 | M19: ASSUMPTION | N19: 0 | O19: 0 | P19: =Assumptions!$D$28 -> 3000
A20: Base | B20: LEAD | C20: Tech lead / full stack | D20: Employee | E20: Core | F20: 1 | G20: 60 | H20: 1 | I20: 1 | J20: 1 | K20: 1 | L20: 165000 | M20: BLS-DEV | N20: =Assumptions!$D$11 -> 0.4 | O20: =Assumptions!$D$27 -> 8000 | P20: =Assumptions!$D$28 -> 3000
A21: Base | B21: BACKEND | C21: Backend / tenant API / data migration | D21: Employee | E21: Core | F21: 3 | G21: 60 | H21: 1 | I21: 1 | J21: 2 | K21: 2 | L21: 145000 | M21: BLS-DEV | N21: =Assumptions!$D$11 -> 0.4 | O21: =Assumptions!$D$27 -> 8000 | P21: =Assumptions!$D$28 -> 3000
A22: Base | B22: FRONTEND | C22: Frontend / mobile workflows | D22: Employee | E22: Core | F22: 4 | G22: 60 | H22: 0.5 | I22: 1 | J22: 1 | K22: 2 | L22: 140000 | M22: BLS-DEV | N22: =Assumptions!$D$11 -> 0.4 | O22: =Assumptions!$D$27 -> 8000 | P22: =Assumptions!$D$28 -> 3000
A23: Base | B23: QA | C23: QA automation / migration reconciliation | D23: Employee | E23: Core | F23: 4 | G23: 60 | H23: 0.5 | I23: 0.75 | J23: 1 | K23: 2 | L23: 110000 | M23: BLS-QA | N23: =Assumptions!$D$11 -> 0.4 | O23: =Assumptions!$D$27 -> 8000 | P23: =Assumptions!$D$28 -> 3000
A24: Base | B24: OPS | C24: DevOps / security engineering | D24: Fractional contractor | E24: Core | F24: 2 | G24: 60 | H24: 0.25 | I24: 0.5 | J24: 0.75 | K24: 1 | L24: 190000 | M24: BLS-DEV | N24: 0 | O24: 0 | P24: =Assumptions!$D$28 -> 3000
A25: Base | B25: DESIGN | C25: Product design / accessibility | D25: Fractional contractor | E25: Core | F25: 2 | G25: 36 | H25: 0.25 | I25: 0.25 | J25: 0.25 | K25: 0.25 | L25: 130000 | M25: ASSUMPTION | N25: 0 | O25: 0 | P25: =Assumptions!$D$28 -> 3000
A26: Base | B26: VALIDATION | C26: Compliance / legal / validation owner | D26: Fractional contractor | E26: Core | F26: 2 | G26: 60 | H26: 0.15 | I26: 0.25 | J26: 0.25 | K26: 0.5 | L26: 200000 | M26: ASSUMPTION | N26: 0 | O26: 0 | P26: =Assumptions!$D$28 -> 3000
A27: Base | B27: SUCCESS | C27: Implementation / customer success / support | D27: Employee | E27: Core | F27: 10 | G27: 60 | H27: 0 | I27: 0.5 | J27: 1 | K27: 2 | L27: 90000 | M27: ASSUMPTION | N27: =Assumptions!$D$11 -> 0.4 | O27: =Assumptions!$D$27 -> 8000 | P27: =Assumptions!$D$28 -> 3000
A28: Base | B28: SALES | C28: Sales / partnerships (no commission forecast) | D28: Employee | E28: Core | F28: 19 | G28: 60 | H28: 0 | I28: 0 | J28: 0.5 | K28: 1 | L28: 120000 | M28: ASSUMPTION | N28: =Assumptions!$D$11 -> 0.4 | O28: =Assumptions!$D$27 -> 8000 | P28: =Assumptions!$D$28 -> 3000
A29: Base | B29: AI-ENG | C29: Optional AI / data evaluation engineer | D29: Employee | E29: AI | F29: 16 | G29: 60 | H29: 0 | I29: 0 | J29: 0.75 | K29: 1 | L29: 170000 | M29: BLS-DEV | N29: =Assumptions!$D$11 -> 0.4 | O29: =Assumptions!$D$27 -> 8000 | P29: =Assumptions!$D$28 -> 3000
A30: Base | B30: CTMS-PM | C30: Optional research operations / CTMS domain lead | D30: Fractional contractor | E30: CTMS | F30: 25 | G30: 60 | H30: 0 | I30: 0 | J30: 0.5 | K30: 1 | L30: 180000 | M30: ASSUMPTION | N30: 0 | O30: 0 | P30: =Assumptions!$D$28 -> 3000
A31: Base | B31: CTMS-ENG | C31: Optional CTMS integrations / research validation | D31: Employee | E31: CTMS | F31: 25 | G31: 60 | H31: 0 | I31: 0 | J31: 0.5 | K31: 1 | L31: 155000 | M31: BLS-DEV | N31: =Assumptions!$D$11 -> 0.4 | O31: =Assumptions!$D$27 -> 8000 | P31: =Assumptions!$D$28 -> 3000
A32: Growth | B32: FOUNDER | C32: Founder / product / clinical lead | D32: Founder | E32: Core | F32: 1 | G32: 60 | H32: 1 | I32: 1 | J32: 1 | K32: 1 | L32: =Assumptions!$E$26 -> 200000 | M32: ASSUMPTION | N32: 0 | O32: 0 | P32: =Assumptions!$E$28 -> 3500
A33: Growth | B33: LEAD | C33: Tech lead / full stack | D33: Employee | E33: Core | F33: 1 | G33: 60 | H33: 1 | I33: 1 | J33: 1 | K33: 1 | L33: 165000 | M33: BLS-DEV | N33: =Assumptions!$E$11 -> 0.4 | O33: =Assumptions!$E$27 -> 12000 | P33: =Assumptions!$E$28 -> 3500
A34: Growth | B34: BACKEND | C34: Backend / tenant API / data migration | D34: Employee | E34: Core | F34: 2 | G34: 60 | H34: 1 | I34: 2 | J34: 3 | K34: 4 | L34: 145000 | M34: BLS-DEV | N34: =Assumptions!$E$11 -> 0.4 | O34: =Assumptions!$E$27 -> 12000 | P34: =Assumptions!$E$28 -> 3500
A35: Growth | B35: FRONTEND | C35: Frontend / mobile workflows | D35: Employee | E35: Core | F35: 3 | G35: 60 | H35: 1 | I35: 1 | J35: 2 | K35: 3 | L35: 140000 | M35: BLS-DEV | N35: =Assumptions!$E$11 -> 0.4 | O35: =Assumptions!$E$27 -> 12000 | P35: =Assumptions!$E$28 -> 3500
A36: Growth | B36: QA | C36: QA automation / migration reconciliation | D36: Employee | E36: Core | F36: 3 | G36: 60 | H36: 0.5 | I36: 1 | J36: 2 | K36: 3 | L36: 110000 | M36: BLS-QA | N36: =Assumptions!$E$11 -> 0.4 | O36: =Assumptions!$E$27 -> 12000 | P36: =Assumptions!$E$28 -> 3500
A37: Growth | B37: OPS | C37: DevOps / security engineering | D37: Fractional contractor | E37: Core | F37: 2 | G37: 60 | H37: 0.5 | I37: 0.75 | J37: 1 | K37: 2 | L37: 190000 | M37: BLS-DEV | N37: 0 | O37: 0 | P37: =Assumptions!$E$28 -> 3500
A38: Growth | B38: DESIGN | C38: Product design / accessibility | D38: Fractional contractor | E38: Core | F38: 2 | G38: 60 | H38: 0.5 | I38: 0.5 | J38: 0.75 | K38: 1 | L38: 130000 | M38: ASSUMPTION | N38: 0 | O38: 0 | P38: =Assumptions!$E$28 -> 3500
A39: Growth | B39: VALIDATION | C39: Compliance / legal / validation owner | D39: Fractional contractor | E39: Core | F39: 2 | G39: 60 | H39: 0.25 | I39: 0.5 | J39: 0.75 | K39: 1 | L39: 200000 | M39: ASSUMPTION | N39: 0 | O39: 0 | P39: =Assumptions!$E$28 -> 3500
A40: Growth | B40: SUCCESS | C40: Implementation / customer success / support | D40: Employee | E40: Core | F40: 9 | G40: 60 | H40: 0 | I40: 1 | J40: 2 | K40: 4 | L40: 90000 | M40: ASSUMPTION | N40: =Assumptions!$E$11 -> 0.4 | O40: =Assumptions!$E$27 -> 12000 | P40: =Assumptions!$E$28 -> 3500
A41: Growth | B41: SALES | C41: Sales / partnerships (no commission forecast) | D41: Employee | E41: Core | F41: 16 | G41: 60 | H41: 0 | I41: 0 | J41: 1 | K41: 3 | L41: 120000 | M41: ASSUMPTION | N41: =Assumptions!$E$11 -> 0.4 | O41: =Assumptions!$E$27 -> 12000 | P41: =Assumptions!$E$28 -> 3500
A42: Growth | B42: AI-ENG | C42: Optional AI / data evaluation engineer | D42: Employee | E42: AI | F42: 16 | G42: 60 | H42: 0 | I42: 1 | J42: 1 | K42: 2 | L42: 170000 | M42: BLS-DEV | N42: =Assumptions!$E$11 -> 0.4 | O42: =Assumptions!$E$27 -> 12000 | P42: =Assumptions!$E$28 -> 3500
A43: Growth | B43: CTMS-PM | C43: Optional research operations / CTMS domain lead | D43: Fractional contractor | E43: CTMS | F43: 25 | G43: 60 | H43: 0 | I43: 0 | J43: 1 | K43: 1 | L43: 180000 | M43: ASSUMPTION | N43: 0 | O43: 0 | P43: =Assumptions!$E$28 -> 3500
A44: Growth | B44: CTMS-ENG | C44: Optional CTMS integrations / research validation | D44: Employee | E44: CTMS | F44: 25 | G44: 60 | H44: 0 | I44: 0 | J44: 1 | K44: 2 | L44: 155000 | M44: BLS-DEV | N44: =Assumptions!$E$11 -> 0.4 | O44: =Assumptions!$E$27 -> 12000 | P44: =Assumptions!$E$28 -> 3500

Sheet Nonlabor
A1: Non-labor cash catalog | stable cost IDs
A2: Only one cloud stack charged. Annual items recur start+12n; Once items occur once. Optional items start at MAX(catalog start, scenario expansion start). Salary is only in Staffing; WBS labor is informational.
A3: ← Start Here
A5: Cost ID | B5: Category | C5: Line item | D5: Stack | E5: Scope | F5: Start | G5: End | H5: Frequency | I5: Quantity driver | J5: Selected rate USD | K5: Source ID | L5: Evidence status | M5: Caveat / exclusions | N5: Active unresolved line
A6: INFRA-APP | B6: INFRA | C6: API / worker / frontend managed app allowance | D6: Azure | E6: Core | F6: 1 | G6: 60 | H6: Monthly | I6: Fixed | J6: 400 | K6: AZURE-APP | L6: Quote required | M6: App Service candidate; dev/stage/prod pooled allowance, not an SKU quote | N6: =IF(AND(OR(D6="Both",D6='Start Here'!$B$9),IF(E6="Core",1,IF(E6="AI",'Start Here'!$B$7,'Start Here'!$B$8))=1,OR(L6="Quote required",L6="Unverified")),1,0) -> 1
A7: INFRA-DB | B7: INFRA | C7: Managed PostgreSQL HA + nonprod allowance | D7: Azure | E7: Core | F7: 1 | G7: 60 | H7: Monthly | I7: Fixed | J7: 600 | K7: AZURE-PG | L7: Quote required | M7: Flexible Server candidate; production primary + HA standby, nonprod smaller; backups separate | N7: =IF(AND(OR(D7="Both",D7='Start Here'!$B$9),IF(E7="Core",1,IF(E7="AI",'Start Here'!$B$7,'Start Here'!$B$8))=1,OR(L7="Quote required",L7="Unverified")),1,0) -> 1
A8: INFRA-AWS | B8: INFRA | C8: Alternative AWS app + PostgreSQL HA bundle | D8: AWS | E8: Core | F8: 1 | G8: 60 | H8: Monthly | I8: Fixed | J8: 1100 | K8: AWS | L8: Quote required | M8: Mutually exclusive Azure app/DB; App Runner + RDS Multi-AZ candidate, not quote | N8: =IF(AND(OR(D8="Both",D8='Start Here'!$B$9),IF(E8="Core",1,IF(E8="AI",'Start Here'!$B$7,'Start Here'!$B$8))=1,OR(L8="Quote required",L8="Unverified")),1,0) -> 0
A9: INFRA-EDGE | B9: INFRA | C9: WAF/CDN, identity, DNS and transactional email | D9: Both | E9: Core | F9: 1 | G9: 60 | H9: Monthly | I9: Fixed | J9: 250 | K9: ASSUMPTION | L9: Quote required | M9: Includes minimum identity/email allowance; eligibility and MAU tiers to quote | N9: =IF(AND(OR(D9="Both",D9='Start Here'!$B$9),IF(E9="Core",1,IF(E9="AI",'Start Here'!$B$7,'Start Here'!$B$8))=1,OR(L9="Quote required",L9="Unverified")),1,0) -> 1
A10: INFRA-STORE | B10: INFRA | C10: Object storage / backups / egress | D10: Both | E10: Core | F10: 1 | G10: 60 | H10: Monthly | I10: StorageGB | J10: 0.15 | K10: ASSUMPTION | L10: Planning allowance | M10: Blended selected rate, no claim of Azure/AWS retail storage price | N10: =IF(AND(OR(D10="Both",D10='Start Here'!$B$9),IF(E10="Core",1,IF(E10="AI",'Start Here'!$B$7,'Start Here'!$B$8))=1,OR(L10="Quote required",L10="Unverified")),1,0) -> 0
A11: INFRA-LOG | B11: INFRA | C11: Logs / queues / secrets / metrics | D11: Both | E11: Core | F11: 1 | G11: 60 | H11: Monthly | I11: LogGB | J11: 5 | K11: ASSUMPTION | L11: Planning allowance | M11: Blended usage rate; privacy filters, retention and ingestion caps required | N11: =IF(AND(OR(D11="Both",D11='Start Here'!$B$9),IF(E11="Core",1,IF(E11="AI",'Start Here'!$B$7,'Start Here'!$B$8))=1,OR(L11="Quote required",L11="Unverified")),1,0) -> 0
A12: INFRA-REQ | B12: INFRA | C12: Capacity growth reserve per million API requests | D12: Both | E12: Core | F12: 1 | G12: 60 | H12: Monthly | I12: RequestsM | J12: 30 | K12: ASSUMPTION | L12: Planning allowance | M12: Capacity reserve not serverless quote; load test before resize | N12: =IF(AND(OR(D12="Both",D12='Start Here'!$B$9),IF(E12="Core",1,IF(E12="AI",'Start Here'!$B$7,'Start Here'!$B$8))=1,OR(L12="Quote required",L12="Unverified")),1,0) -> 0
A13: TOOLS-GH | B13: TOOLS | C13: GitHub Team seats (only selected plan) | D13: Both | E13: Core | F13: 1 | G13: 60 | H13: Monthly | I13: Seats | J13: 4 | K13: GITHUB | L13: Published price | M13: Public starting price; promotions/taxes/CI allowances not assumed perpetual | N13: =IF(AND(OR(D13="Both",D13='Start Here'!$B$9),IF(E13="Core",1,IF(E13="AI",'Start Here'!$B$7,'Start Here'!$B$8))=1,OR(L13="Quote required",L13="Unverified")),1,0) -> 0
A14: TOOLS-CI | B14: TOOLS | C14: Incremental CI, dependency scan, secrets and security tools | D14: Both | E14: Core | F14: 1 | G14: 60 | H14: Monthly | I14: Seats | J14: 45 | K14: ASSUMPTION | L14: Planning allowance | M14: Above included plan limits; no Copilot or enterprise plan implicitly charged | N14: =IF(AND(OR(D14="Both",D14='Start Here'!$B$9),IF(E14="Core",1,IF(E14="AI",'Start Here'!$B$7,'Start Here'!$B$8))=1,OR(L14="Quote required",L14="Unverified")),1,0) -> 0
A15: LEGAL-SETUP | B15: LEGAL | C15: Privacy, DPA, BAA, terms, company and IP contracts | D15: Both | E15: Core | F15: 2 | G15: 2 | H15: Once | I15: Fixed | J15: 20000 | K15: ASSUMPTION | L15: Quote required | M15: External counsel deliverables, not duplicate embedded validation staff | N15: =IF(AND(OR(D15="Both",D15='Start Here'!$B$9),IF(E15="Core",1,IF(E15="AI",'Start Here'!$B$7,'Start Here'!$B$8))=1,OR(L15="Quote required",L15="Unverified")),1,0) -> 1
A16: LEGAL-RENEW | B16: LEGAL | C16: External legal contract review retainer | D16: Both | E16: Core | F16: 14 | G16: 60 | H16: Annual | I16: Fixed | J16: 12000 | K16: ASSUMPTION | L16: Quote required | M16: Annual renewal at start+12n; legal applicability not guaranteed | N16: =IF(AND(OR(D16="Both",D16='Start Here'!$B$9),IF(E16="Core",1,IF(E16="AI",'Start Here'!$B$7,'Start Here'!$B$8))=1,OR(L16="Quote required",L16="Unverified")),1,0) -> 1
A17: SECURITY-TEST | B17: SECURITY | C17: Independent penetration test + retest | D17: Both | E17: Core | F17: 10 | G17: 60 | H17: Annual | I17: Fixed | J17: 18000 | K17: ASSUMPTION | L17: Quote required | M17: Independent assessment, not engineering labor | N17: =IF(AND(OR(D17="Both",D17='Start Here'!$B$9),IF(E17="Core",1,IF(E17="AI",'Start Here'!$B$7,'Start Here'!$B$8))=1,OR(L17="Quote required",L17="Unverified")),1,0) -> 1
... A27: CTMS-EXT | B27: CTMS | C27: Optional research systems validation and integration contracts | D27: Both | E27: CTMS | F27: 1 | G27: 60 | H27: Annual | I27: Fixed | J27: 40000 | K27: ASSUMPTION | L27: Quote required | M27: First at CTMS start; study/site/EDC/eTMF scope, not patient relabeling | N27: =IF(AND(OR(D27="Both",D27='Start Here'!$B$9),IF(E27="Core",1,IF(E27="AI",'Start Here'!$B$7,'Start Here'!$B$8))=1,OR(L27="Quote required",L27="Unverified")),1,0) -> 0

Sheet Requirements
A1: Requirements and evidence register
A2: Repository presence = Implemented, not Verified or In customer use. Successful M365 PoC is user-reported; no deployment verification performed.
A3: ← Start Here
A5: Id | B5: Heading | C5: Item | D5: Evidence | E5: Status | F5: Caveat | G5: Requirement | H5: Acceptance | I5: Priority | J5: Phase | K5: Owner | L5: Dependency | M5: Scope | N5: Wbs | O5: Cost
A6: R1.1 | B6: 1. Product / current baseline | C6: 1.1 Census, encounters, findings, procedures, STAT, handoff and history | D6: clinical-rounding-adaptive.html: openModal, savePatient, renderMainTable, generateHandoff; USP.md | E6: Implemented | F6: Code/documentation present; no running deployment or customer-use verification here. | G6: Preserve core rounding behavior through characterization and clinical acceptance. | H6: Synthetic golden journeys; visit history/backfeed excludes fresh findings; clinician sign-off. | I6: P0 | J6: Assess | K6: Founder / QA | L6: None | M6: Core | N6: W1.1 | O6: STAFF
A7: R1.2 | B7: 1. Product / source of truth | C7: 1.2 Canonical source and release inventory | D7: README.md; AGENTS.md; .github/copilot-instructions.md; release/; azure-integration.js; clinical-rounding-adaptive.html.orig/.rej | E7: Implemented | F7: Firebase-era instructions conflict with newer browser-MSAL-Graph-M365 description. Root/release duplicates and Azure alternative are not interchangeable. | G7: Record canonical product/version, alternatives and supported artifact manifest. | H7: Approved inventory and diff; no changes to PoC during planning; one future release source of truth. | I7: P0 | J7: Assess | K7: Tech lead | L7: R1.1 | M7: Core | N7: W1.2 | O7: STAFF
A8: R1.3 | B8: 1. Product / customers | C8: 1.3 Intended use, buyer and commercial scope | D8: USP.md; README.md; documents/exec-brief/Clinical-Roundup-CTMS-Exec-Brief.md | E8: Idea | F8: User reports successful M365 PoC; this is not evidence of paid demand or CTMS readiness. | G8: Choose specialty-practice rounding wedge; define exclusions, pilot agreement and success criteria. | H8: Buyer interviews, named decision-maker, clinical safety review, pilot acceptance contract; no valuation target. | I8: P0 | J8: Assess | K8: Founder / clinical lead | L8: R1.1 | M8: Core | N8: W1.3 | O8: STAFF
A9: R2.1 | B9: 2. Refactor / frontend | C9: 2.1 Extract UI and domain modules | D9: clinical-rounding-adaptive.html: savePatient, renderUI, setTab, Device; import-engine.js | E9: Idea | F9: Large single-file app is reusable behavior, not an established modular SaaS codebase. | G9: Extract forms/domain services, typed API boundary and mobile components incrementally; framework decision after spike. | H9: Characterization regressions pass; accessible phone/tablet flows, no PHI in fixtures. | I9: P0 | J9: Foundation | K9: Tech lead / frontend | L9: R1.1 | M9: Core | N9: W2.1 | O9: STAFF
A10: R2.2 | B10: 2. Refactor / services | C10: 2.2 Server API, contracts and authorization | D10: api/patients/index.js; api/backfeed/index.js; api/settings/index.js; api/onCallSchedule/index.js; api/export/index.js; api/shared/dataService.js; staticwebapp.config.json | E10: Implemented | F10: API alternative has role checks and Graph access; runtime trust boundary and deployment not verified. Not a proven SaaS backend. | G10: Validate requests, trusted identity and tenant-scoped access server-side; contract/version tests, idempotency and optimistic concurrency. | H10: Cross-tenant negative tests on every method including export; malformed requests denied; replay/concurrency tests; no header trust without gateway validation. | I10: P0 | J10: Foundation | K10: Backend / security | L10: R3.1 | M10: Core | N10: W2.2 | O10: STAFF
A11: R3.1 | B11: 3. Identity / tenant data | C11: 3.1 Organizations, membership, roles and boundaries | D11: m365-integration.js: M365_CONFIG, login, getAccessToken; api/patients/index.js | E11: Idea | F11: Single configured site/list and UI controls are not proof of commercial tenant isolation. | G11: Tenant lifecycle, verified organization membership, per-resource authorization, invitation/revocation and admin separation. | H11: Two synthetic tenants cannot enumerate/read/write/export each other; offboarding revokes access. | I11: P0 | J11: Foundation | K11: Backend / tech lead | L11: R1.3 | M11: Core | N11: W3.1 | O11: STAFF
A12: R3.2 | B12: 3. Identity / tenant data | C12: 3.2 Patient and encounter identity, schema and indexes | D12: m365-integration.js: api_savePatient computeVisitKey, resolvePatientItemIdByVisitKey; api/shared/dataService.js | E12: Implemented | F12: Current MRN/date-style VisitKey is not globally unique across organizations; hospital/source scope must be decided. | G12: Design tenant+source/facility-scoped patient IDs and encounter IDs; constraints, migrations, indexes and retention. | H12: Same MRN/date in two organizations remains isolated; multiple encounters/day policy; reversible migration and query plans. | I12: P0 | J12: Foundation | K12: Backend / data lead | L12: R3.1 | M12: Core | N12: W3.2 | O12: STAFF
A13: R3.3 | B13: 3. Identity / tenant data | C13: 3.3 Cache, offline, conflict and session policy | D13: m365-integration.js: startPolling, fetchAllData, localStorage cache, triggerServerSessionInvalidation; clinical-rounding-adaptive.html | E13: Implemented | F13: Polling/cache/session code presence does not prove isolation, revocation or privacy behavior. | G13: Explicit offline/PHI policy, tenant-aware cache purge, session timeout, conflict detection and safe retries. | H13: Shared-browser tenant switch, lost-device/logout/cache purge, expired session and stale write tests. | I13: P0 | J13: Foundation | K13: Frontend / security | L13: R3.1 | M13: Core | N13: W3.3 | O13: STAFF
A14: R4.1 | B14: 4. Migration / interoperability | C14: 4.1 SharePoint extraction and field mapping | D14: m365-integration.js: api_fetchPatients, api_savePatient, api_fetchOnCallSchedule, api_fetchSettings; api/shared/dataService.js | E14: Idea | F14: Graph/SharePoint field names, choices, dates, JSON findings and attachments must be mapped, not copied blindly. | G14: Version source schema manifest and export mapping; map internal field names/types/nulls/timezones/VisitKey to SaaS IDs. | H14: Synthetic sample export with findings/codes/values, archive, on-call, settings, document links; signed mapping and exceptions. | I14: P0 | J14: Foundation | K14: Backend / implementation | L14: R3.2 | M14: Core | N14: W4.1 | O14: STAFF
A15: R4.2 | B15: 4. Migration / interoperability | C15: 4.2 Import/export data integrity and documents | D15: import-engine.js; clinical-rounding-adaptive.html: previewBulkImport, proceedBulkImport; m365-integration.js: exportToOneDrive, api_uploadPatientFile, api_fetchPatientFiles | E15: Implemented | F15: Preview, bulk/resume and document paths require production-oriented validation, limits and authorization. | G15: Retain preview/dedup/resume semantics with server validation; tenant object storage, signed downloads, safe CSV/XLSX exports and malware policy. | H15: Synthetic duplicate/corrupt/large-file/retry tests; formula-injection controls; no cross-tenant document access or public PHI links. | I15: P0 | J15: Foundation | K15: Backend / QA | L15: R4.1 | M15: Core | N15: W4.2 | O15: STAFF
A16: R4.3 | B16: 4. Migration / interoperability | C16: 4.3 Rehearsal, reconciliation, cutover and rollback | D16: m365-integration.js; import-engine.js; docs/testing/E2E_TEST_RECORDS_MANUAL.txt | E16: Idea | F16: No evidence here of a verified migration runbook or lossless live cutover. | G16: Synthetic rehearsals; counts, canonical hashes and per-field reconciliation; staged tenant cutover with source write pause and rollback. | H16: 100% explained record/field exceptions; restore rehearsal; signed go/no-go, rollback trigger and elapsed window; no uncontrolled dual-write. | I16: P0 | J16: Synthetic pilot | K16: Implementation / backend / QA | L16: R4.2 | M16: Core | N16: W4.3 | O16: STAFF
... A26: R7.2 | B26: 7. Optional expansions | C26: 7.2 Trial operations intelligence / CTMS discovery | D26: documents/exec-brief/Clinical-Roundup-CTMS-Exec-Brief.md; AI_USP.md | E26: Idea | F26: CTMS is not patient relabeling. No trial-management capability or revenue assumed. | G26: Separate study/site/subject model, protocol and milestone workflows, permissions, sponsor/CRO buyer research, EDC/eTMF integrations and scope-specific validation/e-signatures. | H26: Research stakeholder validation, data/licensing agreements, intended-use and regulatory assessment, separate synthetic pilot and go/no-go investment case. | I26: Optional | J26: Expansion | K26: Research domain lead / integration / validation | L26: R6.5 | M26: CTMS | N26: W7.2 | O26: CTMS

Sheet Migration WBS
A1: Migration and refactoring WBS
A2: Effort is an assumed person-day range, not a separate engineering charge. STAFF references the staffing pool; no WBS labor added to financial totals. Freeze/write-pause cutover; no unqualified dual-write.
A3: ← Start Here
A5: Id | B5: Requirement | C5: Work | D5: Decision | E5: Evidence | F5: Effort Days | G5: Start | H5: End | I5: Owner | J5: Dependency | K5: Scope | L5: Cost | M5: Acceptance | N5: Low assumed days (−30%) | O5: High assumed days (+50%)
A6: W1.1 | B6: R1.1 | C6: Characterize rounding journeys and historical/backfeed semantics with synthetic fixtures | D6: Reuse behavior; verify before extraction | E6: clinical-rounding-adaptive.html; USP.md | F6: 25 | G6: 1 | H6: 3 | I6: Founder / QA | J6: None | K6: Core | L6: STAFF | M6: Golden workflow baseline signed | N6: =F6*0.7 -> 17.5 | O6: =F6*1.5 -> 37.5
A7: W1.2 | B7: R1.2 | C7: Inventory root/release and Azure/M365 alternatives; choose canonical app and release manifest | D7: Assess now; defer code cleanup until authorized migration | E7: README.md; AGENTS.md; release/; .github/copilot-instructions.md | F7: 8 | G7: 1 | H7: 2 | I7: Tech lead | J7: W1.1 | K7: Core | L7: STAFF | M7: Canonical-source decision record | N7: =F7*0.7 -> 5.6 | O7: =F7*1.5 -> 12
A8: W1.3 | B8: R1.3 | C8: Buyer discovery, intended-use scope and pilot acceptance criteria | D8: Reuse clinical wedge; defer CTMS and EHR connectors | E8: USP.md; documents/exec-brief/Clinical-Roundup-CTMS-Exec-Brief.md | F8: 20 | G8: 1 | H8: 3 | I8: Founder | J8: W1.1 | K8: Core | L8: STAFF | M8: Scope and pilot go/no-go | N8: =F8*0.7 -> 14 | O8: =F8*1.5 -> 30
A9: W2.1 | B9: R2.1 | C9: Extract domain/form/render services, establish API adapters, mobile accessibility regression | D9: Refactor incrementally, not a big-bang framework rewrite | E9: clinical-rounding-adaptive.html; import-engine.js | F9: 90 | G9: 4 | H9: 8 | I9: Frontend / tech lead | J9: W1.1 | K9: Core | L9: STAFF | M9: Core synthetic journeys preserved | N9: =F9*0.7 -> 63 | O9: =F9*1.5 -> 135
A10: W2.2 | B10: R2.2 | C10: API validation, trusted identity integration, server authorization, concurrency and contract tests | D10: Refactor API ideas; replace browser-direct data trust boundary | E10: api/*; api/shared/dataService.js; staticwebapp.config.json | F10: 75 | G10: 4 | H10: 8 | I10: Backend / security | J10: W3.1 | K10: Core | L10: STAFF | M10: Negative tenant tests and contract suite | N10: =F10*0.7 -> 52.5 | O10: =F10*1.5 -> 112.5
A11: W3.1 | B11: R3.1 | C11: Organization membership, invitations, role matrix and enforceable tenant query context | D11: Replace single-site tenancy assumptions | E11: m365-integration.js; api/patients/index.js | F11: 45 | G11: 3 | H11: 6 | I11: Backend / tech lead | J11: W1.3 | K11: Core | L11: STAFF | M11: Isolation design and two-tenant tests | N11: =F11*0.7 -> 31.5 | O11: =F11*1.5 -> 67.5
A12: W3.2 | B12: R3.2 | C12: Relational tenant/patient/encounter schema, constraints, migrations/indexes, archive policy | D12: Replace MRN/date global identity; retain source keys as mapped provenance | E12: m365-integration.js: api_savePatient; api/shared/dataService.js | F12: 45 | G12: 4 | H12: 7 | I12: Backend | J12: W3.1 | K12: Core | L12: STAFF | M12: Migration up/down, duplicate MRN tenant tests | N12: =F12*0.7 -> 31.5 | O12: =F12*1.5 -> 67.5
A13: W3.3 | B13: R3.3 | C13: Cache/session/offline policy, revocation, stale-write UX and safe retry semantics | D13: Refactor; offline PHI may be restricted rather than retained | E13: m365-integration.js: cache, polling, session invalidation | F13: 30 | G13: 5 | H13: 8 | I13: Frontend / security | J13: W3.1 | K13: Core | L13: STAFF | M13: Tenant switch/logout/offline tests | N13: =F13*0.7 -> 21 | O13: =F13*1.5 -> 45
A14: W4.1 | B14: R4.1 | C14: Extract SharePoint schema and snapshots; typed field mapping and source-to-target key map | D14: Reuse field knowledge; replace direct persistence mapping | E14: m365-integration.js; api/shared/dataService.js | F14: 25 | G14: 6 | H14: 8 | I14: Backend / implementation | J14: W3.2 | K14: Core | L14: STAFF | M14: Versioned mapping with exceptions | N14: =F14*0.7 -> 17.5 | O14: =F14*1.5 -> 37.5
A15: W4.2 | B15: R4.2 | C15: Import preview/dedup/resume and export parity; document store and scoped download access | D15: Reuse parser semantics; refactor job/storage execution | E15: import-engine.js; m365-integration.js: patient file APIs; clinical-rounding-adaptive.html | F15: 45 | G15: 6 | H15: 9 | I15: Backend / QA | J15: W4.1 | K15: Core | L15: STAFF | M15: Synthetic round-trip including attachments | N15: =F15*0.7 -> 31.5 | O15: =F15*1.5 -> 67.5
A16: W4.3 | B16: R4.3 | C16: Synthetic rehearsal, count/canonical-hash/field reconciliation, write-pause cutover and rollback drills | D16: New migration tooling; avoid uncontrolled dual-write | E16: m365-integration.js; docs/testing/* | F16: 35 | G16: 9 | H16: 11 | I16: QA / backend / implementation | J16: W4.2 | K16: Core | L16: STAFF | M16: Explained differences and timed rollback | N16: =F16*0.7 -> 24.5 | O16: =F16*1.5 -> 52.5
A17: W4.4 | B17: R4.4 | C17: Per-tenant source-of-record, PoC read-only coexistence/retirement and customer exit workflow | D17: Defer PoC deletion until retention/rollback sign-off | E17: README.md; release/; .github/workflows/deploy-to-pages.yml | F17: 15 | G17: 12 | H17: 15 | I17: Founder / success | J17: W4.3 | K17: Core | L17: STAFF | M17: Signed tenant handover and exit export | N17: =F17*0.7 -> 10.5 | O17: =F17*1.5 -> 22.5
... A26: W7.2 | B26: R7.2 | C26: Optional CTMS discovery, study/site model, research integrations and scope-dependent validation/e-signatures | D26: Defer by default; separate product case, not relabeling rounding | E26: documents/exec-brief/Clinical-Roundup-CTMS-Exec-Brief.md | F26: 180 | G26: 25 | H26: 42 | I26: Research domain / integration / validation | J26: W6.5 | K26: CTMS | L26: CTMS | M26: Research buyer evidence and independent go/no-go | N26: =F26*0.7 -> 126 | O26: =F26*1.5 -> 270

Sheet Architecture
A1: Architecture candidates | managed modular monolith
A2: Azure East US is a modeled candidate, not mandated. AWS US East managed alternative is mutually exclusive. All HA/retention/SKUs require sizing, eligibility review and quotes; no Kubernetes prerequisite.
A3: ← Start Here
A5: Id | B5: Component | C5: Azure | D5: Alternative | E5: Decision | F5: Driver | G5: Sku | H5: Region | I5: Allowance | J5: Ha | K5: Retention | L5: Trigger | M5: Effort Days | N5: Cost
A6: A1 | B6: Frontend / API / worker | C6: Static frontend + Linux App Service modular monolith; queue worker | D6: Static S3/CloudFront frontend + App Runner service/worker | E6: Mutually exclusive candidate stacks; framework chosen by spike, no Kubernetes prerequisite | F6: Environments, instances, measured request concurrency; RequestsM reserve | G6: App Service Linux SKU TBD / App Runner size TBD; quote required | H6: East US baseline; AWS US East alternate TBD | I6: INFRA-APP $400/month or INFRA-AWS pooled $1100; not SKU rates | J6: Proposed prod 2 app instances; smaller dev/stage; quote/review required | K6: No PHI in app logs; signed release artifacts | L6: Sustained p95/CPU/queue saturation against approved SLO | M6: 15 | N6: INFRA
A7: A2 | B7: Managed relational database | C7: PostgreSQL Flexible Server | D7: RDS PostgreSQL Multi-AZ | E7: Tenant IDs, constraints and query authorization; RLS defense-in-depth evaluated | F7: Compute, primary+standby, nonprod, provisioned GB and backup retention | G7: General Purpose candidate; vCPU/storage TBD, not Burstable assumed healthcare-ready | H7: East US / AWS US East TBD | I7: INFRA-DB $600/month or AWS bundle; actual quote unresolved | J7: Proposed production primary + HA standby; nonprod 1 smaller each | K7: Proposed 35-day point-in-time backup; long-term retention per approved policy | L7: DB saturation, storage growth, restore time or tenant isolation tier | M7: 15 | N7: INFRA
A8: A3 | B8: Organization identity and authorization | C8: Entra External ID/federation candidate; server membership enforcement | D8: Cognito/federation candidate; same server enforcement | E8: Do not equate IdP tenant with app organization; verify B2B/MAU terms | F8: MAUs, federation/SSO/MFA and support tier | G8: Plan and MAU allowances TBD, quote required | H8: Tenant/processing residency reviewed | I8: INFRA-EDGE pooled allowance; not unlimited free identity | J8: Managed provider plus recovery/break-glass policy | K8: Invitation/access review/audit per legal policy | L8: Enterprise SSO requirements or MAU tier | M8: 20 | N8: INFRA
A9: A4 | B9: Object storage / exports / customer documents | C9: Blob Storage with tenant-scoped signed access | D9: S3 with tenant-scoped presigned access | E9: No public patient objects; per-request tenant authorization, scanning and lifecycle | F9: StorageGB blended $0.15/GB-month covers backup/egress allowance, not retail rate | G9: Standard hot/cool candidate; operations/egress quote TBD | H9: East US / AWS US East TBD | I9: INFRA-STORE includes selected blended costs; minimum fixed services elsewhere | J9: Replication policy and restore independence TBD | K9: Clinical and export lifecycle per contract; proposed export expiry 7 days | L9: GB, egress and object count growth; retention changes | M9: 10 | N9: INFRA
A10: A5 | B10: Queues / secrets / observability | C10: Storage Queue/Service Bus candidate; Key Vault; Azure Monitor | D10: SQS; Secrets Manager; CloudWatch | E10: Managed jobs, retries/idempotency, least privilege, no PHI in telemetry | F10: LogsGB $5 blended plus RequestsM $30 capacity reserve; actual per-meter quotes needed | G10: Service tiers TBD; included allowance/minimum unverified, not treated as zero price | H10: East US / AWS US East TBD | I10: INFRA-LOG and INFRA-REQ; engineer implementation cost is STAFF | J10: Dead-letter queue, alert owner and credential rotation | K10: Proposed 30-day searchable logs / 90-day security summary; audit separate legal policy | L10: Ingestion cap, queue age, error budget and request volume | M10: 15 | N10: INFRA
A11: A6 | B11: Edge/WAF/DNS/email and environments | C11: Azure Front Door/WAF, DNS, approved email provider | D11: CloudFront/WAF, Route53, SES candidate | E11: Separate dev/stage/prod; staging synthetic only; eligibility and outbound data review | F11: Base minima, requests, egress, emails; quoted bundle allowance | G11: WAF/CDN/transactional email plan TBD | H11: Edge global; origin/data East US candidate | I11: INFRA-EDGE $250/month shared candidate bundle; provider prices unresolved | J11: Proposed redundant edge and deployment rollback | K11: DNS/email audit and delivery logs without PHI | L11: Traffic/abuse, geography, transactional email volume | M11: 10 | N11: INFRA
A12: A7 | B12: Backup / disaster recovery / operations | C12: DB PITR + Blob recovery + separately protected backups | D12: RDS PITR + S3 recovery + separately protected backups | E12: Vendor HA is not DR; timed restore evidence required before customer pilot | F12: Backup GB and retention, restore environments, independent copies | G12: Backup/replication SKU TBD; no cross-region guarantee in allowance | H12: Second region is decision/quote, not silently included | I12: INFRA-DB / INFRA-STORE allowances, revisit at DR gate | J12: Pilot RPO 24h/RTO 8h; growth candidate 1h/4h, not guaranteed | K12: 35-day PITR proposal; legal hold/deletion reconciliation specialist-reviewed | L12: Customer recovery target, material data volume or legal retention change | M12: 10 | N12: INFRA
A13: A8 | B13: Optional AI / CTMS services | C13: Provider-neutral AI adapter; separate research bounded context | D13: Same modular boundary on alternate managed stack | E13: Default off; no competing stack sum, no data sharing until approval | F13: AI InputM/OutputM + evaluation; CTMS integration/validation annual allowance | G13: GPT-4.1-mini candidate unverified; EDC/eTMF partner licenses TBD | H13: Provider residency and endpoints unresolved | I13: AI and CTMS line items plus optional STAFF; no revenue uplift | J13: Non-AI fallback, human approval, independent research gates | K13: Provider/clinical/research policy review; no PHI in prompts by default | L13: Separate investment case, buyer evidence and specialist approvals | M13: 30 | N13: AI / CTMS

Sheet Roadmap
A1: Methodology, roadmap and decision gates
A2: Assume 2-week iterations, small vertical slices, acceptance criteria, PR review + tests, threat model, staged release, feedback. Gates can delay dates; added headcount does not halve timelines.
A3: ← Start Here
A5: Id | B5: Phase | C5: Start | D5: End | E5: Dependency | F5: Owner | G5: Acceptance | H5: Confidence | I5: Scope | J5: Risk | K5: 1 | L5: 2 | M5: 3 | N5: 4 | O5: 5 | P5: 6 | Q5: 7 | R5: 8 | S5: 9 | T5: 10 | U5: 11 | V5: 12 | W5: 13 | X5: 14 | Y5: 15 | Z5: 16 | AA5: 17 | AB5: 18 | AC5: 19 | AD5: 20 | AE5: 21 | AF5: 22 | AG5: 23 | AH5: 24 | AI5: 25 | AJ5: 26 | AK5: 27 | AL5: 28 | AM5: 29 | AN5: 30 | AO5: 31 | AP5: 32 | AQ5: 33 | AR5: 34 | AS5: 35 | AT5: 36 | AU5: 37 | AV5: 38 | AW5: 39 | AX5: 40 | AY5: 41 | AZ5: 42 | BA5: 43 | BB5: 44 | BC5: 45 | BD5: 46 | BE5: 47 | BF5: 48 | BG5: 49 | BH5: 50 | BI5: 51 | BJ5: 52 | BK5: 53 | BL5: 54 | BM5: 55 | BN5: 56 | BO5: 57 | BP5: 58 | BQ5: 59 | BR5: 60
A6: G1 | B6: Assess: characterize and choose scope | C6: 1 | D6: 3 | E6: None | F6: Founder / tech lead | G6: Product wedge, intended use, canonical inventory and test baseline; reject/stop if no viable pilot need. | H6: Medium; ±1 month | I6: Core | J6: Buyer and inherited behavior uncertainty | K6: =IF(AND(K$5>=IF(I6="Core",C6,IF(I6="AI",Assumptions!$H$24,Assumptions!$H$25)),K$5<=IF(I6="Core",D6,IF(I6="AI",Assumptions!$H$24,Assumptions!$H$25)+D6-C6),IF(I6="Core",1,IF(I6="AI",'Start Here'!$B$7,'Start Here'!$B$8))=1),1,0) -> 1 | L6: =IF(AND(L$5>=IF(I6="Core",C6,IF(I6="AI",Assumptions!$H$24,Assumptions!$H$25)),L$5<=IF(I6="Core",D6,IF(I6="AI",Assumptions!$H$24,Assumptions!$H$25)+D6-C6),IF(I6="Core",1,IF(I6="AI",'Start Here'!$B$7,'Start Here'!$B$8))=1),1,0) -> 1 | M6: =IF(AND(M$5>=IF(I6="Core",C6,IF(I6="AI",Assumptions!$H$24,Assumptions!$H$25)),M$5<=IF(I6="Core",D6,IF(I6="AI",Assumptions!$H$24,Assumptions!$H$25)+D6-C6),IF(I6="Core",1,IF(I6="AI",'Start Here'!$B$7,'Start Here'!$B$8))=1),1,0) -> 1 | N6: =IF(AND(N$5>=IF(I6="Core",C6,IF(I6="AI",Assumptions!$H$24,Assumptions!$H$25)),N$5<=IF(I6="Core",D6,IF(I6="AI",Assumptions!$H$24,Assumptions!$H$25)+D6-C6),IF(I6="Core",1,IF(I6="AI",'Start Here'!$B$7,'Start Here'!$B$8))=1),1,0) -> 0 | O6: =IF(AND(O$5>=IF(I6="Core",C6,IF(I6="AI",Assumptions!$H$24,Assumptions!$H$25)),O$5<=IF(I6="Core",D6,IF(I6="AI",Assumptions!$H$24,Assumptions!$H$25)+D6-C6),IF(I6="Core",1,IF(I6="AI",'Start Here'!$B$7,'Start Here'!$B$8))=1),1,0) -> 0 | P6: =IF(AND(P$5>=IF(I6="Core",C6,IF(I6="AI",Assumptions!$H$24,Assumptions!$H$25)),P$5<=IF(I6="Core",D6,IF(I6="AI",Assumptions!$H$24,Assumptions!$H$25)+D6-C6),IF(I6="Core",1,IF(I6="AI",'Start Here'!$B$7,'Start Here'!$B$8))=1),1,0) -> 0 | Q6: =IF(AND(Q$5>=IF(I6="Core",C6,IF(I6="AI",Assumptions!$H$24,Assumptions!$H$25)),Q$5<=IF(I6="Core",D6,IF(I6="AI",Assumptions!$H$24,Assumptions!$H$25)+D6-C6),IF(I6="Core",1,IF(I6="AI",'Start Here'!$B$7,'Start Here'!$B$8))=1),1,0) -> 0 | R6: =IF(AND(R$5>=IF(I6="Core",C6,IF(I6="AI",Assumptions!$H$24,Assumptions!$H$25)),R$5<=IF(I6="Core",D6,IF(I6="AI",Assumptions!$H$24,Assumptions!$H$25)+D6-C6),IF(I6="Core",1,IF(I6="AI",'Start Here'!$B$7,'Start Here'!$B$8))=1),1,0) -> 0 | S6: =IF(AND(S$5>=IF(I6="Core",C6,IF(I6="AI",Assumptions!$H$24,Assumptions!$H$25)),S$5<=IF(I6="Core",D6,IF(I6="AI",Assumptions!$H$24,Assumptions!$H$25)+D6-C6),IF(I6="Core",1,IF(I6="AI",'Start Here'!$B$7,'Start Here'!$B$8))=1),1,0) -> 0 | T6: =IF(AND(T$5>=IF(I6="Core",C6,IF(I6="AI",Assumptions!$H$24,Assumptions!$H$25)),T$5<=IF(I6="Core",D6,IF(I6="AI",Assumptions!$H$24,Assumptions!$H$25)+D6-C6),IF(I6="Core",1,IF(I6="AI",'Start Here'!$B$7,'Start Here'!$B$8))=1),1,0) -> 0 | U6: =IF(AND(U$5>=IF(I6="Core",C6,IF(I6="AI",Assumptions!$H$24,Assumptions!$H$25)),U$5<=IF(I6="Core",D6,IF(I6="AI",Assumptions!$H$24,Assumptions!$H$25)+D6-C6),IF(I6="Core",1,IF(I6="AI",'Start Here'!$B$7,'Start Here'!$B$8))=1),1,0) -> 0 | V6: =IF(AND(V$5>=IF(I6="Core",C6,IF(I6="AI",Assumptions!$H$24,Assumptions!$H$25)),V$5<=IF(I6="Core",D6,IF(I6="AI",Assumptions!$H$24,Assumptions!$H$25)+D6-C6),IF(I6="Core",1,IF(I6="AI",'Start Here'!$B$7,'Start Here'!$B$8))=1),1,0) -> 0 | W6: =IF(AND(W$5>=IF(I6="Core",C6,IF(I6="AI",Assumptions!$H$24,Assumptions!$H$25)),W$5<=IF(I6="Core",D6,IF(I6="AI",Assumptions!$H$24,Assumptions!$H$25)+D6-C6),IF(I6="Core",1,IF(I6="AI",'Start Here'!$B$7,'Start Here'!$B$8))=1),1,0) -> 0 | X6: =IF(AND(X$5>=IF(I6="Core",C6,IF(I6="AI",Assumptions!$H$24,Assumptions!$H$25)),X$5<=IF(I6="Core",D6,IF(I6="AI",Assumptions!$H$24,Assumptions!$H$25)+D6-C6),IF(I6="Core",1,IF(I6="AI",'Start Here'!$B$7,'Start Here'!$B$8))=1),1,0) -> 0 | Y6: =IF(AND(Y$5>=IF(I6="Core",C6,IF(I6="AI",Assumptions!$H$24,Assumptions!$H$25)),Y$5<=IF(I6="Core",D6,IF(I6="AI",Assumptions!$H$24,Assumptions!$H$25)+D6-C6),IF(I6="Core",1,IF(I6="AI",'Start Here'!$B$7,'Start Here'!$B$8))=1),1,0) -> 0 | Z6: =IF(AND(Z$5>=IF(I6="Core",C6,IF(I6="AI",Assumptions!$H$24,Assumptions!$H$25)),Z$5<=IF(I6="Core",D6,IF(I6="AI",Assumptions!$H$24,Assumptions!$H$25)+D6-C6),IF(I6="Core",1,IF(I6="AI",'Start Here'!$B$7,'Start Here'!$B$8))=1),1,0) -> 0 | AA6: =IF(AND(AA$5>=IF(I6="Core",C6,IF(I6="AI",Assumptions!$H$24,Assumptions!$H$25)),AA$5<=IF(I6="Core",D6,IF(I6="AI",Assumptions!$H$24,Assumptions!$H$25)+D6-C6),IF(I6="Core",1,IF(I6="AI",'Start Here'!$B$7,'Start Here'!$B$8))=1),1,0) -> 0 | AB6: =IF(AND(AB$5>=IF(I6="Core",C6,IF(I6="AI",Assumptions!$H$24,Assumptions!$H$25)),AB$5<=IF(I6="Core",D6,IF(I6="AI",Assumptions!$H$24,Assumptions!$H$25)+D6-C6),IF(I6="Core",1,IF(I6="AI",'Start Here'!$B$7,'Start Here'!$B$8))=1),1,0) -> 0 | AC6: =IF(AND(AC$5>=IF(I6="Core",C6,IF(I6="AI",Assumptions!$H$24,Assumptions!$H$25)),AC$5<=IF(I6="Core",D6,IF(I6="AI",Assumptions!$H$24,Assumptions!$H$25)+D6-C6),IF(I6="Core",1,IF(I6="AI",'Start Here'!$B$7,'Start Here'!$B$8))=1),1,0) -> 0 | AD6: =IF(AND(AD$5>=IF(I6="Core",C6,IF(I6="AI",Assumptions!$H$24,Assumptions!$H$25)),AD$5<=IF(I6="Core",D6,IF(I6="AI",Assumptions!$H$24,Assumptions!$H$25)+D6-C6),IF(I6="Core",1,IF(I6="AI",'Start Here'!$B$7,'Start Here'!$B$8))=1),1,0) -> 0 | AE6: =IF(AND(AE$5>=IF(I6="Core",C6,IF(I6="AI",Assumptions!$H$24,Assumptions!$H$25)),AE$5<=IF(I6="Core",D6,IF(I6="AI",Assumptions!$H$24,Assumptions!$H$25)+D6-C6),IF(I6="Core",1,IF(I6="AI",'Start Here'!$B$7,'Start Here'!$B$8))=1),1,0) -> 0 | AF6: =IF(AND(AF$5>=IF(I6="Core",C6,IF(I6="AI",Assumptions!$H$24,Assumptions!$H$25)),AF$5<=IF(I6="Core",D6,IF(I6="AI",Assumptions!$H$24,Assumptions!$H$25)+D6-C6),IF(I6="Core",1,IF(I6="AI",'Start Here'!$B$7,'Start Here'!$B$8))=1),1,0) -> 0 | AG6: =IF(AND(AG$5>=IF(I6="Core",C6,IF(I6="AI",Assumptions!$H$24,Assumptions!$H$25)),AG$5<=IF(I6="Core",D6,IF(I6="AI",Assumptions!$H$24,Assumptions!$H$25)+D6-C6),IF(I6="Core",1,IF(I6="AI",'Start Here'!$B$7,'Start Here'!$B$8))=1),1,0) -> 0 | AH6: =IF(AND(AH$5>=IF(I6="Core",C6,IF(I6="AI",Assumptions!$H$24,Assumptions!$H$25)),AH$5<=IF(I6="Core",D6,IF(I6="AI",Assumptions!$H$24,Assumptions!$H$25)+D6-C6),IF(I6="Core",1,IF(I6="AI",'Start Here'!$B$7,'Start Here'!$B$8))=1),1,0) -> 0 | AI6: =IF(AND(AI$5>=IF(I6="Core",C6,IF(I6="AI",Assumptions!$H$24,Assumptions!$H$25)),AI$5<=IF(I6="Core",D6,IF(I6="AI",Assumptions!$H$24,Assumptions!$H$25)+D6-C6),IF(I6="Core",1,IF(I6="AI",'Start Here'!$B$7,'Start Here'!$B$8))=1),1,0) -> 0 | AJ6: =IF(AND(AJ$5>=IF(I6="Core",C6,IF(I6="AI",Assumptions!$H$24,Assumptions!$H$25)),AJ$5<=IF(I6="Core",D6,IF(I6="AI",Assumptions!$H$24,Assumptions!$H$25)+D6-C6),IF(I6="Core",1,IF(I6="AI",'Start Here'!$B$7,'Start Here'!$B$8))=1),1,0) -> 0 | AK6: =IF(AND(AK$5>=IF(I6="Core",C6,IF(I6="AI",Assumptions!$H$24,Assumptions!$H$25)),AK$5<=IF(I6="Core",D6,IF(I6="AI",Assumptions!$H$24,Assumptions!$H$25)+D6-C6),IF(I6="Core",1,IF(I6="AI",'Start Here'!$B$7,'Start Here'!$B$8))=1),1,0) -> 0 | AL6: =IF(AND(AL$5>=IF(I6="Core",C6,IF(I6="AI",Assumptions!$H$24,Assumptions!$H$25)),AL$5<=IF(I6="Core",D6,IF(I6="AI",Assumptions!$H$24,Assumptions!$H$25)+D6-C6),IF(I6="Core",1,IF(I6="AI",'Start Here'!$B$7,'Start Here'!$B$8))=1),1,0) -> 0 | AM6: =IF(AND(AM$5>=IF(I6="Core",C6,IF(I6="AI",Assumptions!$H$24,Assumptions!$H$25)),AM$5<=IF(I6="Core",D6,IF(I6="AI",Assumptions!$H$24,Assumptions!$H$25)+D6-C6),IF(I6="Core",1,IF(I6="AI",'Start Here'!$B$7,'Start Here'!$B$8))=1),1,0) -> 0 | AN6: =IF(AND(AN$5>=IF(I6="Core",C6,IF(I6="AI",Assumptions!$H$24,Assumptions!$H$25)),AN$5<=IF(I6="Core",D6,IF(I6="AI",Assumptions!$H$24,Assumptions!$H$25)+D6-C6),IF(I6="Core",1,IF(I6="AI",'Start Here'!$B$7,'Start Here'!$B$8))=1),1,0) -> 0 | AO6: =IF(AND(AO$5>=IF(I6="Core",C6,IF(I6="AI",Assumptions!$H$24,Assumptions!$H$25)),AO$5<=IF(I6="Core",D6,IF(I6="AI",Assumptions!$H$24,Assumptions!$H$25)+D6-C6),IF(I6="Core",1,IF(I6="AI",'Start Here'!$B$7,'Start Here'!$B$8))=1),1,0) -> 0 | AP6: =IF(AND(AP$5>=IF(I6="Core",C6,IF(I6="AI",Assumptions!$H$24,Assumptions!$H$25)),AP$5<=IF(I6="Core",D6,IF(I6="AI",Assumptions!$H$24,Assumptions!$H$25)+D6-C6),IF(I6="Core",1,IF(I6="AI",'Start Here'!$B$7,'Start Here'!$B$8))=1),1,0) -> 0 | AQ6: =IF(AND(AQ$5>=IF(I6="Core",C6,IF(I6="AI",Assumptions!$H$24,Assumptions!$H$25)),AQ$5<=IF(I6="Core",D6,IF(I6="AI",Assumptions!$H$24,Assumptions!$H$25)+D6-C6),IF(I6="Core",1,IF(I6="AI",'Start Here'!$B$7,'Start Here'!$B$8))=1),1,0) -> 0 | AR6: =IF(AND(AR$5>=IF(I6="Core",C6,IF(I6="AI",Assumptions!$H$24,Assumptions!$H$25)),AR$5<=IF(I6="Core",D6,IF(I6="AI",Assumptions!$H$24,Assumptions!$H$25)+D6-C6),IF(I6="Core",1,IF(I6="AI",'Start Here'!$B$7,'Start Here'!$B$8))=1),1,0) -> 0 | AS6: =IF(AND(AS$5>=IF(I6="Core",C6,IF(I6="AI",Assumptions!$H$24,Assumptions!$H$25)),AS$5<=IF(I6="Core",D6,IF(I6="AI",Assumptions!$H$24,Assumptions!$H$25)+D6-C6),IF(I6="Core",1,IF(I6="AI",'Start Here'!$B$7,'Start Here'!$B$8))=1),1,0) -> 0 | AT6: =IF(AND(AT$5>=IF(I6="Core",C6,IF(I6="AI",Assumptions!$H$24,Assumptions!$H$25)),AT$5<=IF(I6="Core",D6,IF(I6="AI",Assumptions!$H$24,Assumptions!$H$25)+D6-C6),IF(I6="Core",1,IF(I6="AI",'Start Here'!$B$7,'Start Here'!$B$8))=1),1,0) -> 0 | AU6: =IF(AND(AU$5>=IF(I6="Core",C6,IF(I6="AI",Assumptions!$H$24,Assumptions!$H$25)),AU$5<=IF(I6="Core",D6,IF(I6="AI",Assumptions!$H$24,Assumptions!$H$25)+D6-C6),IF(I6="Core",1,IF(I6="AI",'Start Here'!$B$7,'Start Here'!$B$8))=1),1,0) -> 0 | AV6: =IF(AND(AV$5>=IF(I6="Core",C6,IF(I6="AI",Assumptions!$H$24,Assumptions!$H$25)),AV$5<=IF(I6="Core",D6,IF(I6="AI",Assumptions!$H$24,Assumptions!$H$25)+D6-C6),IF(I6="Core",1,IF(I6="AI",'Start Here'!$B$7,'Start Here'!$B$8))=1),1,0) -> 0 | AW6: =IF(AND(AW$5>=IF(I6="Core",C6,IF(I6="AI",Assumptions!$H$24,Assumptions!$H$25)),AW$5<=IF(I6="Core",D6,IF(I6="AI",Assumptions!$H$24,Assumptions!$H$25)+D6-C6),IF(I6="Core",1,IF(I6="AI",'Start Here'!$B$7,'Start Here'!$B$8))=1),1,0) -> 0 | AX6: =IF(AND(AX$5>=IF(I6="Core",C6,IF(I6="AI",Assumptions!$H$24,Assumptions!$H$25)),AX$5<=IF(I6="Core",D6,IF(I6="AI",Assumptions!$H$24,Assumptions!$H$25)+D6-C6),IF(I6="Core",1,IF(I6="AI",'Start Here'!$B$7,'Start Here'!$B$8))=1),1,0) -> 0 | AY6: =IF(AND(AY$5>=IF(I6="Core",C6,IF(I6="AI",Assumptions!$H$24,Assumptions!$H$25)),AY$5<=IF(I6="Core",D6,IF(I6="AI",Assumptions!$H$24,Assumptions!$H$25)+D6-C6),IF(I6="Core",1,IF(I6="AI",'Start Here'!$B$7,'Start Here'!$B$8))=1),1,0) -> 0 | AZ6: =IF(AND(AZ$5>=IF(I6="Core",C6,IF(I6="AI",Assumptions!$H$24,Assumptions!$H$25)),AZ$5<=IF(I6="Core",D6,IF(I6="AI",Assumptions!$H$24,Assumptions!$H$25)+D6-C6),IF(I6="Core",1,IF(I6="AI",'Start Here'!$B$7,'Start Here'!$B$8))=1),1,0) -> 0 | BA6: =IF(AND(BA$5>=IF(I6="Core",C6,IF(I6="AI",Assumptions!$H$24,Assumptions!$H$25)),BA$5<=IF(I6="Core",D6,IF(I6="AI",Assumptions!$H$24,Assumptions!$H$25)+D6-C6),IF(I6="Core",1,IF(I6="AI",'Start Here'!$B$7,'Start Here'!$B$8))=1),1,0) -> 0 | BB6: =IF(AND(BB$5>=IF(I6="Core",C6,IF(I6="AI",Assumptions!$H$24,Assumptions!$H$25)),BB$5<=IF(I6="Core",D6,IF(I6="AI",Assumptions!$H$24,Assumptions!$H$25)+D6-C6),IF(I6="Core",1,IF(I6="AI",'Start Here'!$B$7,'Start Here'!$B$8))=1),1,0) -> 0 | BC6: =IF(AND(BC$5>=IF(I6="Core",C6,IF(I6="AI",Assumptions!$H$24,Assumptions!$H$25)),BC$5<=IF(I6="Core",D6,IF(I6="AI",Assumptions!$H$24,Assumptions!$H$25)+D6-C6),IF(I6="Core",1,IF(I6="AI",'Start Here'!$B$7,'Start Here'!$B$8))=1),1,0) -> 0 | BD6: =IF(AND(BD$5>=IF(I6="Core",C6,IF(I6="AI",Assumptions!$H$24,Assumptions!$H$25)),BD$5<=IF(I6="Core",D6,IF(I6="AI",Assumptions!$H$24,Assumptions!$H$25)+D6-C6),IF(I6="Core",1,IF(I6="AI",'Start Here'!$B$7,'Start Here'!$B$8))=1),1,0) -> 0 | BE6: =IF(AND(BE$5>=IF(I6="Core",C6,IF(I6="AI",Assumptions!$H$24,Assumptions!$H$25)),BE$5<=IF(I6="Core",D6,IF(I6="AI",Assumptions!$H$24,Assumptions!$H$25)+D6-C6),IF(I6="Core",1,IF(I6="AI",'Start Here'!$B$7,'Start Here'!$B$8))=1),1,0) -> 0 | BF6: =IF(AND(BF$5>=IF(I6="Core",C6,IF(I6="AI",Assumptions!$H$24,Assumptions!$H$25)),BF$5<=IF(I6="Core",D6,IF(I6="AI",Assumptions!$H$24,Assumptions!$H$25)+D6-C6),IF(I6="Core",1,IF(I6="AI",'Start Here'!$B$7,'Start Here'!$B$8))=1),1,0) -> 0 | BG6: =IF(AND(BG$5>=IF(I6="Core",C6,IF(I6="AI",Assumptions!$H$24,Assumptions!$H$25)),BG$5<=IF(I6="Core",D6,IF(I6="AI",Assumptions!$H$24,Assumptions!$H$25)+D6-C6),IF(I6="Core",1,IF(I6="AI",'Start Here'!$B$7,'Start Here'!$B$8))=1),1,0) -> 0 | BH6: =IF(AND(BH$5>=IF(I6="Core",C6,IF(I6="AI",Assumptions!$H$24,Assumptions!$H$25)),BH$5<=IF(I6="Core",D6,IF(I6="AI",Assumptions!$H$24,Assumptions!$H$25)+D6-C6),IF(I6="Core",1,IF(I6="AI",'Start Here'!$B$7,'Start Here'!$B$8))=1),1,0) -> 0 | BI6: =IF(AND(BI$5>=IF(I6="Core",C6,IF(I6="AI",Assumptions!$H$24,Assumptions!$H$25)),BI$5<=IF(I6="Core",D6,IF(I6="AI",Assumptions!$H$24,Assumptions!$H$25)+D6-C6),IF(I6="Core",1,IF(I6="AI",'Start Here'!$B$7,'Start Here'!$B$8))=1),1,0) -> 0 | BJ6: =IF(AND(BJ$5>=IF(I6="Core",C6,IF(I6="AI",Assumptions!$H$24,Assumptions!$H$25)),BJ$5<=IF(I6="Core",D6,IF(I6="AI",Assumptions!$H$24,Assumptions!$H$25)+D6-C6),IF(I6="Core",1,IF(I6="AI",'Start Here'!$B$7,'Start Here'!$B$8))=1),1,0) -> 0 | BK6: =IF(AND(BK$5>=IF(I6="Core",C6,IF(I6="AI",Assumptions!$H$24,Assumptions!$H$25)),BK$5<=IF(I6="Core",D6,IF(I6="AI",Assumptions!$H$24,Assumptions!$H$25)+D6-C6),IF(I6="Core",1,IF(I6="AI",'Start Here'!$B$7,'Start Here'!$B$8))=1),1,0) -> 0 | BL6: =IF(AND(BL$5>=IF(I6="Core",C6,IF(I6="AI",Assumptions!$H$24,Assumptions!$H$25)),BL$5<=IF(I6="Core",D6,IF(I6="AI",Assumptions!$H$24,Assumptions!$H$25)+D6-C6),IF(I6="Core",1,IF(I6="AI",'Start Here'!$B$7,'Start Here'!$B$8))=1),1,0) -> 0 | BM6: =IF(AND(BM$5>=IF(I6="Core",C6,IF(I6="AI",Assumptions!$H$24,Assumptions!$H$25)),BM$5<=IF(I6="Core",D6,IF(I6="AI",Assumptions!$H$24,Assumptions!$H$25)+D6-C6),IF(I6="Core",1,IF(I6="AI",'Start Here'!$B$7,'Start Here'!$B$8))=1),1,0) -> 0 | BN6: =IF(AND(BN$5>=IF(I6="Core",C6,IF(I6="AI",Assumptions!$H$24,Assumptions!$H$25)),BN$5<=IF(I6="Core",D6,IF(I6="AI",Assumptions!$H$24,Assumptions!$H$25)+D6-C6),IF(I6="Core",1,IF(I6="AI",'Start Here'!$B$7,'Start Here'!$B$8))=1),1,0) -> 0 | BO6: =IF(AND(BO$5>=IF(I6="Core",C6,IF(I6="AI",Assumptions!$H$24,Assumptions!$H$25)),BO$5<=IF(I6="Core",D6,IF(I6="AI",Assumptions!$H$24,Assumptions!$H$25)+D6-C6),IF(I6="Core",1,IF(I6="AI",'Start Here'!$B$7,'Start Here'!$B$8))=1),1,0) -> 0 | BP6: =IF(AND(BP$5>=IF(I6="Core",C6,IF(I6="AI",Assumptions!$H$24,Assumptions!$H$25)),BP$5<=IF(I6="Core",D6,IF(I6="AI",Assumptions!$H$24,Assumptions!$H$25)+D6-C6),IF(I6="Core",1,IF(I6="AI",'Start Here'!$B$7,'Start Here'!$B$8))=1),1,0) -> 0 | BQ6: =IF(AND(BQ$5>=IF(I6="Core",C6,IF(I6="AI",Assumptions!$H$24,Assumptions!$H$25)),BQ$5<=IF(I6="Core",D6,IF(I6="AI",Assumptions!$H$24,Assumptions!$H$25)+D6-C6),IF(I6="Core",1,IF(I6="AI",'Start Here'!$B$7,'Start Here'!$B$8))=1),1,0) -> 0 | BR6: =IF(AND(BR$5>=IF(I6="Core",C6,IF(I6="AI",Assumptions!$H$24,Assumptions!$H$25)),BR$5<=IF(I6="Core",D6,IF(I6="AI",Assumptions!$H$24,Assumptions!$H$25)+D6-C6),IF(I6="Core",1,IF(I6="AI",'Start Here'!$B$7,'Start Here'!$B$8))=1),1,0) -> 0
A7: G2 | B7: SaaS foundation | C7: 4 | D7: 8 | E7: G1; W3.1 identity design begins M3 | F7: Tech lead | G7: Tenant model, auth/API, schema/mapping, modular UI and CI; review threat model and infrastructure quote. | H7: Low–medium; −1/+3 months | I7: Core | J7: Identity and schema discoveries; hiring lead time | K7: =IF(AND(K$5>=IF(I7="Core",C7,IF(I7="AI",Assumptions!$H$24,Assumptions!$H$25)),K$5<=IF(I7="Core",D7,IF(I7="AI",Assumptions!$H$24,Assumptions!$H$25)+D7-C7),IF(I7="Core",1,IF(I7="AI",'Start Here'!$B$7,'Start Here'!$B$8))=1),1,0) -> 0 | L7: =IF(AND(L$5>=IF(I7="Core",C7,IF(I7="AI",Assumptions!$H$24,Assumptions!$H$25)),L$5<=IF(I7="Core",D7,IF(I7="AI",Assumptions!$H$24,Assumptions!$H$25)+D7-C7),IF(I7="Core",1,IF(I7="AI",'Start Here'!$B$7,'Start Here'!$B$8))=1),1,0) -> 0 | M7: =IF(AND(M$5>=IF(I7="Core",C7,IF(I7="AI",Assumptions!$H$24,Assumptions!$H$25)),M$5<=IF(I7="Core",D7,IF(I7="AI",Assumptions!$H$24,Assumptions!$H$25)+D7-C7),IF(I7="Core",1,IF(I7="AI",'Start Here'!$B$7,'Start Here'!$B$8))=1),1,0) -> 0 | N7: =IF(AND(N$5>=IF(I7="Core",C7,IF(I7="AI",Assumptions!$H$24,Assumptions!$H$25)),N$5<=IF(I7="Core",D7,IF(I7="AI",Assumptions!$H$24,Assumptions!$H$25)+D7-C7),IF(I7="Core",1,IF(I7="AI",'Start Here'!$B$7,'Start Here'!$B$8))=1),1,0) -> 1 | O7: =IF(AND(O$5>=IF(I7="Core",C7,IF(I7="AI",Assumptions!$H$24,Assumptions!$H$25)),O$5<=IF(I7="Core",D7,IF(I7="AI",Assumptions!$H$24,Assumptions!$H$25)+D7-C7),IF(I7="Core",1,IF(I7="AI",'Start Here'!$B$7,'Start Here'!$B$8))=1),1,0) -> 1 | P7: =IF(AND(P$5>=IF(I7="Core",C7,IF(I7="AI",Assumptions!$H$24,Assumptions!$H$25)),P$5<=IF(I7="Core",D7,IF(I7="AI",Assumptions!$H$24,Assumptions!$H$25)+D7-C7),IF(I7="Core",1,IF(I7="AI",'Start Here'!$B$7,'Start Here'!$B$8))=1),1,0) -> 1 | Q7: =IF(AND(Q$5>=IF(I7="Core",C7,IF(I7="AI",Assumptions!$H$24,Assumptions!$H$25)),Q$5<=IF(I7="Core",D7,IF(I7="AI",Assumptions!$H$24,Assumptions!$H$25)+D7-C7),IF(I7="Core",1,IF(I7="AI",'Start Here'!$B$7,'Start Here'!$B$8))=1),1,0) -> 1 | R7: =IF(AND(R$5>=IF(I7="Core",C7,IF(I7="AI",Assumptions!$H$24,Assumptions!$H$25)),R$5<=IF(I7="Core",D7,IF(I7="AI",Assumptions!$H$24,Assumptions!$H$25)+D7-C7),IF(I7="Core",1,IF(I7="AI",'Start Here'!$B$7,'Start Here'!$B$8))=1),1,0) -> 1 | S7: =IF(AND(S$5>=IF(I7="Core",C7,IF(I7="AI",Assumptions!$H$24,Assumptions!$H$25)),S$5<=IF(I7="Core",D7,IF(I7="AI",Assumptions!$H$24,Assumptions!$H$25)+D7-C7),IF(I7="Core",1,IF(I7="AI",'Start Here'!$B$7,'Start Here'!$B$8))=1),1,0) -> 0 | T7: =IF(AND(T$5>=IF(I7="Core",C7,IF(I7="AI",Assumptions!$H$24,Assumptions!$H$25)),T$5<=IF(I7="Core",D7,IF(I7="AI",Assumptions!$H$24,Assumptions!$H$25)+D7-C7),IF(I7="Core",1,IF(I7="AI",'Start Here'!$B$7,'Start Here'!$B$8))=1),1,0) -> 0 | U7: =IF(AND(U$5>=IF(I7="Core",C7,IF(I7="AI",Assumptions!$H$24,Assumptions!$H$25)),U$5<=IF(I7="Core",D7,IF(I7="AI",Assumptions!$H$24,Assumptions!$H$25)+D7-C7),IF(I7="Core",1,IF(I7="AI",'Start Here'!$B$7,'Start Here'!$B$8))=1),1,0) -> 0 | V7: =IF(AND(V$5>=IF(I7="Core",C7,IF(I7="AI",Assumptions!$H$24,Assumptions!$H$25)),V$5<=IF(I7="Core",D7,IF(I7="AI",Assumptions!$H$24,Assumptions!$H$25)+D7-C7),IF(I7="Core",1,IF(I7="AI",'Start Here'!$B$7,'Start Here'!$B$8))=1),1,0) -> 0 | W7: =IF(AND(W$5>=IF(I7="Core",C7,IF(I7="AI",Assumptions!$H$24,Assumptions!$H$25)),W$5<=IF(I7="Core",D7,IF(I7="AI",Assumptions!$H$24,Assumptions!$H$25)+D7-C7),IF(I7="Core",1,IF(I7="AI",'Start Here'!$B$7,'Start Here'!$B$8))=1),1,0) -> 0 | X7: =IF(AND(X$5>=IF(I7="Core",C7,IF(I7="AI",Assumptions!$H$24,Assumptions!$H$25)),X$5<=IF(I7="Core",D7,IF(I7="AI",Assumptions!$H$24,Assumptions!$H$25)+D7-C7),IF(I7="Core",1,IF(I7="AI",'Start Here'!$B$7,'Start Here'!$B$8))=1),1,0) -> 0 | Y7: =IF(AND(Y$5>=IF(I7="Core",C7,IF(I7="AI",Assumptions!$H$24,Assumptions!$H$25)),Y$5<=IF(I7="Core",D7,IF(I7="AI",Assumptions!$H$24,Assumptions!$H$25)+D7-C7),IF(I7="Core",1,IF(I7="AI",'Start Here'!$B$7,'Start Here'!$B$8))=1),1,0) -> 0 | Z7: =IF(AND(Z$5>=IF(I7="Core",C7,IF(I7="AI",Assumptions!$H$24,Assumptions!$H$25)),Z$5<=IF(I7="Core",D7,IF(I7="AI",Assumptions!$H$24,Assumptions!$H$25)+D7-C7),IF(I7="Core",1,IF(I7="AI",'Start Here'!$B$7,'Start Here'!$B$8))=1),1,0) -> 0 | AA7: =IF(AND(AA$5>=IF(I7="Core",C7,IF(I7="AI",Assumptions!$H$24,Assumptions!$H$25)),AA$5<=IF(I7="Core",D7,IF(I7="AI",Assumptions!$H$24,Assumptions!$H$25)+D7-C7),IF(I7="Core",1,IF(I7="AI",'Start Here'!$B$7,'Start Here'!$B$8))=1),1,0) -> 0 | AB7: =IF(AND(AB$5>=IF(I7="Core",C7,IF(I7="AI",Assumptions!$H$24,Assumptions!$H$25)),AB$5<=IF(I7="Core",D7,IF(I7="AI",Assumptions!$H$24,Assumptions!$H$25)+D7-C7),IF(I7="Core",1,IF(I7="AI",'Start Here'!$B$7,'Start Here'!$B$8))=1),1,0) -> 0 | AC7: =IF(AND(AC$5>=IF(I7="Core",C7,IF(I7="AI",Assumptions!$H$24,Assumptions!$H$25)),AC$5<=IF(I7="Core",D7,IF(I7="AI",Assumptions!$H$24,Assumptions!$H$25)+D7-C7),IF(I7="Core",1,IF(I7="AI",'Start Here'!$B$7,'Start Here'!$B$8))=1),1,0) -> 0 | AD7: =IF(AND(AD$5>=IF(I7="Core",C7,IF(I7="AI",Assumptions!$H$24,Assumptions!$H$25)),AD$5<=IF(I7="Core",D7,IF(I7="AI",Assumptions!$H$24,Assumptions!$H$25)+D7-C7),IF(I7="Core",1,IF(I7="AI",'Start Here'!$B$7,'Start Here'!$B$8))=1),1,0) -> 0 | AE7: =IF(AND(AE$5>=IF(I7="Core",C7,IF(I7="AI",Assumptions!$H$24,Assumptions!$H$25)),AE$5<=IF(I7="Core",D7,IF(I7="AI",Assumptions!$H$24,Assumptions!$H$25)+D7-C7),IF(I7="Core",1,IF(I7="AI",'Start Here'!$B$7,'Start Here'!$B$8))=1),1,0) -> 0 | AF7: =IF(AND(AF$5>=IF(I7="Core",C7,IF(I7="AI",Assumptions!$H$24,Assumptions!$H$25)),AF$5<=IF(I7="Core",D7,IF(I7="AI",Assumptions!$H$24,Assumptions!$H$25)+D7-C7),IF(I7="Core",1,IF(I7="AI",'Start Here'!$B$7,'Start Here'!$B$8))=1),1,0) -> 0 | AG7: =IF(AND(AG$5>=IF(I7="Core",C7,IF(I7="AI",Assumptions!$H$24,Assumptions!$H$25)),AG$5<=IF(I7="Core",D7,IF(I7="AI",Assumptions!$H$24,Assumptions!$H$25)+D7-C7),IF(I7="Core",1,IF(I7="AI",'Start Here'!$B$7,'Start Here'!$B$8))=1),1,0) -> 0 | AH7: =IF(AND(AH$5>=IF(I7="Core",C7,IF(I7="AI",Assumptions!$H$24,Assumptions!$H$25)),AH$5<=IF(I7="Core",D7,IF(I7="AI",Assumptions!$H$24,Assumptions!$H$25)+D7-C7),IF(I7="Core",1,IF(I7="AI",'Start Here'!$B$7,'Start Here'!$B$8))=1),1,0) -> 0 | AI7: =IF(AND(AI$5>=IF(I7="Core",C7,IF(I7="AI",Assumptions!$H$24,Assumptions!$H$25)),AI$5<=IF(I7="Core",D7,IF(I7="AI",Assumptions!$H$24,Assumptions!$H$25)+D7-C7),IF(I7="Core",1,IF(I7="AI",'Start Here'!$B$7,'Start Here'!$B$8))=1),1,0) -> 0 | AJ7: =IF(AND(AJ$5>=IF(I7="Core",C7,IF(I7="AI",Assumptions!$H$24,Assumptions!$H$25)),AJ$5<=IF(I7="Core",D7,IF(I7="AI",Assumptions!$H$24,Assumptions!$H$25)+D7-C7),IF(I7="Core",1,IF(I7="AI",'Start Here'!$B$7,'Start Here'!$B$8))=1),1,0) -> 0 | AK7: =IF(AND(AK$5>=IF(I7="Core",C7,IF(I7="AI",Assumptions!$H$24,Assumptions!$H$25)),AK$5<=IF(I7="Core",D7,IF(I7="AI",Assumptions!$H$24,Assumptions!$H$25)+D7-C7),IF(I7="Core",1,IF(I7="AI",'Start Here'!$B$7,'Start Here'!$B$8))=1),1,0) -> 0 | AL7: =IF(AND(AL$5>=IF(I7="Core",C7,IF(I7="AI",Assumptions!$H$24,Assumptions!$H$25)),AL$5<=IF(I7="Core",D7,IF(I7="AI",Assumptions!$H$24,Assumptions!$H$25)+D7-C7),IF(I7="Core",1,IF(I7="AI",'Start Here'!$B$7,'Start Here'!$B$8))=1),1,0) -> 0 | AM7: =IF(AND(AM$5>=IF(I7="Core",C7,IF(I7="AI",Assumptions!$H$24,Assumptions!$H$25)),AM$5<=IF(I7="Core",D7,IF(I7="AI",Assumptions!$H$24,Assumptions!$H$25)+D7-C7),IF(I7="Core",1,IF(I7="AI",'Start Here'!$B$7,'Start Here'!$B$8))=1),1,0) -> 0 | AN7: =IF(AND(AN$5>=IF(I7="Core",C7,IF(I7="AI",Assumptions!$H$24,Assumptions!$H$25)),AN$5<=IF(I7="Core",D7,IF(I7="AI",Assumptions!$H$24,Assumptions!$H$25)+D7-C7),IF(I7="Core",1,IF(I7="AI",'Start Here'!$B$7,'Start Here'!$B$8))=1),1,0) -> 0 | AO7: =IF(AND(AO$5>=IF(I7="Core",C7,IF(I7="AI",Assumptions!$H$24,Assumptions!$H$25)),AO$5<=IF(I7="Core",D7,IF(I7="AI",Assumptions!$H$24,Assumptions!$H$25)+D7-C7),IF(I7="Core",1,IF(I7="AI",'Start Here'!$B$7,'Start Here'!$B$8))=1),1,0) -> 0 | AP7: =IF(AND(AP$5>=IF(I7="Core",C7,IF(I7="AI",Assumptions!$H$24,Assumptions!$H$25)),AP$5<=IF(I7="Core",D7,IF(I7="AI",Assumptions!$H$24,Assumptions!$H$25)+D7-C7),IF(I7="Core",1,IF(I7="AI",'Start Here'!$B$7,'Start Here'!$B$8))=1),1,0) -> 0 | AQ7: =IF(AND(AQ$5>=IF(I7="Core",C7,IF(I7="AI",Assumptions!$H$24,Assumptions!$H$25)),AQ$5<=IF(I7="Core",D7,IF(I7="AI",Assumptions!$H$24,Assumptions!$H$25)+D7-C7),IF(I7="Core",1,IF(I7="AI",'Start Here'!$B$7,'Start Here'!$B$8))=1),1,0) -> 0 | AR7: =IF(AND(AR$5>=IF(I7="Core",C7,IF(I7="AI",Assumptions!$H$24,Assumptions!$H$25)),AR$5<=IF(I7="Core",D7,IF(I7="AI",Assumptions!$H$24,Assumptions!$H$25)+D7-C7),IF(I7="Core",1,IF(I7="AI",'Start Here'!$B$7,'Start Here'!$B$8))=1),1,0) -> 0 | AS7: =IF(AND(AS$5>=IF(I7="Core",C7,IF(I7="AI",Assumptions!$H$24,Assumptions!$H$25)),AS$5<=IF(I7="Core",D7,IF(I7="AI",Assumptions!$H$24,Assumptions!$H$25)+D7-C7),IF(I7="Core",1,IF(I7="AI",'Start Here'!$B$7,'Start Here'!$B$8))=1),1,0) -> 0 | AT7: =IF(AND(AT$5>=IF(I7="Core",C7,IF(I7="AI",Assumptions!$H$24,Assumptions!$H$25)),AT$5<=IF(I7="Core",D7,IF(I7="AI",Assumptions!$H$24,Assumptions!$H$25)+D7-C7),IF(I7="Core",1,IF(I7="AI",'Start Here'!$B$7,'Start Here'!$B$8))=1),1,0) -> 0 | AU7: =IF(AND(AU$5>=IF(I7="Core",C7,IF(I7="AI",Assumptions!$H$24,Assumptions!$H$25)),AU$5<=IF(I7="Core",D7,IF(I7="AI",Assumptions!$H$24,Assumptions!$H$25)+D7-C7),IF(I7="Core",1,IF(I7="AI",'Start Here'!$B$7,'Start Here'!$B$8))=1),1,0) -> 0 | AV7: =IF(AND(AV$5>=IF(I7="Core",C7,IF(I7="AI",Assumptions!$H$24,Assumptions!$H$25)),AV$5<=IF(I7="Core",D7,IF(I7="AI",Assumptions!$H$24,Assumptions!$H$25)+D7-C7),IF(I7="Core",1,IF(I7="AI",'Start Here'!$B$7,'Start Here'!$B$8))=1),1,0) -> 0 | AW7: =IF(AND(AW$5>=IF(I7="Core",C7,IF(I7="AI",Assumptions!$H$24,Assumptions!$H$25)),AW$5<=IF(I7="Core",D7,IF(I7="AI",Assumptions!$H$24,Assumptions!$H$25)+D7-C7),IF(I7="Core",1,IF(I7="AI",'Start Here'!$B$7,'Start Here'!$B$8))=1),1,0) -> 0 | AX7: =IF(AND(AX$5>=IF(I7="Core",C7,IF(I7="AI",Assumptions!$H$24,Assumptions!$H$25)),AX$5<=IF(I7="Core",D7,IF(I7="AI",Assumptions!$H$24,Assumptions!$H$25)+D7-C7),IF(I7="Core",1,IF(I7="AI",'Start Here'!$B$7,'Start Here'!$B$8))=1),1,0) -> 0 | AY7: =IF(AND(AY$5>=IF(I7="Core",C7,IF(I7="AI",Assumptions!$H$24,Assumptions!$H$25)),AY$5<=IF(I7="Core",D7,IF(I7="AI",Assumptions!$H$24,Assumptions!$H$25)+D7-C7),IF(I7="Core",1,IF(I7="AI",'Start Here'!$B$7,'Start Here'!$B$8))=1),1,0) -> 0 | AZ7: =IF(AND(AZ$5>=IF(I7="Core",C7,IF(I7="AI",Assumptions!$H$24,Assumptions!$H$25)),AZ$5<=IF(I7="Core",D7,IF(I7="AI",Assumptions!$H$24,Assumptions!$H$25)+D7-C7),IF(I7="Core",1,IF(I7="AI",'Start Here'!$B$7,'Start Here'!$B$8))=1),1,0) -> 0 | BA7: =IF(AND(BA$5>=IF(I7="Core",C7,IF(I7="AI",Assumptions!$H$24,Assumptions!$H$25)),BA$5<=IF(I7="Core",D7,IF(I7="AI",Assumptions!$H$24,Assumptions!$H$25)+D7-C7),IF(I7="Core",1,IF(I7="AI",'Start Here'!$B$7,'Start Here'!$B$8))=1),1,0) -> 0 | BB7: =IF(AND(BB$5>=IF(I7="Core",C7,IF(I7="AI",Assumptions!$H$24,Assumptions!$H$25)),BB$5<=IF(I7="Core",D7,IF(I7="AI",Assumptions!$H$24,Assumptions!$H$25)+D7-C7),IF(I7="Core",1,IF(I7="AI",'Start Here'!$B$7,'Start Here'!$B$8))=1),1,0) -> 0 | BC7: =IF(AND(BC$5>=IF(I7="Core",C7,IF(I7="AI",Assumptions!$H$24,Assumptions!$H$25)),BC$5<=IF(I7="Core",D7,IF(I7="AI",Assumptions!$H$24,Assumptions!$H$25)+D7-C7),IF(I7="Core",1,IF(I7="AI",'Start Here'!$B$7,'Start Here'!$B$8))=1),1,0) -> 0 | BD7: =IF(AND(BD$5>=IF(I7="Core",C7,IF(I7="AI",Assumptions!$H$24,Assumptions!$H$25)),BD$5<=IF(I7="Core",D7,IF(I7="AI",Assumptions!$H$24,Assumptions!$H$25)+D7-C7),IF(I7="Core",1,IF(I7="AI",'Start Here'!$B$7,'Start Here'!$B$8))=1),1,0) -> 0 | BE7: =IF(AND(BE$5>=IF(I7="Core",C7,IF(I7="AI",Assumptions!$H$24,Assumptions!$H$25)),BE$5<=IF(I7="Core",D7,IF(I7="AI",Assumptions!$H$24,Assumptions!$H$25)+D7-C7),IF(I7="Core",1,IF(I7="AI",'Start Here'!$B$7,'Start Here'!$B$8))=1),1,0) -> 0 | BF7: =IF(AND(BF$5>=IF(I7="Core",C7,IF(I7="AI",Assumptions!$H$24,Assumptions!$H$25)),BF$5<=IF(I7="Core",D7,IF(I7="AI",Assumptions!$H$24,Assumptions!$H$25)+D7-C7),IF(I7="Core",1,IF(I7="AI",'Start Here'!$B$7,'Start Here'!$B$8))=1),1,0) -> 0 | BG7: =IF(AND(BG$5>=IF(I7="Core",C7,IF(I7="AI",Assumptions!$H$24,Assumptions!$H$25)),BG$5<=IF(I7="Core",D7,IF(I7="AI",Assumptions!$H$24,Assumptions!$H$25)+D7-C7),IF(I7="Core",1,IF(I7="AI",'Start Here'!$B$7,'Start Here'!$B$8))=1),1,0) -> 0 | BH7: =IF(AND(BH$5>=IF(I7="Core",C7,IF(I7="AI",Assumptions!$H$24,Assumptions!$H$25)),BH$5<=IF(I7="Core",D7,IF(I7="AI",Assumptions!$H$24,Assumptions!$H$25)+D7-C7),IF(I7="Core",1,IF(I7="AI",'Start Here'!$B$7,'Start Here'!$B$8))=1),1,0) -> 0 | BI7: =IF(AND(BI$5>=IF(I7="Core",C7,IF(I7="AI",Assumptions!$H$24,Assumptions!$H$25)),BI$5<=IF(I7="Core",D7,IF(I7="AI",Assumptions!$H$24,Assumptions!$H$25)+D7-C7),IF(I7="Core",1,IF(I7="AI",'Start Here'!$B$7,'Start Here'!$B$8))=1),1,0) -> 0 | BJ7: =IF(AND(BJ$5>=IF(I7="Core",C7,IF(I7="AI",Assumptions!$H$24,Assumptions!$H$25)),BJ$5<=IF(I7="Core",D7,IF(I7="AI",Assumptions!$H$24,Assumptions!$H$25)+D7-C7),IF(I7="Core",1,IF(I7="AI",'Start Here'!$B$7,'Start Here'!$B$8))=1),1,0) -> 0 | BK7: =IF(AND(BK$5>=IF(I7="Core",C7,IF(I7="AI",Assumptions!$H$24,Assumptions!$H$25)),BK$5<=IF(I7="Core",D7,IF(I7="AI",Assumptions!$H$24,Assumptions!$H$25)+D7-C7),IF(I7="Core",1,IF(I7="AI",'Start Here'!$B$7,'Start Here'!$B$8))=1),1,0) -> 0 | BL7: =IF(AND(BL$5>=IF(I7="Core",C7,IF(I7="AI",Assumptions!$H$24,Assumptions!$H$25)),BL$5<=IF(I7="Core",D7,IF(I7="AI",Assumptions!$H$24,Assumptions!$H$25)+D7-C7),IF(I7="Core",1,IF(I7="AI",'Start Here'!$B$7,'Start Here'!$B$8))=1),1,0) -> 0 | BM7: =IF(AND(BM$5>=IF(I7="Core",C7,IF(I7="AI",Assumptions!$H$24,Assumptions!$H$25)),BM$5<=IF(I7="Core",D7,IF(I7="AI",Assumptions!$H$24,Assumptions!$H$25)+D7-C7),IF(I7="Core",1,IF(I7="AI",'Start Here'!$B$7,'Start Here'!$B$8))=1),1,0) -> 0 | BN7: =IF(AND(BN$5>=IF(I7="Core",C7,IF(I7="AI",Assumptions!$H$24,Assumptions!$H$25)),BN$5<=IF(I7="Core",D7,IF(I7="AI",Assumptions!$H$24,Assumptions!$H$25)+D7-C7),IF(I7="Core",1,IF(I7="AI",'Start Here'!$B$7,'Start Here'!$B$8))=1),1,0) -> 0 | BO7: =IF(AND(BO$5>=IF(I7="Core",C7,IF(I7="AI",Assumptions!$H$24,Assumptions!$H$25)),BO$5<=IF(I7="Core",D7,IF(I7="AI",Assumptions!$H$24,Assumptions!$H$25)+D7-C7),IF(I7="Core",1,IF(I7="AI",'Start Here'!$B$7,'Start Here'!$B$8))=1),1,0) -> 0 | BP7: =IF(AND(BP$5>=IF(I7="Core",C7,IF(I7="AI",Assumptions!$H$24,Assumptions!$H$25)),BP$5<=IF(I7="Core",D7,IF(I7="AI",Assumptions!$H$24,Assumptions!$H$25)+D7-C7),IF(I7="Core",1,IF(I7="AI",'Start Here'!$B$7,'Start Here'!$B$8))=1),1,0) -> 0 | BQ7: =IF(AND(BQ$5>=IF(I7="Core",C7,IF(I7="AI",Assumptions!$H$24,Assumptions!$H$25)),BQ$5<=IF(I7="Core",D7,IF(I7="AI",Assumptions!$H$24,Assumptions!$H$25)+D7-C7),IF(I7="Core",1,IF(I7="AI",'Start Here'!$B$7,'Start Here'!$B$8))=1),1,0) -> 0 | BR7: =IF(AND(BR$5>=IF(I7="Core",C7,IF(I7="AI",Assumptions!$H$24,Assumptions!$H$25)),BR$5<=IF(I7="Core",D7,IF(I7="AI",Assumptions!$H$24,Assumptions!$H$25)+D7-C7),IF(I7="Core",1,IF(I7="AI",'Start Here'!$B$7,'Start Here'!$B$8))=1),1,0) -> 0
A8: G3 | B8: Synthetic-data pilot only | C8: 9 | D8: 11 | E8: G2 | F8: QA / implementation | G8: Synthetic migration reconciliation, restore/rollback, load and negative isolation tests; no customer PHI. | H8: Medium; −1/+2 months | I8: Core | J8: Mapping loss, concurrency and recovery | K8: =IF(AND(K$5>=IF(I8="Core",C8,IF(I8="AI",Assumptions!$H$24,Assumptions!$H$25)),K$5<=IF(I8="Core",D8,IF(I8="AI",Assumptions!$H$24,Assumptions!$H$25)+D8-C8),IF(I8="Core",1,IF(I8="AI",'Start Here'!$B$7,'Start Here'!$B$8))=1),1,0) -> 0 | L8: =IF(AND(L$5>=IF(I8="Core",C8,IF(I8="AI",Assumptions!$H$24,Assumptions!$H$25)),L$5<=IF(I8="Core",D8,IF(I8="AI",Assumptions!$H$24,Assumptions!$H$25)+D8-C8),IF(I8="Core",1,IF(I8="AI",'Start Here'!$B$7,'Start Here'!$B$8))=1),1,0) -> 0 | M8: =IF(AND(M$5>=IF(I8="Core",C8,IF(I8="AI",Assumptions!$H$24,Assumptions!$H$25)),M$5<=IF(I8="Core",D8,IF(I8="AI",Assumptions!$H$24,Assumptions!$H$25)+D8-C8),IF(I8="Core",1,IF(I8="AI",'Start Here'!$B$7,'Start Here'!$B$8))=1),1,0) -> 0 | N8: =IF(AND(N$5>=IF(I8="Core",C8,IF(I8="AI",Assumptions!$H$24,Assumptions!$H$25)),N$5<=IF(I8="Core",D8,IF(I8="AI",Assumptions!$H$24,Assumptions!$H$25)+D8-C8),IF(I8="Core",1,IF(I8="AI",'Start Here'!$B$7,'Start Here'!$B$8))=1),1,0) -> 0 | O8: =IF(AND(O$5>=IF(I8="Core",C8,IF(I8="AI",Assumptions!$H$24,Assumptions!$H$25)),O$5<=IF(I8="Core",D8,IF(I8="AI",Assumptions!$H$24,Assumptions!$H$25)+D8-C8),IF(I8="Core",1,IF(I8="AI",'Start Here'!$B$7,'Start Here'!$B$8))=1),1,0) -> 0 | P8: =IF(AND(P$5>=IF(I8="Core",C8,IF(I8="AI",Assumptions!$H$24,Assumptions!$H$25)),P$5<=IF(I8="Core",D8,IF(I8="AI",Assumptions!$H$24,Assumptions!$H$25)+D8-C8),IF(I8="Core",1,IF(I8="AI",'Start Here'!$B$7,'Start Here'!$B$8))=1),1,0) -> 0 | Q8: =IF(AND(Q$5>=IF(I8="Core",C8,IF(I8="AI",Assumptions!$H$24,Assumptions!$H$25)),Q$5<=IF(I8="Core",D8,IF(I8="AI",Assumptions!$H$24,Assumptions!$H$25)+D8-C8),IF(I8="Core",1,IF(I8="AI",'Start Here'!$B$7,'Start Here'!$B$8))=1),1,0) -> 0 | R8: =IF(AND(R$5>=IF(I8="Core",C8,IF(I8="AI",Assumptions!$H$24,Assumptions!$H$25)),R$5<=IF(I8="Core",D8,IF(I8="AI",Assumptions!$H$24,Assumptions!$H$25)+D8-C8),IF(I8="Core",1,IF(I8="AI",'Start Here'!$B$7,'Start Here'!$B$8))=1),1,0) -> 0 | S8: =IF(AND(S$5>=IF(I8="Core",C8,IF(I8="AI",Assumptions!$H$24,Assumptions!$H$25)),S$5<=IF(I8="Core",D8,IF(I8="AI",Assumptions!$H$24,Assumptions!$H$25)+D8-C8),IF(I8="Core",1,IF(I8="AI",'Start Here'!$B$7,'Start Here'!$B$8))=1),1,0) -> 1 | T8: =IF(AND(T$5>=IF(I8="Core",C8,IF(I8="AI",Assumptions!$H$24,Assumptions!$H$25)),T$5<=IF(I8="Core",D8,IF(I8="AI",Assumptions!$H$24,Assumptions!$H$25)+D8-C8),IF(I8="Core",1,IF(I8="AI",'Start Here'!$B$7,'Start Here'!$B$8))=1),1,0) -> 1 | U8: =IF(AND(U$5>=IF(I8="Core",C8,IF(I8="AI",Assumptions!$H$24,Assumptions!$H$25)),U$5<=IF(I8="Core",D8,IF(I8="AI",Assumptions!$H$24,Assumptions!$H$25)+D8-C8),IF(I8="Core",1,IF(I8="AI",'Start Here'!$B$7,'Start Here'!$B$8))=1),1,0) -> 1 | V8: =IF(AND(V$5>=IF(I8="Core",C8,IF(I8="AI",Assumptions!$H$24,Assumptions!$H$25)),V$5<=IF(I8="Core",D8,IF(I8="AI",Assumptions!$H$24,Assumptions!$H$25)+D8-C8),IF(I8="Core",1,IF(I8="AI",'Start Here'!$B$7,'Start Here'!$B$8))=1),1,0) -> 0 | W8: =IF(AND(W$5>=IF(I8="Core",C8,IF(I8="AI",Assumptions!$H$24,Assumptions!$H$25)),W$5<=IF(I8="Core",D8,IF(I8="AI",Assumptions!$H$24,Assumptions!$H$25)+D8-C8),IF(I8="Core",1,IF(I8="AI",'Start Here'!$B$7,'Start Here'!$B$8))=1),1,0) -> 0 | X8: =IF(AND(X$5>=IF(I8="Core",C8,IF(I8="AI",Assumptions!$H$24,Assumptions!$H$25)),X$5<=IF(I8="Core",D8,IF(I8="AI",Assumptions!$H$24,Assumptions!$H$25)+D8-C8),IF(I8="Core",1,IF(I8="AI",'Start Here'!$B$7,'Start Here'!$B$8))=1),1,0) -> 0 | Y8: =IF(AND(Y$5>=IF(I8="Core",C8,IF(I8="AI",Assumptions!$H$24,Assumptions!$H$25)),Y$5<=IF(I8="Core",D8,IF(I8="AI",Assumptions!$H$24,Assumptions!$H$25)+D8-C8),IF(I8="Core",1,IF(I8="AI",'Start Here'!$B$7,'Start Here'!$B$8))=1),1,0) -> 0 | Z8: =IF(AND(Z$5>=IF(I8="Core",C8,IF(I8="AI",Assumptions!$H$24,Assumptions!$H$25)),Z$5<=IF(I8="Core",D8,IF(I8="AI",Assumptions!$H$24,Assumptions!$H$25)+D8-C8),IF(I8="Core",1,IF(I8="AI",'Start Here'!$B$7,'Start Here'!$B$8))=1),1,0) -> 0 | AA8: =IF(AND(AA$5>=IF(I8="Core",C8,IF(I8="AI",Assumptions!$H$24,Assumptions!$H$25)),AA$5<=IF(I8="Core",D8,IF(I8="AI",Assumptions!$H$24,Assumptions!$H$25)+D8-C8),IF(I8="Core",1,IF(I8="AI",'Start Here'!$B$7,'Start Here'!$B$8))=1),1,0) -> 0 | AB8: =IF(AND(AB$5>=IF(I8="Core",C8,IF(I8="AI",Assumptions!$H$24,Assumptions!$H$25)),AB$5<=IF(I8="Core",D8,IF(I8="AI",Assumptions!$H$24,Assumptions!$H$25)+D8-C8),IF(I8="Core",1,IF(I8="AI",'Start Here'!$B$7,'Start Here'!$B$8))=1),1,0) -> 0 | AC8: =IF(AND(AC$5>=IF(I8="Core",C8,IF(I8="AI",Assumptions!$H$24,Assumptions!$H$25)),AC$5<=IF(I8="Core",D8,IF(I8="AI",Assumptions!$H$24,Assumptions!$H$25)+D8-C8),IF(I8="Core",1,IF(I8="AI",'Start Here'!$B$7,'Start Here'!$B$8))=1),1,0) -> 0 | AD8: =IF(AND(AD$5>=IF(I8="Core",C8,IF(I8="AI",Assumptions!$H$24,Assumptions!$H$25)),AD$5<=IF(I8="Core",D8,IF(I8="AI",Assumptions!$H$24,Assumptions!$H$25)+D8-C8),IF(I8="Core",1,IF(I8="AI",'Start Here'!$B$7,'Start Here'!$B$8))=1),1,0) -> 0 | AE8: =IF(AND(AE$5>=IF(I8="Core",C8,IF(I8="AI",Assumptions!$H$24,Assumptions!$H$25)),AE$5<=IF(I8="Core",D8,IF(I8="AI",Assumptions!$H$24,Assumptions!$H$25)+D8-C8),IF(I8="Core",1,IF(I8="AI",'Start Here'!$B$7,'Start Here'!$B$8))=1),1,0) -> 0 | AF8: =IF(AND(AF$5>=IF(I8="Core",C8,IF(I8="AI",Assumptions!$H$24,Assumptions!$H$25)),AF$5<=IF(I8="Core",D8,IF(I8="AI",Assumptions!$H$24,Assumptions!$H$25)+D8-C8),IF(I8="Core",1,IF(I8="AI",'Start Here'!$B$7,'Start Here'!$B$8))=1),1,0) -> 0 | AG8: =IF(AND(AG$5>=IF(I8="Core",C8,IF(I8="AI",Assumptions!$H$24,Assumptions!$H$25)),AG$5<=IF(I8="Core",D8,IF(I8="AI",Assumptions!$H$24,Assumptions!$H$25)+D8-C8),IF(I8="Core",1,IF(I8="AI",'Start Here'!$B$7,'Start Here'!$B$8))=1),1,0) -> 0 | AH8: =IF(AND(AH$5>=IF(I8="Core",C8,IF(I8="AI",Assumptions!$H$24,Assumptions!$H$25)),AH$5<=IF(I8="Core",D8,IF(I8="AI",Assumptions!$H$24,Assumptions!$H$25)+D8-C8),IF(I8="Core",1,IF(I8="AI",'Start Here'!$B$7,'Start Here'!$B$8))=1),1,0) -> 0 | AI8: =IF(AND(AI$5>=IF(I8="Core",C8,IF(I8="AI",Assumptions!$H$24,Assumptions!$H$25)),AI$5<=IF(I8="Core",D8,IF(I8="AI",Assumptions!$H$24,Assumptions!$H$25)+D8-C8),IF(I8="Core",1,IF(I8="AI",'Start Here'!$B$7,'Start Here'!$B$8))=1),1,0) -> 0 | AJ8: =IF(AND(AJ$5>=IF(I8="Core",C8,IF(I8="AI",Assumptions!$H$24,Assumptions!$H$25)),AJ$5<=IF(I8="Core",D8,IF(I8="AI",Assumptions!$H$24,Assumptions!$H$25)+D8-C8),IF(I8="Core",1,IF(I8="AI",'Start Here'!$B$7,'Start Here'!$B$8))=1),1,0) -> 0 | AK8: =IF(AND(AK$5>=IF(I8="Core",C8,IF(I8="AI",Assumptions!$H$24,Assumptions!$H$25)),AK$5<=IF(I8="Core",D8,IF(I8="AI",Assumptions!$H$24,Assumptions!$H$25)+D8-C8),IF(I8="Core",1,IF(I8="AI",'Start Here'!$B$7,'Start Here'!$B$8))=1),1,0) -> 0 | AL8: =IF(AND(AL$5>=IF(I8="Core",C8,IF(I8="AI",Assumptions!$H$24,Assumptions!$H$25)),AL$5<=IF(I8="Core",D8,IF(I8="AI",Assumptions!$H$24,Assumptions!$H$25)+D8-C8),IF(I8="Core",1,IF(I8="AI",'Start Here'!$B$7,'Start Here'!$B$8))=1),1,0) -> 0 | AM8: =IF(AND(AM$5>=IF(I8="Core",C8,IF(I8="AI",Assumptions!$H$24,Assumptions!$H$25)),AM$5<=IF(I8="Core",D8,IF(I8="AI",Assumptions!$H$24,Assumptions!$H$25)+D8-C8),IF(I8="Core",1,IF(I8="AI",'Start Here'!$B$7,'Start Here'!$B$8))=1),1,0) -> 0 | AN8: =IF(AND(AN$5>=IF(I8="Core",C8,IF(I8="AI",Assumptions!$H$24,Assumptions!$H$25)),AN$5<=IF(I8="Core",D8,IF(I8="AI",Assumptions!$H$24,Assumptions!$H$25)+D8-C8),IF(I8="Core",1,IF(I8="AI",'Start Here'!$B$7,'Start Here'!$B$8))=1),1,0) -> 0 | AO8: =IF(AND(AO$5>=IF(I8="Core",C8,IF(I8="AI",Assumptions!$H$24,Assumptions!$H$25)),AO$5<=IF(I8="Core",D8,IF(I8="AI",Assumptions!$H$24,Assumptions!$H$25)+D8-C8),IF(I8="Core",1,IF(I8="AI",'Start Here'!$B$7,'Start Here'!$B$8))=1),1,0) -> 0 | AP8: =IF(AND(AP$5>=IF(I8="Core",C8,IF(I8="AI",Assumptions!$H$24,Assumptions!$H$25)),AP$5<=IF(I8="Core",D8,IF(I8="AI",Assumptions!$H$24,Assumptions!$H$25)+D8-C8),IF(I8="Core",1,IF(I8="AI",'Start Here'!$B$7,'Start Here'!$B$8))=1),1,0) -> 0 | AQ8: =IF(AND(AQ$5>=IF(I8="Core",C8,IF(I8="AI",Assumptions!$H$24,Assumptions!$H$25)),AQ$5<=IF(I8="Core",D8,IF(I8="AI",Assumptions!$H$24,Assumptions!$H$25)+D8-C8),IF(I8="Core",1,IF(I8="AI",'Start Here'!$B$7,'Start Here'!$B$8))=1),1,0) -> 0 | AR8: =IF(AND(AR$5>=IF(I8="Core",C8,IF(I8="AI",Assumptions!$H$24,Assumptions!$H$25)),AR$5<=IF(I8="Core",D8,IF(I8="AI",Assumptions!$H$24,Assumptions!$H$25)+D8-C8),IF(I8="Core",1,IF(I8="AI",'Start Here'!$B$7,'Start Here'!$B$8))=1),1,0) -> 0 | AS8: =IF(AND(AS$5>=IF(I8="Core",C8,IF(I8="AI",Assumptions!$H$24,Assumptions!$H$25)),AS$5<=IF(I8="Core",D8,IF(I8="AI",Assumptions!$H$24,Assumptions!$H$25)+D8-C8),IF(I8="Core",1,IF(I8="AI",'Start Here'!$B$7,'Start Here'!$B$8))=1),1,0) -> 0 | AT8: =IF(AND(AT$5>=IF(I8="Core",C8,IF(I8="AI",Assumptions!$H$24,Assumptions!$H$25)),AT$5<=IF(I8="Core",D8,IF(I8="AI",Assumptions!$H$24,Assumptions!$H$25)+D8-C8),IF(I8="Core",1,IF(I8="AI",'Start Here'!$B$7,'Start Here'!$B$8))=1),1,0) -> 0 | AU8: =IF(AND(AU$5>=IF(I8="Core",C8,IF(I8="AI",Assumptions!$H$24,Assumptions!$H$25)),AU$5<=IF(I8="Core",D8,IF(I8="AI",Assumptions!$H$24,Assumptions!$H$25)+D8-C8),IF(I8="Core",1,IF(I8="AI",'Start Here'!$B$7,'Start Here'!$B$8))=1),1,0) -> 0 | AV8: =IF(AND(AV$5>=IF(I8="Core",C8,IF(I8="AI",Assumptions!$H$24,Assumptions!$H$25)),AV$5<=IF(I8="Core",D8,IF(I8="AI",Assumptions!$H$24,Assumptions!$H$25)+D8-C8),IF(I8="Core",1,IF(I8="AI",'Start Here'!$B$7,'Start Here'!$B$8))=1),1,0) -> 0 | AW8: =IF(AND(AW$5>=IF(I8="Core",C8,IF(I8="AI",Assumptions!$H$24,Assumptions!$H$25)),AW$5<=IF(I8="Core",D8,IF(I8="AI",Assumptions!$H$24,Assumptions!$H$25)+D8-C8),IF(I8="Core",1,IF(I8="AI",'Start Here'!$B$7,'Start Here'!$B$8))=1),1,0) -> 0 | AX8: =IF(AND(AX$5>=IF(I8="Core",C8,IF(I8="AI",Assumptions!$H$24,Assumptions!$H$25)),AX$5<=IF(I8="Core",D8,IF(I8="AI",Assumptions!$H$24,Assumptions!$H$25)+D8-C8),IF(I8="Core",1,IF(I8="AI",'Start Here'!$B$7,'Start Here'!$B$8))=1),1,0) -> 0 | AY8: =IF(AND(AY$5>=IF(I8="Core",C8,IF(I8="AI",Assumptions!$H$24,Assumptions!$H$25)),AY$5<=IF(I8="Core",D8,IF(I8="AI",Assumptions!$H$24,Assumptions!$H$25)+D8-C8),IF(I8="Core",1,IF(I8="AI",'Start Here'!$B$7,'Start Here'!$B$8))=1),1,0) -> 0 | AZ8: =IF(AND(AZ$5>=IF(I8="Core",C8,IF(I8="AI",Assumptions!$H$24,Assumptions!$H$25)),AZ$5<=IF(I8="Core",D8,IF(I8="AI",Assumptions!$H$24,Assumptions!$H$25)+D8-C8),IF(I8="Core",1,IF(I8="AI",'Start Here'!$B$7,'Start Here'!$B$8))=1),1,0) -> 0 | BA8: =IF(AND(BA$5>=IF(I8="Core",C8,IF(I8="AI",Assumptions!$H$24,Assumptions!$H$25)),BA$5<=IF(I8="Core",D8,IF(I8="AI",Assumptions!$H$24,Assumptions!$H$25)+D8-C8),IF(I8="Core",1,IF(I8="AI",'Start Here'!$B$7,'Start Here'!$B$8))=1),1,0) -> 0 | BB8: =IF(AND(BB$5>=IF(I8="Core",C8,IF(I8="AI",Assumptions!$H$24,Assumptions!$H$25)),BB$5<=IF(I8="Core",D8,IF(I8="AI",Assumptions!$H$24,Assumptions!$H$25)+D8-C8),IF(I8="Core",1,IF(I8="AI",'Start Here'!$B$7,'Start Here'!$B$8))=1),1,0) -> 0 | BC8: =IF(AND(BC$5>=IF(I8="Core",C8,IF(I8="AI",Assumptions!$H$24,Assumptions!$H$25)),BC$5<=IF(I8="Core",D8,IF(I8="AI",Assumptions!$H$24,Assumptions!$H$25)+D8-C8),IF(I8="Core",1,IF(I8="AI",'Start Here'!$B$7,'Start Here'!$B$8))=1),1,0) -> 0 | BD8: =IF(AND(BD$5>=IF(I8="Core",C8,IF(I8="AI",Assumptions!$H$24,Assumptions!$H$25)),BD$5<=IF(I8="Core",D8,IF(I8="AI",Assumptions!$H$24,Assumptions!$H$25)+D8-C8),IF(I8="Core",1,IF(I8="AI",'Start Here'!$B$7,'Start Here'!$B$8))=1),1,0) -> 0 | BE8: =IF(AND(BE$5>=IF(I8="Core",C8,IF(I8="AI",Assumptions!$H$24,Assumptions!$H$25)),BE$5<=IF(I8="Core",D8,IF(I8="AI",Assumptions!$H$24,Assumptions!$H$25)+D8-C8),IF(I8="Core",1,IF(I8="AI",'Start Here'!$B$7,'Start Here'!$B$8))=1),1,0) -> 0 | BF8: =IF(AND(BF$5>=IF(I8="Core",C8,IF(I8="AI",Assumptions!$H$24,Assumptions!$H$25)),BF$5<=IF(I8="Core",D8,IF(I8="AI",Assumptions!$H$24,Assumptions!$H$25)+D8-C8),IF(I8="Core",1,IF(I8="AI",'Start Here'!$B$7,'Start Here'!$B$8))=1),1,0) -> 0 | BG8: =IF(AND(BG$5>=IF(I8="Core",C8,IF(I8="AI",Assumptions!$H$24,Assumptions!$H$25)),BG$5<=IF(I8="Core",D8,IF(I8="AI",Assumptions!$H$24,Assumptions!$H$25)+D8-C8),IF(I8="Core",1,IF(I8="AI",'Start Here'!$B$7,'Start Here'!$B$8))=1),1,0) -> 0 | BH8: =IF(AND(BH$5>=IF(I8="Core",C8,IF(I8="AI",Assumptions!$H$24,Assumptions!$H$25)),BH$5<=IF(I8="Core",D8,IF(I8="AI",Assumptions!$H$24,Assumptions!$H$25)+D8-C8),IF(I8="Core",1,IF(I8="AI",'Start Here'!$B$7,'Start Here'!$B$8))=1),1,0) -> 0 | BI8: =IF(AND(BI$5>=IF(I8="Core",C8,IF(I8="AI",Assumptions!$H$24,Assumptions!$H$25)),BI$5<=IF(I8="Core",D8,IF(I8="AI",Assumptions!$H$24,Assumptions!$H$25)+D8-C8),IF(I8="Core",1,IF(I8="AI",'Start Here'!$B$7,'Start Here'!$B$8))=1),1,0) -> 0 | BJ8: =IF(AND(BJ$5>=IF(I8="Core",C8,IF(I8="AI",Assumptions!$H$24,Assumptions!$H$25)),BJ$5<=IF(I8="Core",D8,IF(I8="AI",Assumptions!$H$24,Assumptions!$H$25)+D8-C8),IF(I8="Core",1,IF(I8="AI",'Start Here'!$B$7,'Start Here'!$B$8))=1),1,0) -> 0 | BK8: =IF(AND(BK$5>=IF(I8="Core",C8,IF(I8="AI",Assumptions!$H$24,Assumptions!$H$25)),BK$5<=IF(I8="Core",D8,IF(I8="AI",Assumptions!$H$24,Assumptions!$H$25)+D8-C8),IF(I8="Core",1,IF(I8="AI",'Start Here'!$B$7,'Start Here'!$B$8))=1),1,0) -> 0 | BL8: =IF(AND(BL$5>=IF(I8="Core",C8,IF(I8="AI",Assumptions!$H$24,Assumptions!$H$25)),BL$5<=IF(I8="Core",D8,IF(I8="AI",Assumptions!$H$24,Assumptions!$H$25)+D8-C8),IF(I8="Core",1,IF(I8="AI",'Start Here'!$B$7,'Start Here'!$B$8))=1),1,0) -> 0 | BM8: =IF(AND(BM$5>=IF(I8="Core",C8,IF(I8="AI",Assumptions!$H$24,Assumptions!$H$25)),BM$5<=IF(I8="Core",D8,IF(I8="AI",Assumptions!$H$24,Assumptions!$H$25)+D8-C8),IF(I8="Core",1,IF(I8="AI",'Start Here'!$B$7,'Start Here'!$B$8))=1),1,0) -> 0 | BN8: =IF(AND(BN$5>=IF(I8="Core",C8,IF(I8="AI",Assumptions!$H$24,Assumptions!$H$25)),BN$5<=IF(I8="Core",D8,IF(I8="AI",Assumptions!$H$24,Assumptions!$H$25)+D8-C8),IF(I8="Core",1,IF(I8="AI",'Start Here'!$B$7,'Start Here'!$B$8))=1),1,0) -> 0 | BO8: =IF(AND(BO$5>=IF(I8="Core",C8,IF(I8="AI",Assumptions!$H$24,Assumptions!$H$25)),BO$5<=IF(I8="Core",D8,IF(I8="AI",Assumptions!$H$24,Assumptions!$H$25)+D8-C8),IF(I8="Core",1,IF(I8="AI",'Start Here'!$B$7,'Start Here'!$B$8))=1),1,0) -> 0 | BP8: =IF(AND(BP$5>=IF(I8="Core",C8,IF(I8="AI",Assumptions!$H$24,Assumptions!$H$25)),BP$5<=IF(I8="Core",D8,IF(I8="AI",Assumptions!$H$24,Assumptions!$H$25)+D8-C8),IF(I8="Core",1,IF(I8="AI",'Start Here'!$B$7,'Start Here'!$B$8))=1),1,0) -> 0 | BQ8: =IF(AND(BQ$5>=IF(I8="Core",C8,IF(I8="AI",Assumptions!$H$24,Assumptions!$H$25)),BQ$5<=IF(I8="Core",D8,IF(I8="AI",Assumptions!$H$24,Assumptions!$H$25)+D8-C8),IF(I8="Core",1,IF(I8="AI",'Start Here'!$B$7,'Start Here'!$B$8))=1),1,0) -> 0 | BR8: =IF(AND(BR$5>=IF(I8="Core",C8,IF(I8="AI",Assumptions!$H$24,Assumptions!$H$25)),BR$5<=IF(I8="Core",D8,IF(I8="AI",Assumptions!$H$24,Assumptions!$H$25)+D8-C8),IF(I8="Core",1,IF(I8="AI",'Start Here'!$B$7,'Start Here'!$B$8))=1),1,0) -> 0
A9: G4 | B9: Approved customer pilot | C9: 12 | D9: 15 | E9: G3 plus legal/security/clinical approval | F9: Founder / validation | G9: Contracts, service eligibility/BAA where needed, security/clinical sign-off; staged tenant cutover and customer feedback. Stop for safety/control failure. | H9: Low; −1/+4 months | I9: Core | J9: Procurement, remediation, training and clinical risk | K9: =IF(AND(K$5>=IF(I9="Core",C9,IF(I9="AI",Assumptions!$H$24,Assumptions!$H$25)),K$5<=IF(I9="Core",D9,IF(I9="AI",Assumptions!$H$24,Assumptions!$H$25)+D9-C9),IF(I9="Core",1,IF(I9="AI",'Start Here'!$B$7,'Start Here'!$B$8))=1),1,0) -> 0 | L9: =IF(AND(L$5>=IF(I9="Core",C9,IF(I9="AI",Assumptions!$H$24,Assumptions!$H$25)),L$5<=IF(I9="Core",D9,IF(I9="AI",Assumptions!$H$24,Assumptions!$H$25)+D9-C9),IF(I9="Core",1,IF(I9="AI",'Start Here'!$B$7,'Start Here'!$B$8))=1),1,0) -> 0 | M9: =IF(AND(M$5>=IF(I9="Core",C9,IF(I9="AI",Assumptions!$H$24,Assumptions!$H$25)),M$5<=IF(I9="Core",D9,IF(I9="AI",Assumptions!$H$24,Assumptions!$H$25)+D9-C9),IF(I9="Core",1,IF(I9="AI",'Start Here'!$B$7,'Start Here'!$B$8))=1),1,0) -> 0 | N9: =IF(AND(N$5>=IF(I9="Core",C9,IF(I9="AI",Assumptions!$H$24,Assumptions!$H$25)),N$5<=IF(I9="Core",D9,IF(I9="AI",Assumptions!$H$24,Assumptions!$H$25)+D9-C9),IF(I9="Core",1,IF(I9="AI",'Start Here'!$B$7,'Start Here'!$B$8))=1),1,0) -> 0 | O9: =IF(AND(O$5>=IF(I9="Core",C9,IF(I9="AI",Assumptions!$H$24,Assumptions!$H$25)),O$5<=IF(I9="Core",D9,IF(I9="AI",Assumptions!$H$24,Assumptions!$H$25)+D9-C9),IF(I9="Core",1,IF(I9="AI",'Start Here'!$B$7,'Start Here'!$B$8))=1),1,0) -> 0 | P9: =IF(AND(P$5>=IF(I9="Core",C9,IF(I9="AI",Assumptions!$H$24,Assumptions!$H$25)),P$5<=IF(I9="Core",D9,IF(I9="AI",Assumptions!$H$24,Assumptions!$H$25)+D9-C9),IF(I9="Core",1,IF(I9="AI",'Start Here'!$B$7,'Start Here'!$B$8))=1),1,0) -> 0 | Q9: =IF(AND(Q$5>=IF(I9="Core",C9,IF(I9="AI",Assumptions!$H$24,Assumptions!$H$25)),Q$5<=IF(I9="Core",D9,IF(I9="AI",Assumptions!$H$24,Assumptions!$H$25)+D9-C9),IF(I9="Core",1,IF(I9="AI",'Start Here'!$B$7,'Start Here'!$B$8))=1),1,0) -> 0 | R9: =IF(AND(R$5>=IF(I9="Core",C9,IF(I9="AI",Assumptions!$H$24,Assumptions!$H$25)),R$5<=IF(I9="Core",D9,IF(I9="AI",Assumptions!$H$24,Assumptions!$H$25)+D9-C9),IF(I9="Core",1,IF(I9="AI",'Start Here'!$B$7,'Start Here'!$B$8))=1),1,0) -> 0 | S9: =IF(AND(S$5>=IF(I9="Core",C9,IF(I9="AI",Assumptions!$H$24,Assumptions!$H$25)),S$5<=IF(I9="Core",D9,IF(I9="AI",Assumptions!$H$24,Assumptions!$H$25)+D9-C9),IF(I9="Core",1,IF(I9="AI",'Start Here'!$B$7,'Start Here'!$B$8))=1),1,0) -> 0 | T9: =IF(AND(T$5>=IF(I9="Core",C9,IF(I9="AI",Assumptions!$H$24,Assumptions!$H$25)),T$5<=IF(I9="Core",D9,IF(I9="AI",Assumptions!$H$24,Assumptions!$H$25)+D9-C9),IF(I9="Core",1,IF(I9="AI",'Start Here'!$B$7,'Start Here'!$B$8))=1),1,0) -> 0 | U9: =IF(AND(U$5>=IF(I9="Core",C9,IF(I9="AI",Assumptions!$H$24,Assumptions!$H$25)),U$5<=IF(I9="Core",D9,IF(I9="AI",Assumptions!$H$24,Assumptions!$H$25)+D9-C9),IF(I9="Core",1,IF(I9="AI",'Start Here'!$B$7,'Start Here'!$B$8))=1),1,0) -> 0 | V9: =IF(AND(V$5>=IF(I9="Core",C9,IF(I9="AI",Assumptions!$H$24,Assumptions!$H$25)),V$5<=IF(I9="Core",D9,IF(I9="AI",Assumptions!$H$24,Assumptions!$H$25)+D9-C9),IF(I9="Core",1,IF(I9="AI",'Start Here'!$B$7,'Start Here'!$B$8))=1),1,0) -> 1 | W9: =IF(AND(W$5>=IF(I9="Core",C9,IF(I9="AI",Assumptions!$H$24,Assumptions!$H$25)),W$5<=IF(I9="Core",D9,IF(I9="AI",Assumptions!$H$24,Assumptions!$H$25)+D9-C9),IF(I9="Core",1,IF(I9="AI",'Start Here'!$B$7,'Start Here'!$B$8))=1),1,0) -> 1 | X9: =IF(AND(X$5>=IF(I9="Core",C9,IF(I9="AI",Assumptions!$H$24,Assumptions!$H$25)),X$5<=IF(I9="Core",D9,IF(I9="AI",Assumptions!$H$24,Assumptions!$H$25)+D9-C9),IF(I9="Core",1,IF(I9="AI",'Start Here'!$B$7,'Start Here'!$B$8))=1),1,0) -> 1 | Y9: =IF(AND(Y$5>=IF(I9="Core",C9,IF(I9="AI",Assumptions!$H$24,Assumptions!$H$25)),Y$5<=IF(I9="Core",D9,IF(I9="AI",Assumptions!$H$24,Assumptions!$H$25)+D9-C9),IF(I9="Core",1,IF(I9="AI",'Start Here'!$B$7,'Start Here'!$B$8))=1),1,0) -> 1 | Z9: =IF(AND(Z$5>=IF(I9="Core",C9,IF(I9="AI",Assumptions!$H$24,Assumptions!$H$25)),Z$5<=IF(I9="Core",D9,IF(I9="AI",Assumptions!$H$24,Assumptions!$H$25)+D9-C9),IF(I9="Core",1,IF(I9="AI",'Start Here'!$B$7,'Start Here'!$B$8))=1),1,0) -> 0 | AA9: =IF(AND(AA$5>=IF(I9="Core",C9,IF(I9="AI",Assumptions!$H$24,Assumptions!$H$25)),AA$5<=IF(I9="Core",D9,IF(I9="AI",Assumptions!$H$24,Assumptions!$H$25)+D9-C9),IF(I9="Core",1,IF(I9="AI",'Start Here'!$B$7,'Start Here'!$B$8))=1),1,0) -> 0 | AB9: =IF(AND(AB$5>=IF(I9="Core",C9,IF(I9="AI",Assumptions!$H$24,Assumptions!$H$25)),AB$5<=IF(I9="Core",D9,IF(I9="AI",Assumptions!$H$24,Assumptions!$H$25)+D9-C9),IF(I9="Core",1,IF(I9="AI",'Start Here'!$B$7,'Start Here'!$B$8))=1),1,0) -> 0 | AC9: =IF(AND(AC$5>=IF(I9="Core",C9,IF(I9="AI",Assumptions!$H$24,Assumptions!$H$25)),AC$5<=IF(I9="Core",D9,IF(I9="AI",Assumptions!$H$24,Assumptions!$H$25)+D9-C9),IF(I9="Core",1,IF(I9="AI",'Start Here'!$B$7,'Start Here'!$B$8))=1),1,0) -> 0 | AD9: =IF(AND(AD$5>=IF(I9="Core",C9,IF(I9="AI",Assumptions!$H$24,Assumptions!$H$25)),AD$5<=IF(I9="Core",D9,IF(I9="AI",Assumptions!$H$24,Assumptions!$H$25)+D9-C9),IF(I9="Core",1,IF(I9="AI",'Start Here'!$B$7,'Start Here'!$B$8))=1),1,0) -> 0 | AE9: =IF(AND(AE$5>=IF(I9="Core",C9,IF(I9="AI",Assumptions!$H$24,Assumptions!$H$25)),AE$5<=IF(I9="Core",D9,IF(I9="AI",Assumptions!$H$24,Assumptions!$H$25)+D9-C9),IF(I9="Core",1,IF(I9="AI",'Start Here'!$B$7,'Start Here'!$B$8))=1),1,0) -> 0 | AF9: =IF(AND(AF$5>=IF(I9="Core",C9,IF(I9="AI",Assumptions!$H$24,Assumptions!$H$25)),AF$5<=IF(I9="Core",D9,IF(I9="AI",Assumptions!$H$24,Assumptions!$H$25)+D9-C9),IF(I9="Core",1,IF(I9="AI",'Start Here'!$B$7,'Start Here'!$B$8))=1),1,0) -> 0 | AG9: =IF(AND(AG$5>=IF(I9="Core",C9,IF(I9="AI",Assumptions!$H$24,Assumptions!$H$25)),AG$5<=IF(I9="Core",D9,IF(I9="AI",Assumptions!$H$24,Assumptions!$H$25)+D9-C9),IF(I9="Core",1,IF(I9="AI",'Start Here'!$B$7,'Start Here'!$B$8))=1),1,0) -> 0 | AH9: =IF(AND(AH$5>=IF(I9="Core",C9,IF(I9="AI",Assumptions!$H$24,Assumptions!$H$25)),AH$5<=IF(I9="Core",D9,IF(I9="AI",Assumptions!$H$24,Assumptions!$H$25)+D9-C9),IF(I9="Core",1,IF(I9="AI",'Start Here'!$B$7,'Start Here'!$B$8))=1),1,0) -> 0 | AI9: =IF(AND(AI$5>=IF(I9="Core",C9,IF(I9="AI",Assumptions!$H$24,Assumptions!$H$25)),AI$5<=IF(I9="Core",D9,IF(I9="AI",Assumptions!$H$24,Assumptions!$H$25)+D9-C9),IF(I9="Core",1,IF(I9="AI",'Start Here'!$B$7,'Start Here'!$B$8))=1),1,0) -> 0 | AJ9: =IF(AND(AJ$5>=IF(I9="Core",C9,IF(I9="AI",Assumptions!$H$24,Assumptions!$H$25)),AJ$5<=IF(I9="Core",D9,IF(I9="AI",Assumptions!$H$24,Assumptions!$H$25)+D9-C9),IF(I9="Core",1,IF(I9="AI",'Start Here'!$B$7,'Start Here'!$B$8))=1),1,0) -> 0 | AK9: =IF(AND(AK$5>=IF(I9="Core",C9,IF(I9="AI",Assumptions!$H$24,Assumptions!$H$25)),AK$5<=IF(I9="Core",D9,IF(I9="AI",Assumptions!$H$24,Assumptions!$H$25)+D9-C9),IF(I9="Core",1,IF(I9="AI",'Start Here'!$B$7,'Start Here'!$B$8))=1),1,0) -> 0 | AL9: =IF(AND(AL$5>=IF(I9="Core",C9,IF(I9="AI",Assumptions!$H$24,Assumptions!$H$25)),AL$5<=IF(I9="Core",D9,IF(I9="AI",Assumptions!$H$24,Assumptions!$H$25)+D9-C9),IF(I9="Core",1,IF(I9="AI",'Start Here'!$B$7,'Start Here'!$B$8))=1),1,0) -> 0 | AM9: =IF(AND(AM$5>=IF(I9="Core",C9,IF(I9="AI",Assumptions!$H$24,Assumptions!$H$25)),AM$5<=IF(I9="Core",D9,IF(I9="AI",Assumptions!$H$24,Assumptions!$H$25)+D9-C9),IF(I9="Core",1,IF(I9="AI",'Start Here'!$B$7,'Start Here'!$B$8))=1),1,0) -> 0 | AN9: =IF(AND(AN$5>=IF(I9="Core",C9,IF(I9="AI",Assumptions!$H$24,Assumptions!$H$25)),AN$5<=IF(I9="Core",D9,IF(I9="AI",Assumptions!$H$24,Assumptions!$H$25)+D9-C9),IF(I9="Core",1,IF(I9="AI",'Start Here'!$B$7,'Start Here'!$B$8))=1),1,0) -> 0 | AO9: =IF(AND(AO$5>=IF(I9="Core",C9,IF(I9="AI",Assumptions!$H$24,Assumptions!$H$25)),AO$5<=IF(I9="Core",D9,IF(I9="AI",Assumptions!$H$24,Assumptions!$H$25)+D9-C9),IF(I9="Core",1,IF(I9="AI",'Start Here'!$B$7,'Start Here'!$B$8))=1),1,0) -> 0 | AP9: =IF(AND(AP$5>=IF(I9="Core",C9,IF(I9="AI",Assumptions!$H$24,Assumptions!$H$25)),AP$5<=IF(I9="Core",D9,IF(I9="AI",Assumptions!$H$24,Assumptions!$H$25)+D9-C9),IF(I9="Core",1,IF(I9="AI",'Start Here'!$B$7,'Start Here'!$B$8))=1),1,0) -> 0 | AQ9: =IF(AND(AQ$5>=IF(I9="Core",C9,IF(I9="AI",Assumptions!$H$24,Assumptions!$H$25)),AQ$5<=IF(I9="Core",D9,IF(I9="AI",Assumptions!$H$24,Assumptions!$H$25)+D9-C9),IF(I9="Core",1,IF(I9="AI",'Start Here'!$B$7,'Start Here'!$B$8))=1),1,0) -> 0 | AR9: =IF(AND(AR$5>=IF(I9="Core",C9,IF(I9="AI",Assumptions!$H$24,Assumptions!$H$25)),AR$5<=IF(I9="Core",D9,IF(I9="AI",Assumptions!$H$24,Assumptions!$H$25)+D9-C9),IF(I9="Core",1,IF(I9="AI",'Start Here'!$B$7,'Start Here'!$B$8))=1),1,0) -> 0 | AS9: =IF(AND(AS$5>=IF(I9="Core",C9,IF(I9="AI",Assumptions!$H$24,Assumptions!$H$25)),AS$5<=IF(I9="Core",D9,IF(I9="AI",Assumptions!$H$24,Assumptions!$H$25)+D9-C9),IF(I9="Core",1,IF(I9="AI",'Start Here'!$B$7,'Start Here'!$B$8))=1),1,0) -> 0 | AT9: =IF(AND(AT$5>=IF(I9="Core",C9,IF(I9="AI",Assumptions!$H$24,Assumptions!$H$25)),AT$5<=IF(I9="Core",D9,IF(I9="AI",Assumptions!$H$24,Assumptions!$H$25)+D9-C9),IF(I9="Core",1,IF(I9="AI",'Start Here'!$B$7,'Start Here'!$B$8))=1),1,0) -> 0 | AU9: =IF(AND(AU$5>=IF(I9="Core",C9,IF(I9="AI",Assumptions!$H$24,Assumptions!$H$25)),AU$5<=IF(I9="Core",D9,IF(I9="AI",Assumptions!$H$24,Assumptions!$H$25)+D9-C9),IF(I9="Core",1,IF(I9="AI",'Start Here'!$B$7,'Start Here'!$B$8))=1),1,0) -> 0 | AV9: =IF(AND(AV$5>=IF(I9="Core",C9,IF(I9="AI",Assumptions!$H$24,Assumptions!$H$25)),AV$5<=IF(I9="Core",D9,IF(I9="AI",Assumptions!$H$24,Assumptions!$H$25)+D9-C9),IF(I9="Core",1,IF(I9="AI",'Start Here'!$B$7,'Start Here'!$B$8))=1),1,0) -> 0 | AW9: =IF(AND(AW$5>=IF(I9="Core",C9,IF(I9="AI",Assumptions!$H$24,Assumptions!$H$25)),AW$5<=IF(I9="Core",D9,IF(I9="AI",Assumptions!$H$24,Assumptions!$H$25)+D9-C9),IF(I9="Core",1,IF(I9="AI",'Start Here'!$B$7,'Start Here'!$B$8))=1),1,0) -> 0 | AX9: =IF(AND(AX$5>=IF(I9="Core",C9,IF(I9="AI",Assumptions!$H$24,Assumptions!$H$25)),AX$5<=IF(I9="Core",D9,IF(I9="AI",Assumptions!$H$24,Assumptions!$H$25)+D9-C9),IF(I9="Core",1,IF(I9="AI",'Start Here'!$B$7,'Start Here'!$B$8))=1),1,0) -> 0 | AY9: =IF(AND(AY$5>=IF(I9="Core",C9,IF(I9="AI",Assumptions!$H$24,Assumptions!$H$25)),AY$5<=IF(I9="Core",D9,IF(I9="AI",Assumptions!$H$24,Assumptions!$H$25)+D9-C9),IF(I9="Core",1,IF(I9="AI",'Start Here'!$B$7,'Start Here'!$B$8))=1),1,0) -> 0 | AZ9: =IF(AND(AZ$5>=IF(I9="Core",C9,IF(I9="AI",Assumptions!$H$24,Assumptions!$H$25)),AZ$5<=IF(I9="Core",D9,IF(I9="AI",Assumptions!$H$24,Assumptions!$H$25)+D9-C9),IF(I9="Core",1,IF(I9="AI",'Start Here'!$B$7,'Start Here'!$B$8))=1),1,0) -> 0 | BA9: =IF(AND(BA$5>=IF(I9="Core",C9,IF(I9="AI",Assumptions!$H$24,Assumptions!$H$25)),BA$5<=IF(I9="Core",D9,IF(I9="AI",Assumptions!$H$24,Assumptions!$H$25)+D9-C9),IF(I9="Core",1,IF(I9="AI",'Start Here'!$B$7,'Start Here'!$B$8))=1),1,0) -> 0 | BB9: =IF(AND(BB$5>=IF(I9="Core",C9,IF(I9="AI",Assumptions!$H$24,Assumptions!$H$25)),BB$5<=IF(I9="Core",D9,IF(I9="AI",Assumptions!$H$24,Assumptions!$H$25)+D9-C9),IF(I9="Core",1,IF(I9="AI",'Start Here'!$B$7,'Start Here'!$B$8))=1),1,0) -> 0 | BC9: =IF(AND(BC$5>=IF(I9="Core",C9,IF(I9="AI",Assumptions!$H$24,Assumptions!$H$25)),BC$5<=IF(I9="Core",D9,IF(I9="AI",Assumptions!$H$24,Assumptions!$H$25)+D9-C9),IF(I9="Core",1,IF(I9="AI",'Start Here'!$B$7,'Start Here'!$B$8))=1),1,0) -> 0 | BD9: =IF(AND(BD$5>=IF(I9="Core",C9,IF(I9="AI",Assumptions!$H$24,Assumptions!$H$25)),BD$5<=IF(I9="Core",D9,IF(I9="AI",Assumptions!$H$24,Assumptions!$H$25)+D9-C9),IF(I9="Core",1,IF(I9="AI",'Start Here'!$B$7,'Start Here'!$B$8))=1),1,0) -> 0 | BE9: =IF(AND(BE$5>=IF(I9="Core",C9,IF(I9="AI",Assumptions!$H$24,Assumptions!$H$25)),BE$5<=IF(I9="Core",D9,IF(I9="AI",Assumptions!$H$24,Assumptions!$H$25)+D9-C9),IF(I9="Core",1,IF(I9="AI",'Start Here'!$B$7,'Start Here'!$B$8))=1),1,0) -> 0 | BF9: =IF(AND(BF$5>=IF(I9="Core",C9,IF(I9="AI",Assumptions!$H$24,Assumptions!$H$25)),BF$5<=IF(I9="Core",D9,IF(I9="AI",Assumptions!$H$24,Assumptions!$H$25)+D9-C9),IF(I9="Core",1,IF(I9="AI",'Start Here'!$B$7,'Start Here'!$B$8))=1),1,0) -> 0 | BG9: =IF(AND(BG$5>=IF(I9="Core",C9,IF(I9="AI",Assumptions!$H$24,Assumptions!$H$25)),BG$5<=IF(I9="Core",D9,IF(I9="AI",Assumptions!$H$24,Assumptions!$H$25)+D9-C9),IF(I9="Core",1,IF(I9="AI",'Start Here'!$B$7,'Start Here'!$B$8))=1),1,0) -> 0 | BH9: =IF(AND(BH$5>=IF(I9="Core",C9,IF(I9="AI",Assumptions!$H$24,Assumptions!$H$25)),BH$5<=IF(I9="Core",D9,IF(I9="AI",Assumptions!$H$24,Assumptions!$H$25)+D9-C9),IF(I9="Core",1,IF(I9="AI",'Start Here'!$B$7,'Start Here'!$B$8))=1),1,0) -> 0 | BI9: =IF(AND(BI$5>=IF(I9="Core",C9,IF(I9="AI",Assumptions!$H$24,Assumptions!$H$25)),BI$5<=IF(I9="Core",D9,IF(I9="AI",Assumptions!$H$24,Assumptions!$H$25)+D9-C9),IF(I9="Core",1,IF(I9="AI",'Start Here'!$B$7,'Start Here'!$B$8))=1),1,0) -> 0 | BJ9: =IF(AND(BJ$5>=IF(I9="Core",C9,IF(I9="AI",Assumptions!$H$24,Assumptions!$H$25)),BJ$5<=IF(I9="Core",D9,IF(I9="AI",Assumptions!$H$24,Assumptions!$H$25)+D9-C9),IF(I9="Core",1,IF(I9="AI",'Start Here'!$B$7,'Start Here'!$B$8))=1),1,0) -> 0 | BK9: =IF(AND(BK$5>=IF(I9="Core",C9,IF(I9="AI",Assumptions!$H$24,Assumptions!$H$25)),BK$5<=IF(I9="Core",D9,IF(I9="AI",Assumptions!$H$24,Assumptions!$H$25)+D9-C9),IF(I9="Core",1,IF(I9="AI",'Start Here'!$B$7,'Start Here'!$B$8))=1),1,0) -> 0 | BL9: =IF(AND(BL$5>=IF(I9="Core",C9,IF(I9="AI",Assumptions!$H$24,Assumptions!$H$25)),BL$5<=IF(I9="Core",D9,IF(I9="AI",Assumptions!$H$24,Assumptions!$H$25)+D9-C9),IF(I9="Core",1,IF(I9="AI",'Start Here'!$B$7,'Start Here'!$B$8))=1),1,0) -> 0 | BM9: =IF(AND(BM$5>=IF(I9="Core",C9,IF(I9="AI",Assumptions!$H$24,Assumptions!$H$25)),BM$5<=IF(I9="Core",D9,IF(I9="AI",Assumptions!$H$24,Assumptions!$H$25)+D9-C9),IF(I9="Core",1,IF(I9="AI",'Start Here'!$B$7,'Start Here'!$B$8))=1),1,0) -> 0 | BN9: =IF(AND(BN$5>=IF(I9="Core",C9,IF(I9="AI",Assumptions!$H$24,Assumptions!$H$25)),BN$5<=IF(I9="Core",D9,IF(I9="AI",Assumptions!$H$24,Assumptions!$H$25)+D9-C9),IF(I9="Core",1,IF(I9="AI",'Start Here'!$B$7,'Start Here'!$B$8))=1),1,0) -> 0 | BO9: =IF(AND(BO$5>=IF(I9="Core",C9,IF(I9="AI",Assumptions!$H$24,Assumptions!$H$25)),BO$5<=IF(I9="Core",D9,IF(I9="AI",Assumptions!$H$24,Assumptions!$H$25)+D9-C9),IF(I9="Core",1,IF(I9="AI",'Start Here'!$B$7,'Start Here'!$B$8))=1),1,0) -> 0 | BP9: =IF(AND(BP$5>=IF(I9="Core",C9,IF(I9="AI",Assumptions!$H$24,Assumptions!$H$25)),BP$5<=IF(I9="Core",D9,IF(I9="AI",Assumptions!$H$24,Assumptions!$H$25)+D9-C9),IF(I9="Core",1,IF(I9="AI",'Start Here'!$B$7,'Start Here'!$B$8))=1),1,0) -> 0 | BQ9: =IF(AND(BQ$5>=IF(I9="Core",C9,IF(I9="AI",Assumptions!$H$24,Assumptions!$H$25)),BQ$5<=IF(I9="Core",D9,IF(I9="AI",Assumptions!$H$24,Assumptions!$H$25)+D9-C9),IF(I9="Core",1,IF(I9="AI",'Start Here'!$B$7,'Start Here'!$B$8))=1),1,0) -> 0 | BR9: =IF(AND(BR$5>=IF(I9="Core",C9,IF(I9="AI",Assumptions!$H$24,Assumptions!$H$25)),BR$5<=IF(I9="Core",D9,IF(I9="AI",Assumptions!$H$24,Assumptions!$H$25)+D9-C9),IF(I9="Core",1,IF(I9="AI",'Start Here'!$B$7,'Start Here'!$B$8))=1),1,0) -> 0
A10: G5 | B10: Repeatable deployment and sales learning | C10: 16 | D10: 24 | E10: G4 | F10: Success / tech lead | G10: Repeat onboarding, release/incident/restore evidence, retention and unit-cost evidence before hiring growth capacity. | H10: Low; ±4 months | I10: Core | J10: Unproven retention, acquisition and operating model | K10: =IF(AND(K$5>=IF(I10="Core",C10,IF(I10="AI",Assumptions!$H$24,Assumptions!$H$25)),K$5<=IF(I10="Core",D10,IF(I10="AI",Assumptions!$H$24,Assumptions!$H$25)+D10-C10),IF(I10="Core",1,IF(I10="AI",'Start Here'!$B$7,'Start Here'!$B$8))=1),1,0) -> 0 | L10: =IF(AND(L$5>=IF(I10="Core",C10,IF(I10="AI",Assumptions!$H$24,Assumptions!$H$25)),L$5<=IF(I10="Core",D10,IF(I10="AI",Assumptions!$H$24,Assumptions!$H$25)+D10-C10),IF(I10="Core",1,IF(I10="AI",'Start Here'!$B$7,'Start Here'!$B$8))=1),1,0) -> 0 | M10: =IF(AND(M$5>=IF(I10="Core",C10,IF(I10="AI",Assumptions!$H$24,Assumptions!$H$25)),M$5<=IF(I10="Core",D10,IF(I10="AI",Assumptions!$H$24,Assumptions!$H$25)+D10-C10),IF(I10="Core",1,IF(I10="AI",'Start Here'!$B$7,'Start Here'!$B$8))=1),1,0) -> 0 | N10: =IF(AND(N$5>=IF(I10="Core",C10,IF(I10="AI",Assumptions!$H$24,Assumptions!$H$25)),N$5<=IF(I10="Core",D10,IF(I10="AI",Assumptions!$H$24,Assumptions!$H$25)+D10-C10),IF(I10="Core",1,IF(I10="AI",'Start Here'!$B$7,'Start Here'!$B$8))=1),1,0) -> 0 | O10: =IF(AND(O$5>=IF(I10="Core",C10,IF(I10="AI",Assumptions!$H$24,Assumptions!$H$25)),O$5<=IF(I10="Core",D10,IF(I10="AI",Assumptions!$H$24,Assumptions!$H$25)+D10-C10),IF(I10="Core",1,IF(I10="AI",'Start Here'!$B$7,'Start Here'!$B$8))=1),1,0) -> 0 | P10: =IF(AND(P$5>=IF(I10="Core",C10,IF(I10="AI",Assumptions!$H$24,Assumptions!$H$25)),P$5<=IF(I10="Core",D10,IF(I10="AI",Assumptions!$H$24,Assumptions!$H$25)+D10-C10),IF(I10="Core",1,IF(I10="AI",'Start Here'!$B$7,'Start Here'!$B$8))=1),1,0) -> 0 | Q10: =IF(AND(Q$5>=IF(I10="Core",C10,IF(I10="AI",Assumptions!$H$24,Assumptions!$H$25)),Q$5<=IF(I10="Core",D10,IF(I10="AI",Assumptions!$H$24,Assumptions!$H$25)+D10-C10),IF(I10="Core",1,IF(I10="AI",'Start Here'!$B$7,'Start Here'!$B$8))=1),1,0) -> 0 | R10: =IF(AND(R$5>=IF(I10="Core",C10,IF(I10="AI",Assumptions!$H$24,Assumptions!$H$25)),R$5<=IF(I10="Core",D10,IF(I10="AI",Assumptions!$H$24,Assumptions!$H$25)+D10-C10),IF(I10="Core",1,IF(I10="AI",'Start Here'!$B$7,'Start Here'!$B$8))=1),1,0) -> 0 | S10: =IF(AND(S$5>=IF(I10="Core",C10,IF(I10="AI",Assumptions!$H$24,Assumptions!$H$25)),S$5<=IF(I10="Core",D10,IF(I10="AI",Assumptions!$H$24,Assumptions!$H$25)+D10-C10),IF(I10="Core",1,IF(I10="AI",'Start Here'!$B$7,'Start Here'!$B$8))=1),1,0) -> 0 | T10: =IF(AND(T$5>=IF(I10="Core",C10,IF(I10="AI",Assumptions!$H$24,Assumptions!$H$25)),T$5<=IF(I10="Core",D10,IF(I10="AI",Assumptions!$H$24,Assumptions!$H$25)+D10-C10),IF(I10="Core",1,IF(I10="AI",'Start Here'!$B$7,'Start Here'!$B$8))=1),1,0) -> 0 | U10: =IF(AND(U$5>=IF(I10="Core",C10,IF(I10="AI",Assumptions!$H$24,Assumptions!$H$25)),U$5<=IF(I10="Core",D10,IF(I10="AI",Assumptions!$H$24,Assumptions!$H$25)+D10-C10),IF(I10="Core",1,IF(I10="AI",'Start Here'!$B$7,'Start Here'!$B$8))=1),1,0) -> 0 | V10: =IF(AND(V$5>=IF(I10="Core",C10,IF(I10="AI",Assumptions!$H$24,Assumptions!$H$25)),V$5<=IF(I10="Core",D10,IF(I10="AI",Assumptions!$H$24,Assumptions!$H$25)+D10-C10),IF(I10="Core",1,IF(I10="AI",'Start Here'!$B$7,'Start Here'!$B$8))=1),1,0) -> 0 | W10: =IF(AND(W$5>=IF(I10="Core",C10,IF(I10="AI",Assumptions!$H$24,Assumptions!$H$25)),W$5<=IF(I10="Core",D10,IF(I10="AI",Assumptions!$H$24,Assumptions!$H$25)+D10-C10),IF(I10="Core",1,IF(I10="AI",'Start Here'!$B$7,'Start Here'!$B$8))=1),1,0) -> 0 | X10: =IF(AND(X$5>=IF(I10="Core",C10,IF(I10="AI",Assumptions!$H$24,Assumptions!$H$25)),X$5<=IF(I10="Core",D10,IF(I10="AI",Assumptions!$H$24,Assumptions!$H$25)+D10-C10),IF(I10="Core",1,IF(I10="AI",'Start Here'!$B$7,'Start Here'!$B$8))=1),1,0) -> 0 | Y10: =IF(AND(Y$5>=IF(I10="Core",C10,IF(I10="AI",Assumptions!$H$24,Assumptions!$H$25)),Y$5<=IF(I10="Core",D10,IF(I10="AI",Assumptions!$H$24,Assumptions!$H$25)+D10-C10),IF(I10="Core",1,IF(I10="AI",'Start Here'!$B$7,'Start Here'!$B$8))=1),1,0) -> 0 | Z10: =IF(AND(Z$5>=IF(I10="Core",C10,IF(I10="AI",Assumptions!$H$24,Assumptions!$H$25)),Z$5<=IF(I10="Core",D10,IF(I10="AI",Assumptions!$H$24,Assumptions!$H$25)+D10-C10),IF(I10="Core",1,IF(I10="AI",'Start Here'!$B$7,'Start Here'!$B$8))=1),1,0) -> 1 | AA10: =IF(AND(AA$5>=IF(I10="Core",C10,IF(I10="AI",Assumptions!$H$24,Assumptions!$H$25)),AA$5<=IF(I10="Core",D10,IF(I10="AI",Assumptions!$H$24,Assumptions!$H$25)+D10-C10),IF(I10="Core",1,IF(I10="AI",'Start Here'!$B$7,'Start Here'!$B$8))=1),1,0) -> 1 | AB10: =IF(AND(AB$5>=IF(I10="Core",C10,IF(I10="AI",Assumptions!$H$24,Assumptions!$H$25)),AB$5<=IF(I10="Core",D10,IF(I10="AI",Assumptions!$H$24,Assumptions!$H$25)+D10-C10),IF(I10="Core",1,IF(I10="AI",'Start Here'!$B$7,'Start Here'!$B$8))=1),1,0) -> 1 | AC10: =IF(AND(AC$5>=IF(I10="Core",C10,IF(I10="AI",Assumptions!$H$24,Assumptions!$H$25)),AC$5<=IF(I10="Core",D10,IF(I10="AI",Assumptions!$H$24,Assumptions!$H$25)+D10-C10),IF(I10="Core",1,IF(I10="AI",'Start Here'!$B$7,'Start Here'!$B$8))=1),1,0) -> 1 | AD10: =IF(AND(AD$5>=IF(I10="Core",C10,IF(I10="AI",Assumptions!$H$24,Assumptions!$H$25)),AD$5<=IF(I10="Core",D10,IF(I10="AI",Assumptions!$H$24,Assumptions!$H$25)+D10-C10),IF(I10="Core",1,IF(I10="AI",'Start Here'!$B$7,'Start Here'!$B$8))=1),1,0) -> 1 | AE10: =IF(AND(AE$5>=IF(I10="Core",C10,IF(I10="AI",Assumptions!$H$24,Assumptions!$H$25)),AE$5<=IF(I10="Core",D10,IF(I10="AI",Assumptions!$H$24,Assumptions!$H$25)+D10-C10),IF(I10="Core",1,IF(I10="AI",'Start Here'!$B$7,'Start Here'!$B$8))=1),1,0) -> 1 | AF10: =IF(AND(AF$5>=IF(I10="Core",C10,IF(I10="AI",Assumptions!$H$24,Assumptions!$H$25)),AF$5<=IF(I10="Core",D10,IF(I10="AI",Assumptions!$H$24,Assumptions!$H$25)+D10-C10),IF(I10="Core",1,IF(I10="AI",'Start Here'!$B$7,'Start Here'!$B$8))=1),1,0) -> 1 | AG10: =IF(AND(AG$5>=IF(I10="Core",C10,IF(I10="AI",Assumptions!$H$24,Assumptions!$H$25)),AG$5<=IF(I10="Core",D10,IF(I10="AI",Assumptions!$H$24,Assumptions!$H$25)+D10-C10),IF(I10="Core",1,IF(I10="AI",'Start Here'!$B$7,'Start Here'!$B$8))=1),1,0) -> 1 | AH10: =IF(AND(AH$5>=IF(I10="Core",C10,IF(I10="AI",Assumptions!$H$24,Assumptions!$H$25)),AH$5<=IF(I10="Core",D10,IF(I10="AI",Assumptions!$H$24,Assumptions!$H$25)+D10-C10),IF(I10="Core",1,IF(I10="AI",'Start Here'!$B$7,'Start Here'!$B$8))=1),1,0) -> 1 | AI10: =IF(AND(AI$5>=IF(I10="Core",C10,IF(I10="AI",Assumptions!$H$24,Assumptions!$H$25)),AI$5<=IF(I10="Core",D10,IF(I10="AI",Assumptions!$H$24,Assumptions!$H$25)+D10-C10),IF(I10="Core",1,IF(I10="AI",'Start Here'!$B$7,'Start Here'!$B$8))=1),1,0) -> 0 | AJ10: =IF(AND(AJ$5>=IF(I10="Core",C10,IF(I10="AI",Assumptions!$H$24,Assumptions!$H$25)),AJ$5<=IF(I10="Core",D10,IF(I10="AI",Assumptions!$H$24,Assumptions!$H$25)+D10-C10),IF(I10="Core",1,IF(I10="AI",'Start Here'!$B$7,'Start Here'!$B$8))=1),1,0) -> 0 | AK10: =IF(AND(AK$5>=IF(I10="Core",C10,IF(I10="AI",Assumptions!$H$24,Assumptions!$H$25)),AK$5<=IF(I10="Core",D10,IF(I10="AI",Assumptions!$H$24,Assumptions!$H$25)+D10-C10),IF(I10="Core",1,IF(I10="AI",'Start Here'!$B$7,'Start Here'!$B$8))=1),1,0) -> 0 | AL10: =IF(AND(AL$5>=IF(I10="Core",C10,IF(I10="AI",Assumptions!$H$24,Assumptions!$H$25)),AL$5<=IF(I10="Core",D10,IF(I10="AI",Assumptions!$H$24,Assumptions!$H$25)+D10-C10),IF(I10="Core",1,IF(I10="AI",'Start Here'!$B$7,'Start Here'!$B$8))=1),1,0) -> 0 | AM10: =IF(AND(AM$5>=IF(I10="Core",C10,IF(I10="AI",Assumptions!$H$24,Assumptions!$H$25)),AM$5<=IF(I10="Core",D10,IF(I10="AI",Assumptions!$H$24,Assumptions!$H$25)+D10-C10),IF(I10="Core",1,IF(I10="AI",'Start Here'!$B$7,'Start Here'!$B$8))=1),1,0) -> 0 | AN10: =IF(AND(AN$5>=IF(I10="Core",C10,IF(I10="AI",Assumptions!$H$24,Assumptions!$H$25)),AN$5<=IF(I10="Core",D10,IF(I10="AI",Assumptions!$H$24,Assumptions!$H$25)+D10-C10),IF(I10="Core",1,IF(I10="AI",'Start Here'!$B$7,'Start Here'!$B$8))=1),1,0) -> 0 | AO10: =IF(AND(AO$5>=IF(I10="Core",C10,IF(I10="AI",Assumptions!$H$24,Assumptions!$H$25)),AO$5<=IF(I10="Core",D10,IF(I10="AI",Assumptions!$H$24,Assumptions!$H$25)+D10-C10),IF(I10="Core",1,IF(I10="AI",'Start Here'!$B$7,'Start Here'!$B$8))=1),1,0) -> 0 | AP10: =IF(AND(AP$5>=IF(I10="Core",C10,IF(I10="AI",Assumptions!$H$24,Assumptions!$H$25)),AP$5<=IF(I10="Core",D10,IF(I10="AI",Assumptions!$H$24,Assumptions!$H$25)+D10-C10),IF(I10="Core",1,IF(I10="AI",'Start Here'!$B$7,'Start Here'!$B$8))=1),1,0) -> 0 | AQ10: =IF(AND(AQ$5>=IF(I10="Core",C10,IF(I10="AI",Assumptions!$H$24,Assumptions!$H$25)),AQ$5<=IF(I10="Core",D10,IF(I10="AI",Assumptions!$H$24,Assumptions!$H$25)+D10-C10),IF(I10="Core",1,IF(I10="AI",'Start Here'!$B$7,'Start Here'!$B$8))=1),1,0) -> 0 | AR10: =IF(AND(AR$5>=IF(I10="Core",C10,IF(I10="AI",Assumptions!$H$24,Assumptions!$H$25)),AR$5<=IF(I10="Core",D10,IF(I10="AI",Assumptions!$H$24,Assumptions!$H$25)+D10-C10),IF(I10="Core",1,IF(I10="AI",'Start Here'!$B$7,'Start Here'!$B$8))=1),1,0) -> 0 | AS10: =IF(AND(AS$5>=IF(I10="Core",C10,IF(I10="AI",Assumptions!$H$24,Assumptions!$H$25)),AS$5<=IF(I10="Core",D10,IF(I10="AI",Assumptions!$H$24,Assumptions!$H$25)+D10-C10),IF(I10="Core",1,IF(I10="AI",'Start Here'!$B$7,'Start Here'!$B$8))=1),1,0) -> 0 | AT10: =IF(AND(AT$5>=IF(I10="Core",C10,IF(I10="AI",Assumptions!$H$24,Assumptions!$H$25)),AT$5<=IF(I10="Core",D10,IF(I10="AI",Assumptions!$H$24,Assumptions!$H$25)+D10-C10),IF(I10="Core",1,IF(I10="AI",'Start Here'!$B$7,'Start Here'!$B$8))=1),1,0) -> 0 | AU10: =IF(AND(AU$5>=IF(I10="Core",C10,IF(I10="AI",Assumptions!$H$24,Assumptions!$H$25)),AU$5<=IF(I10="Core",D10,IF(I10="AI",Assumptions!$H$24,Assumptions!$H$25)+D10-C10),IF(I10="Core",1,IF(I10="AI",'Start Here'!$B$7,'Start Here'!$B$8))=1),1,0) -> 0 | AV10: =IF(AND(AV$5>=IF(I10="Core",C10,IF(I10="AI",Assumptions!$H$24,Assumptions!$H$25)),AV$5<=IF(I10="Core",D10,IF(I10="AI",Assumptions!$H$24,Assumptions!$H$25)+D10-C10),IF(I10="Core",1,IF(I10="AI",'Start Here'!$B$7,'Start Here'!$B$8))=1),1,0) -> 0 | AW10: =IF(AND(AW$5>=IF(I10="Core",C10,IF(I10="AI",Assumptions!$H$24,Assumptions!$H$25)),AW$5<=IF(I10="Core",D10,IF(I10="AI",Assumptions!$H$24,Assumptions!$H$25)+D10-C10),IF(I10="Core",1,IF(I10="AI",'Start Here'!$B$7,'Start Here'!$B$8))=1),1,0) -> 0 | AX10: =IF(AND(AX$5>=IF(I10="Core",C10,IF(I10="AI",Assumptions!$H$24,Assumptions!$H$25)),AX$5<=IF(I10="Core",D10,IF(I10="AI",Assumptions!$H$24,Assumptions!$H$25)+D10-C10),IF(I10="Core",1,IF(I10="AI",'Start Here'!$B$7,'Start Here'!$B$8))=1),1,0) -> 0 | AY10: =IF(AND(AY$5>=IF(I10="Core",C10,IF(I10="AI",Assumptions!$H$24,Assumptions!$H$25)),AY$5<=IF(I10="Core",D10,IF(I10="AI",Assumptions!$H$24,Assumptions!$H$25)+D10-C10),IF(I10="Core",1,IF(I10="AI",'Start Here'!$B$7,'Start Here'!$B$8))=1),1,0) -> 0 | AZ10: =IF(AND(AZ$5>=IF(I10="Core",C10,IF(I10="AI",Assumptions!$H$24,Assumptions!$H$25)),AZ$5<=IF(I10="Core",D10,IF(I10="AI",Assumptions!$H$24,Assumptions!$H$25)+D10-C10),IF(I10="Core",1,IF(I10="AI",'Start Here'!$B$7,'Start Here'!$B$8))=1),1,0) -> 0 | BA10: =IF(AND(BA$5>=IF(I10="Core",C10,IF(I10="AI",Assumptions!$H$24,Assumptions!$H$25)),BA$5<=IF(I10="Core",D10,IF(I10="AI",Assumptions!$H$24,Assumptions!$H$25)+D10-C10),IF(I10="Core",1,IF(I10="AI",'Start Here'!$B$7,'Start Here'!$B$8))=1),1,0) -> 0 | BB10: =IF(AND(BB$5>=IF(I10="Core",C10,IF(I10="AI",Assumptions!$H$24,Assumptions!$H$25)),BB$5<=IF(I10="Core",D10,IF(I10="AI",Assumptions!$H$24,Assumptions!$H$25)+D10-C10),IF(I10="Core",1,IF(I10="AI",'Start Here'!$B$7,'Start Here'!$B$8))=1),1,0) -> 0 | BC10: =IF(AND(BC$5>=IF(I10="Core",C10,IF(I10="AI",Assumptions!$H$24,Assumptions!$H$25)),BC$5<=IF(I10="Core",D10,IF(I10="AI",Assumptions!$H$24,Assumptions!$H$25)+D10-C10),IF(I10="Core",1,IF(I10="AI",'Start Here'!$B$7,'Start Here'!$B$8))=1),1,0) -> 0 | BD10: =IF(AND(BD$5>=IF(I10="Core",C10,IF(I10="AI",Assumptions!$H$24,Assumptions!$H$25)),BD$5<=IF(I10="Core",D10,IF(I10="AI",Assumptions!$H$24,Assumptions!$H$25)+D10-C10),IF(I10="Core",1,IF(I10="AI",'Start Here'!$B$7,'Start Here'!$B$8))=1),1,0) -> 0 | BE10: =IF(AND(BE$5>=IF(I10="Core",C10,IF(I10="AI",Assumptions!$H$24,Assumptions!$H$25)),BE$5<=IF(I10="Core",D10,IF(I10="AI",Assumptions!$H$24,Assumptions!$H$25)+D10-C10),IF(I10="Core",1,IF(I10="AI",'Start Here'!$B$7,'Start Here'!$B$8))=1),1,0) -> 0 | BF10: =IF(AND(BF$5>=IF(I10="Core",C10,IF(I10="AI",Assumptions!$H$24,Assumptions!$H$25)),BF$5<=IF(I10="Core",D10,IF(I10="AI",Assumptions!$H$24,Assumptions!$H$25)+D10-C10),IF(I10="Core",1,IF(I10="AI",'Start Here'!$B$7,'Start Here'!$B$8))=1),1,0) -> 0 | BG10: =IF(AND(BG$5>=IF(I10="Core",C10,IF(I10="AI",Assumptions!$H$24,Assumptions!$H$25)),BG$5<=IF(I10="Core",D10,IF(I10="AI",Assumptions!$H$24,Assumptions!$H$25)+D10-C10),IF(I10="Core",1,IF(I10="AI",'Start Here'!$B$7,'Start Here'!$B$8))=1),1,0) -> 0 | BH10: =IF(AND(BH$5>=IF(I10="Core",C10,IF(I10="AI",Assumptions!$H$24,Assumptions!$H$25)),BH$5<=IF(I10="Core",D10,IF(I10="AI",Assumptions!$H$24,Assumptions!$H$25)+D10-C10),IF(I10="Core",1,IF(I10="AI",'Start Here'!$B$7,'Start Here'!$B$8))=1),1,0) -> 0 | BI10: =IF(AND(BI$5>=IF(I10="Core",C10,IF(I10="AI",Assumptions!$H$24,Assumptions!$H$25)),BI$5<=IF(I10="Core",D10,IF(I10="AI",Assumptions!$H$24,Assumptions!$H$25)+D10-C10),IF(I10="Core",1,IF(I10="AI",'Start Here'!$B$7,'Start Here'!$B$8))=1),1,0) -> 0 | BJ10: =IF(AND(BJ$5>=IF(I10="Core",C10,IF(I10="AI",Assumptions!$H$24,Assumptions!$H$25)),BJ$5<=IF(I10="Core",D10,IF(I10="AI",Assumptions!$H$24,Assumptions!$H$25)+D10-C10),IF(I10="Core",1,IF(I10="AI",'Start Here'!$B$7,'Start Here'!$B$8))=1),1,0) -> 0 | BK10: =IF(AND(BK$5>=IF(I10="Core",C10,IF(I10="AI",Assumptions!$H$24,Assumptions!$H$25)),BK$5<=IF(I10="Core",D10,IF(I10="AI",Assumptions!$H$24,Assumptions!$H$25)+D10-C10),IF(I10="Core",1,IF(I10="AI",'Start Here'!$B$7,'Start Here'!$B$8))=1),1,0) -> 0 | BL10: =IF(AND(BL$5>=IF(I10="Core",C10,IF(I10="AI",Assumptions!$H$24,Assumptions!$H$25)),BL$5<=IF(I10="Core",D10,IF(I10="AI",Assumptions!$H$24,Assumptions!$H$25)+D10-C10),IF(I10="Core",1,IF(I10="AI",'Start Here'!$B$7,'Start Here'!$B$8))=1),1,0) -> 0 | BM10: =IF(AND(BM$5>=IF(I10="Core",C10,IF(I10="AI",Assumptions!$H$24,Assumptions!$H$25)),BM$5<=IF(I10="Core",D10,IF(I10="AI",Assumptions!$H$24,Assumptions!$H$25)+D10-C10),IF(I10="Core",1,IF(I10="AI",'Start Here'!$B$7,'Start Here'!$B$8))=1),1,0) -> 0 | BN10: =IF(AND(BN$5>=IF(I10="Core",C10,IF(I10="AI",Assumptions!$H$24,Assumptions!$H$25)),BN$5<=IF(I10="Core",D10,IF(I10="AI",Assumptions!$H$24,Assumptions!$H$25)+D10-C10),IF(I10="Core",1,IF(I10="AI",'Start Here'!$B$7,'Start Here'!$B$8))=1),1,0) -> 0 | BO10: =IF(AND(BO$5>=IF(I10="Core",C10,IF(I10="AI",Assumptions!$H$24,Assumptions!$H$25)),BO$5<=IF(I10="Core",D10,IF(I10="AI",Assumptions!$H$24,Assumptions!$H$25)+D10-C10),IF(I10="Core",1,IF(I10="AI",'Start Here'!$B$7,'Start Here'!$B$8))=1),1,0) -> 0 | BP10: =IF(AND(BP$5>=IF(I10="Core",C10,IF(I10="AI",Assumptions!$H$24,Assumptions!$H$25)),BP$5<=IF(I10="Core",D10,IF(I10="AI",Assumptions!$H$24,Assumptions!$H$25)+D10-C10),IF(I10="Core",1,IF(I10="AI",'Start Here'!$B$7,'Start Here'!$B$8))=1),1,0) -> 0 | BQ10: =IF(AND(BQ$5>=IF(I10="Core",C10,IF(I10="AI",Assumptions!$H$24,Assumptions!$H$25)),BQ$5<=IF(I10="Core",D10,IF(I10="AI",Assumptions!$H$24,Assumptions!$H$25)+D10-C10),IF(I10="Core",1,IF(I10="AI",'Start Here'!$B$7,'Start Here'!$B$8))=1),1,0) -> 0 | BR10: =IF(AND(BR$5>=IF(I10="Core",C10,IF(I10="AI",Assumptions!$H$24,Assumptions!$H$25)),BR$5<=IF(I10="Core",D10,IF(I10="AI",Assumptions!$H$24,Assumptions!$H$25)+D10-C10),IF(I10="Core",1,IF(I10="AI",'Start Here'!$B$7,'Start Here'!$B$8))=1),1,0) -> 0
A11: G6 | B11: Conditional growth / scale | C11: 25 | D11: 60 | E11: G5; capital and demand evidence | F11: Founder / sales / tech lead | G11: Quarterly funding, clinical safety and unit-economics review; hire to measured demand, not valuation; resize from SLOs. | H11: Low; reforecast quarterly | I11: Core | J11: Revenue/hiring forecasts are not commitments | K11: =IF(AND(K$5>=IF(I11="Core",C11,IF(I11="AI",Assumptions!$H$24,Assumptions!$H$25)),K$5<=IF(I11="Core",D11,IF(I11="AI",Assumptions!$H$24,Assumptions!$H$25)+D11-C11),IF(I11="Core",1,IF(I11="AI",'Start Here'!$B$7,'Start Here'!$B$8))=1),1,0) -> 0 | L11: =IF(AND(L$5>=IF(I11="Core",C11,IF(I11="AI",Assumptions!$H$24,Assumptions!$H$25)),L$5<=IF(I11="Core",D11,IF(I11="AI",Assumptions!$H$24,Assumptions!$H$25)+D11-C11),IF(I11="Core",1,IF(I11="AI",'Start Here'!$B$7,'Start Here'!$B$8))=1),1,0) -> 0 | M11: =IF(AND(M$5>=IF(I11="Core",C11,IF(I11="AI",Assumptions!$H$24,Assumptions!$H$25)),M$5<=IF(I11="Core",D11,IF(I11="AI",Assumptions!$H$24,Assumptions!$H$25)+D11-C11),IF(I11="Core",1,IF(I11="AI",'Start Here'!$B$7,'Start Here'!$B$8))=1),1,0) -> 0 | N11: =IF(AND(N$5>=IF(I11="Core",C11,IF(I11="AI",Assumptions!$H$24,Assumptions!$H$25)),N$5<=IF(I11="Core",D11,IF(I11="AI",Assumptions!$H$24,Assumptions!$H$25)+D11-C11),IF(I11="Core",1,IF(I11="AI",'Start Here'!$B$7,'Start Here'!$B$8))=1),1,0) -> 0 | O11: =IF(AND(O$5>=IF(I11="Core",C11,IF(I11="AI",Assumptions!$H$24,Assumptions!$H$25)),O$5<=IF(I11="Core",D11,IF(I11="AI",Assumptions!$H$24,Assumptions!$H$25)+D11-C11),IF(I11="Core",1,IF(I11="AI",'Start Here'!$B$7,'Start Here'!$B$8))=1),1,0) -> 0 | P11: =IF(AND(P$5>=IF(I11="Core",C11,IF(I11="AI",Assumptions!$H$24,Assumptions!$H$25)),P$5<=IF(I11="Core",D11,IF(I11="AI",Assumptions!$H$24,Assumptions!$H$25)+D11-C11),IF(I11="Core",1,IF(I11="AI",'Start Here'!$B$7,'Start Here'!$B$8))=1),1,0) -> 0 | Q11: =IF(AND(Q$5>=IF(I11="Core",C11,IF(I11="AI",Assumptions!$H$24,Assumptions!$H$25)),Q$5<=IF(I11="Core",D11,IF(I11="AI",Assumptions!$H$24,Assumptions!$H$25)+D11-C11),IF(I11="Core",1,IF(I11="AI",'Start Here'!$B$7,'Start Here'!$B$8))=1),1,0) -> 0 | R11: =IF(AND(R$5>=IF(I11="Core",C11,IF(I11="AI",Assumptions!$H$24,Assumptions!$H$25)),R$5<=IF(I11="Core",D11,IF(I11="AI",Assumptions!$H$24,Assumptions!$H$25)+D11-C11),IF(I11="Core",1,IF(I11="AI",'Start Here'!$B$7,'Start Here'!$B$8))=1),1,0) -> 0 | S11: =IF(AND(S$5>=IF(I11="Core",C11,IF(I11="AI",Assumptions!$H$24,Assumptions!$H$25)),S$5<=IF(I11="Core",D11,IF(I11="AI",Assumptions!$H$24,Assumptions!$H$25)+D11-C11),IF(I11="Core",1,IF(I11="AI",'Start Here'!$B$7,'Start Here'!$B$8))=1),1,0) -> 0 | T11: =IF(AND(T$5>=IF(I11="Core",C11,IF(I11="AI",Assumptions!$H$24,Assumptions!$H$25)),T$5<=IF(I11="Core",D11,IF(I11="AI",Assumptions!$H$24,Assumptions!$H$25)+D11-C11),IF(I11="Core",1,IF(I11="AI",'Start Here'!$B$7,'Start Here'!$B$8))=1),1,0) -> 0 | U11: =IF(AND(U$5>=IF(I11="Core",C11,IF(I11="AI",Assumptions!$H$24,Assumptions!$H$25)),U$5<=IF(I11="Core",D11,IF(I11="AI",Assumptions!$H$24,Assumptions!$H$25)+D11-C11),IF(I11="Core",1,IF(I11="AI",'Start Here'!$B$7,'Start Here'!$B$8))=1),1,0) -> 0 | V11: =IF(AND(V$5>=IF(I11="Core",C11,IF(I11="AI",Assumptions!$H$24,Assumptions!$H$25)),V$5<=IF(I11="Core",D11,IF(I11="AI",Assumptions!$H$24,Assumptions!$H$25)+D11-C11),IF(I11="Core",1,IF(I11="AI",'Start Here'!$B$7,'Start Here'!$B$8))=1),1,0) -> 0 | W11: =IF(AND(W$5>=IF(I11="Core",C11,IF(I11="AI",Assumptions!$H$24,Assumptions!$H$25)),W$5<=IF(I11="Core",D11,IF(I11="AI",Assumptions!$H$24,Assumptions!$H$25)+D11-C11),IF(I11="Core",1,IF(I11="AI",'Start Here'!$B$7,'Start Here'!$B$8))=1),1,0) -> 0 | X11: =IF(AND(X$5>=IF(I11="Core",C11,IF(I11="AI",Assumptions!$H$24,Assumptions!$H$25)),X$5<=IF(I11="Core",D11,IF(I11="AI",Assumptions!$H$24,Assumptions!$H$25)+D11-C11),IF(I11="Core",1,IF(I11="AI",'Start Here'!$B$7,'Start Here'!$B$8))=1),1,0) -> 0 | Y11: =IF(AND(Y$5>=IF(I11="Core",C11,IF(I11="AI",Assumptions!$H$24,Assumptions!$H$25)),Y$5<=IF(I11="Core",D11,IF(I11="AI",Assumptions!$H$24,Assumptions!$H$25)+D11-C11),IF(I11="Core",1,IF(I11="AI",'Start Here'!$B$7,'Start Here'!$B$8))=1),1,0) -> 0 | Z11: =IF(AND(Z$5>=IF(I11="Core",C11,IF(I11="AI",Assumptions!$H$24,Assumptions!$H$25)),Z$5<=IF(I11="Core",D11,IF(I11="AI",Assumptions!$H$24,Assumptions!$H$25)+D11-C11),IF(I11="Core",1,IF(I11="AI",'Start Here'!$B$7,'Start Here'!$B$8))=1),1,0) -> 0 | AA11: =IF(AND(AA$5>=IF(I11="Core",C11,IF(I11="AI",Assumptions!$H$24,Assumptions!$H$25)),AA$5<=IF(I11="Core",D11,IF(I11="AI",Assumptions!$H$24,Assumptions!$H$25)+D11-C11),IF(I11="Core",1,IF(I11="AI",'Start Here'!$B$7,'Start Here'!$B$8))=1),1,0) -> 0 | AB11: =IF(AND(AB$5>=IF(I11="Core",C11,IF(I11="AI",Assumptions!$H$24,Assumptions!$H$25)),AB$5<=IF(I11="Core",D11,IF(I11="AI",Assumptions!$H$24,Assumptions!$H$25)+D11-C11),IF(I11="Core",1,IF(I11="AI",'Start Here'!$B$7,'Start Here'!$B$8))=1),1,0) -> 0 | AC11: =IF(AND(AC$5>=IF(I11="Core",C11,IF(I11="AI",Assumptions!$H$24,Assumptions!$H$25)),AC$5<=IF(I11="Core",D11,IF(I11="AI",Assumptions!$H$24,Assumptions!$H$25)+D11-C11),IF(I11="Core",1,IF(I11="AI",'Start Here'!$B$7,'Start Here'!$B$8))=1),1,0) -> 0 | AD11: =IF(AND(AD$5>=IF(I11="Core",C11,IF(I11="AI",Assumptions!$H$24,Assumptions!$H$25)),AD$5<=IF(I11="Core",D11,IF(I11="AI",Assumptions!$H$24,Assumptions!$H$25)+D11-C11),IF(I11="Core",1,IF(I11="AI",'Start Here'!$B$7,'Start Here'!$B$8))=1),1,0) -> 0 | AE11: =IF(AND(AE$5>=IF(I11="Core",C11,IF(I11="AI",Assumptions!$H$24,Assumptions!$H$25)),AE$5<=IF(I11="Core",D11,IF(I11="AI",Assumptions!$H$24,Assumptions!$H$25)+D11-C11),IF(I11="Core",1,IF(I11="AI",'Start Here'!$B$7,'Start Here'!$B$8))=1),1,0) -> 0 | AF11: =IF(AND(AF$5>=IF(I11="Core",C11,IF(I11="AI",Assumptions!$H$24,Assumptions!$H$25)),AF$5<=IF(I11="Core",D11,IF(I11="AI",Assumptions!$H$24,Assumptions!$H$25)+D11-C11),IF(I11="Core",1,IF(I11="AI",'Start Here'!$B$7,'Start Here'!$B$8))=1),1,0) -> 0 | AG11: =IF(AND(AG$5>=IF(I11="Core",C11,IF(I11="AI",Assumptions!$H$24,Assumptions!$H$25)),AG$5<=IF(I11="Core",D11,IF(I11="AI",Assumptions!$H$24,Assumptions!$H$25)+D11-C11),IF(I11="Core",1,IF(I11="AI",'Start Here'!$B$7,'Start Here'!$B$8))=1),1,0) -> 0 | AH11: =IF(AND(AH$5>=IF(I11="Core",C11,IF(I11="AI",Assumptions!$H$24,Assumptions!$H$25)),AH$5<=IF(I11="Core",D11,IF(I11="AI",Assumptions!$H$24,Assumptions!$H$25)+D11-C11),IF(I11="Core",1,IF(I11="AI",'Start Here'!$B$7,'Start Here'!$B$8))=1),1,0) -> 0 | AI11: =IF(AND(AI$5>=IF(I11="Core",C11,IF(I11="AI",Assumptions!$H$24,Assumptions!$H$25)),AI$5<=IF(I11="Core",D11,IF(I11="AI",Assumptions!$H$24,Assumptions!$H$25)+D11-C11),IF(I11="Core",1,IF(I11="AI",'Start Here'!$B$7,'Start Here'!$B$8))=1),1,0) -> 1 | AJ11: =IF(AND(AJ$5>=IF(I11="Core",C11,IF(I11="AI",Assumptions!$H$24,Assumptions!$H$25)),AJ$5<=IF(I11="Core",D11,IF(I11="AI",Assumptions!$H$24,Assumptions!$H$25)+D11-C11),IF(I11="Core",1,IF(I11="AI",'Start Here'!$B$7,'Start Here'!$B$8))=1),1,0) -> 1 | AK11: =IF(AND(AK$5>=IF(I11="Core",C11,IF(I11="AI",Assumptions!$H$24,Assumptions!$H$25)),AK$5<=IF(I11="Core",D11,IF(I11="AI",Assumptions!$H$24,Assumptions!$H$25)+D11-C11),IF(I11="Core",1,IF(I11="AI",'Start Here'!$B$7,'Start Here'!$B$8))=1),1,0) -> 1 | AL11: =IF(AND(AL$5>=IF(I11="Core",C11,IF(I11="AI",Assumptions!$H$24,Assumptions!$H$25)),AL$5<=IF(I11="Core",D11,IF(I11="AI",Assumptions!$H$24,Assumptions!$H$25)+D11-C11),IF(I11="Core",1,IF(I11="AI",'Start Here'!$B$7,'Start Here'!$B$8))=1),1,0) -> 1 | AM11: =IF(AND(AM$5>=IF(I11="Core",C11,IF(I11="AI",Assumptions!$H$24,Assumptions!$H$25)),AM$5<=IF(I11="Core",D11,IF(I11="AI",Assumptions!$H$24,Assumptions!$H$25)+D11-C11),IF(I11="Core",1,IF(I11="AI",'Start Here'!$B$7,'Start Here'!$B$8))=1),1,0) -> 1 | AN11: =IF(AND(AN$5>=IF(I11="Core",C11,IF(I11="AI",Assumptions!$H$24,Assumptions!$H$25)),AN$5<=IF(I11="Core",D11,IF(I11="AI",Assumptions!$H$24,Assumptions!$H$25)+D11-C11),IF(I11="Core",1,IF(I11="AI",'Start Here'!$B$7,'Start Here'!$B$8))=1),1,0) -> 1 | AO11: =IF(AND(AO$5>=IF(I11="Core",C11,IF(I11="AI",Assumptions!$H$24,Assumptions!$H$25)),AO$5<=IF(I11="Core",D11,IF(I11="AI",Assumptions!$H$24,Assumptions!$H$25)+D11-C11),IF(I11="Core",1,IF(I11="AI",'Start Here'!$B$7,'Start Here'!$B$8))=1),1,0) -> 1 | AP11: =IF(AND(AP$5>=IF(I11="Core",C11,IF(I11="AI",Assumptions!$H$24,Assumptions!$H$25)),AP$5<=IF(I11="Core",D11,IF(I11="AI",Assumptions!$H$24,Assumptions!$H$25)+D11-C11),IF(I11="Core",1,IF(I11="AI",'Start Here'!$B$7,'Start Here'!$B$8))=1),1,0) -> 1 | AQ11: =IF(AND(AQ$5>=IF(I11="Core",C11,IF(I11="AI",Assumptions!$H$24,Assumptions!$H$25)),AQ$5<=IF(I11="Core",D11,IF(I11="AI",Assumptions!$H$24,Assumptions!$H$25)+D11-C11),IF(I11="Core",1,IF(I11="AI",'Start Here'!$B$7,'Start Here'!$B$8))=1),1,0) -> 1 | AR11: =IF(AND(AR$5>=IF(I11="Core",C11,IF(I11="AI",Assumptions!$H$24,Assumptions!$H$25)),AR$5<=IF(I11="Core",D11,IF(I11="AI",Assumptions!$H$24,Assumptions!$H$25)+D11-C11),IF(I11="Core",1,IF(I11="AI",'Start Here'!$B$7,'Start Here'!$B$8))=1),1,0) -> 1 | AS11: =IF(AND(AS$5>=IF(I11="Core",C11,IF(I11="AI",Assumptions!$H$24,Assumptions!$H$25)),AS$5<=IF(I11="Core",D11,IF(I11="AI",Assumptions!$H$24,Assumptions!$H$25)+D11-C11),IF(I11="Core",1,IF(I11="AI",'Start Here'!$B$7,'Start Here'!$B$8))=1),1,0) -> 1 | AT11: =IF(AND(AT$5>=IF(I11="Core",C11,IF(I11="AI",Assumptions!$H$24,Assumptions!$H$25)),AT$5<=IF(I11="Core",D11,IF(I11="AI",Assumptions!$H$24,Assumptions!$H$25)+D11-C11),IF(I11="Core",1,IF(I11="AI",'Start Here'!$B$7,'Start Here'!$B$8))=1),1,0) -> 1 | AU11: =IF(AND(AU$5>=IF(I11="Core",C11,IF(I11="AI",Assumptions!$H$24,Assumptions!$H$25)),AU$5<=IF(I11="Core",D11,IF(I11="AI",Assumptions!$H$24,Assumptions!$H$25)+D11-C11),IF(I11="Core",1,IF(I11="AI",'Start Here'!$B$7,'Start Here'!$B$8))=1),1,0) -> 1 | AV11: =IF(AND(AV$5>=IF(I11="Core",C11,IF(I11="AI",Assumptions!$H$24,Assumptions!$H$25)),AV$5<=IF(I11="Core",D11,IF(I11="AI",Assumptions!$H$24,Assumptions!$H$25)+D11-C11),IF(I11="Core",1,IF(I11="AI",'Start Here'!$B$7,'Start Here'!$B$8))=1),1,0) -> 1 | AW11: =IF(AND(AW$5>=IF(I11="Core",C11,IF(I11="AI",Assumptions!$H$24,Assumptions!$H$25)),AW$5<=IF(I11="Core",D11,IF(I11="AI",Assumptions!$H$24,Assumptions!$H$25)+D11-C11),IF(I11="Core",1,IF(I11="AI",'Start Here'!$B$7,'Start Here'!$B$8))=1),1,0) -> 1 | AX11: =IF(AND(AX$5>=IF(I11="Core",C11,IF(I11="AI",Assumptions!$H$24,Assumptions!$H$25)),AX$5<=IF(I11="Core",D11,IF(I11="AI",Assumptions!$H$24,Assumptions!$H$25)+D11-C11),IF(I11="Core",1,IF(I11="AI",'Start Here'!$B$7,'Start Here'!$B$8))=1),1,0) -> 1 | AY11: =IF(AND(AY$5>=IF(I11="Core",C11,IF(I11="AI",Assumptions!$H$24,Assumptions!$H$25)),AY$5<=IF(I11="Core",D11,IF(I11="AI",Assumptions!$H$24,Assumptions!$H$25)+D11-C11),IF(I11="Core",1,IF(I11="AI",'Start Here'!$B$7,'Start Here'!$B$8))=1),1,0) -> 1 | AZ11: =IF(AND(AZ$5>=IF(I11="Core",C11,IF(I11="AI",Assumptions!$H$24,Assumptions!$H$25)),AZ$5<=IF(I11="Core",D11,IF(I11="AI",Assumptions!$H$24,Assumptions!$H$25)+D11-C11),IF(I11="Core",1,IF(I11="AI",'Start Here'!$B$7,'Start Here'!$B$8))=1),1,0) -> 1 | BA11: =IF(AND(BA$5>=IF(I11="Core",C11,IF(I11="AI",Assumptions!$H$24,Assumptions!$H$25)),BA$5<=IF(I11="Core",D11,IF(I11="AI",Assumptions!$H$24,Assumptions!$H$25)+D11-C11),IF(I11="Core",1,IF(I11="AI",'Start Here'!$B$7,'Start Here'!$B$8))=1),1,0) -> 1 | BB11: =IF(AND(BB$5>=IF(I11="Core",C11,IF(I11="AI",Assumptions!$H$24,Assumptions!$H$25)),BB$5<=IF(I11="Core",D11,IF(I11="AI",Assumptions!$H$24,Assumptions!$H$25)+D11-C11),IF(I11="Core",1,IF(I11="AI",'Start Here'!$B$7,'Start Here'!$B$8))=1),1,0) -> 1 | BC11: =IF(AND(BC$5>=IF(I11="Core",C11,IF(I11="AI",Assumptions!$H$24,Assumptions!$H$25)),BC$5<=IF(I11="Core",D11,IF(I11="AI",Assumptions!$H$24,Assumptions!$H$25)+D11-C11),IF(I11="Core",1,IF(I11="AI",'Start Here'!$B$7,'Start Here'!$B$8))=1),1,0) -> 1 | BD11: =IF(AND(BD$5>=IF(I11="Core",C11,IF(I11="AI",Assumptions!$H$24,Assumptions!$H$25)),BD$5<=IF(I11="Core",D11,IF(I11="AI",Assumptions!$H$24,Assumptions!$H$25)+D11-C11),IF(I11="Core",1,IF(I11="AI",'Start Here'!$B$7,'Start Here'!$B$8))=1),1,0) -> 1 | BE11: =IF(AND(BE$5>=IF(I11="Core",C11,IF(I11="AI",Assumptions!$H$24,Assumptions!$H$25)),BE$5<=IF(I11="Core",D11,IF(I11="AI",Assumptions!$H$24,Assumptions!$H$25)+D11-C11),IF(I11="Core",1,IF(I11="AI",'Start Here'!$B$7,'Start Here'!$B$8))=1),1,0) -> 1 | BF11: =IF(AND(BF$5>=IF(I11="Core",C11,IF(I11="AI",Assumptions!$H$24,Assumptions!$H$25)),BF$5<=IF(I11="Core",D11,IF(I11="AI",Assumptions!$H$24,Assumptions!$H$25)+D11-C11),IF(I11="Core",1,IF(I11="AI",'Start Here'!$B$7,'Start Here'!$B$8))=1),1,0) -> 1 | BG11: =IF(AND(BG$5>=IF(I11="Core",C11,IF(I11="AI",Assumptions!$H$24,Assumptions!$H$25)),BG$5<=IF(I11="Core",D11,IF(I11="AI",Assumptions!$H$24,Assumptions!$H$25)+D11-C11),IF(I11="Core",1,IF(I11="AI",'Start Here'!$B$7,'Start Here'!$B$8))=1),1,0) -> 1 | BH11: =IF(AND(BH$5>=IF(I11="Core",C11,IF(I11="AI",Assumptions!$H$24,Assumptions!$H$25)),BH$5<=IF(I11="Core",D11,IF(I11="AI",Assumptions!$H$24,Assumptions!$H$25)+D11-C11),IF(I11="Core",1,IF(I11="AI",'Start Here'!$B$7,'Start Here'!$B$8))=1),1,0) -> 1 | BI11: =IF(AND(BI$5>=IF(I11="Core",C11,IF(I11="AI",Assumptions!$H$24,Assumptions!$H$25)),BI$5<=IF(I11="Core",D11,IF(I11="AI",Assumptions!$H$24,Assumptions!$H$25)+D11-C11),IF(I11="Core",1,IF(I11="AI",'Start Here'!$B$7,'Start Here'!$B$8))=1),1,0) -> 1 | BJ11: =IF(AND(BJ$5>=IF(I11="Core",C11,IF(I11="AI",Assumptions!$H$24,Assumptions!$H$25)),BJ$5<=IF(I11="Core",D11,IF(I11="AI",Assumptions!$H$24,Assumptions!$H$25)+D11-C11),IF(I11="Core",1,IF(I11="AI",'Start Here'!$B$7,'Start Here'!$B$8))=1),1,0) -> 1 | BK11: =IF(AND(BK$5>=IF(I11="Core",C11,IF(I11="AI",Assumptions!$H$24,Assumptions!$H$25)),BK$5<=IF(I11="Core",D11,IF(I11="AI",Assumptions!$H$24,Assumptions!$H$25)+D11-C11),IF(I11="Core",1,IF(I11="AI",'Start Here'!$B$7,'Start Here'!$B$8))=1),1,0) -> 1 | BL11: =IF(AND(BL$5>=IF(I11="Core",C11,IF(I11="AI",Assumptions!$H$24,Assumptions!$H$25)),BL$5<=IF(I11="Core",D11,IF(I11="AI",Assumptions!$H$24,Assumptions!$H$25)+D11-C11),IF(I11="Core",1,IF(I11="AI",'Start Here'!$B$7,'Start Here'!$B$8))=1),1,0) -> 1 | BM11: =IF(AND(BM$5>=IF(I11="Core",C11,IF(I11="AI",Assumptions!$H$24,Assumptions!$H$25)),BM$5<=IF(I11="Core",D11,IF(I11="AI",Assumptions!$H$24,Assumptions!$H$25)+D11-C11),IF(I11="Core",1,IF(I11="AI",'Start Here'!$B$7,'Start Here'!$B$8))=1),1,0) -> 1 | BN11: =IF(AND(BN$5>=IF(I11="Core",C11,IF(I11="AI",Assumptions!$H$24,Assumptions!$H$25)),BN$5<=IF(I11="Core",D11,IF(I11="AI",Assumptions!$H$24,Assumptions!$H$25)+D11-C11),IF(I11="Core",1,IF(I11="AI",'Start Here'!$B$7,'Start Here'!$B$8))=1),1,0) -> 1 | BO11: =IF(AND(BO$5>=IF(I11="Core",C11,IF(I11="AI",Assumptions!$H$24,Assumptions!$H$25)),BO$5<=IF(I11="Core",D11,IF(I11="AI",Assumptions!$H$24,Assumptions!$H$25)+D11-C11),IF(I11="Core",1,IF(I11="AI",'Start Here'!$B$7,'Start Here'!$B$8))=1),1,0) -> 1 | BP11: =IF(AND(BP$5>=IF(I11="Core",C11,IF(I11="AI",Assumptions!$H$24,Assumptions!$H$25)),BP$5<=IF(I11="Core",D11,IF(I11="AI",Assumptions!$H$24,Assumptions!$H$25)+D11-C11),IF(I11="Core",1,IF(I11="AI",'Start Here'!$B$7,'Start Here'!$B$8))=1),1,0) -> 1 | BQ11: =IF(AND(BQ$5>=IF(I11="Core",C11,IF(I11="AI",Assumptions!$H$24,Assumptions!$H$25)),BQ$5<=IF(I11="Core",D11,IF(I11="AI",Assumptions!$H$24,Assumptions!$H$25)+D11-C11),IF(I11="Core",1,IF(I11="AI",'Start Here'!$B$7,'Start Here'!$B$8))=1),1,0) -> 1 | BR11: =IF(AND(BR$5>=IF(I11="Core",C11,IF(I11="AI",Assumptions!$H$24,Assumptions!$H$25)),BR$5<=IF(I11="Core",D11,IF(I11="AI",Assumptions!$H$24,Assumptions!$H$25)+D11-C11),IF(I11="Core",1,IF(I11="AI",'Start Here'!$B$7,'Start Here'!$B$8))=1),1,0) -> 1
A12: G-AI | B12: Optional AI discovery → evaluated assistive pilot | C12: 16 | D12: 24 | E12: G4; separate privacy/provider gate | F12: AI engineer / clinical | G12: Start follows scenario AI month, nine-month discovery/evaluation window; no assumed revenue uplift or clinical automation. | H12: Low; −2/+6 months | I12: AI | J12: Provider, safety, evaluation data and contractual limitations | K12: =IF(AND(K$5>=IF(I12="Core",C12,IF(I12="AI",Assumptions!$H$24,Assumptions!$H$25)),K$5<=IF(I12="Core",D12,IF(I12="AI",Assumptions!$H$24,Assumptions!$H$25)+D12-C12),IF(I12="Core",1,IF(I12="AI",'Start Here'!$B$7,'Start Here'!$B$8))=1),1,0) -> 0 | L12: =IF(AND(L$5>=IF(I12="Core",C12,IF(I12="AI",Assumptions!$H$24,Assumptions!$H$25)),L$5<=IF(I12="Core",D12,IF(I12="AI",Assumptions!$H$24,Assumptions!$H$25)+D12-C12),IF(I12="Core",1,IF(I12="AI",'Start Here'!$B$7,'Start Here'!$B$8))=1),1,0) -> 0 | M12: =IF(AND(M$5>=IF(I12="Core",C12,IF(I12="AI",Assumptions!$H$24,Assumptions!$H$25)),M$5<=IF(I12="Core",D12,IF(I12="AI",Assumptions!$H$24,Assumptions!$H$25)+D12-C12),IF(I12="Core",1,IF(I12="AI",'Start Here'!$B$7,'Start Here'!$B$8))=1),1,0) -> 0 | N12: =IF(AND(N$5>=IF(I12="Core",C12,IF(I12="AI",Assumptions!$H$24,Assumptions!$H$25)),N$5<=IF(I12="Core",D12,IF(I12="AI",Assumptions!$H$24,Assumptions!$H$25)+D12-C12),IF(I12="Core",1,IF(I12="AI",'Start Here'!$B$7,'Start Here'!$B$8))=1),1,0) -> 0 | O12: =IF(AND(O$5>=IF(I12="Core",C12,IF(I12="AI",Assumptions!$H$24,Assumptions!$H$25)),O$5<=IF(I12="Core",D12,IF(I12="AI",Assumptions!$H$24,Assumptions!$H$25)+D12-C12),IF(I12="Core",1,IF(I12="AI",'Start Here'!$B$7,'Start Here'!$B$8))=1),1,0) -> 0 | P12: =IF(AND(P$5>=IF(I12="Core",C12,IF(I12="AI",Assumptions!$H$24,Assumptions!$H$25)),P$5<=IF(I12="Core",D12,IF(I12="AI",Assumptions!$H$24,Assumptions!$H$25)+D12-C12),IF(I12="Core",1,IF(I12="AI",'Start Here'!$B$7,'Start Here'!$B$8))=1),1,0) -> 0 | Q12: =IF(AND(Q$5>=IF(I12="Core",C12,IF(I12="AI",Assumptions!$H$24,Assumptions!$H$25)),Q$5<=IF(I12="Core",D12,IF(I12="AI",Assumptions!$H$24,Assumptions!$H$25)+D12-C12),IF(I12="Core",1,IF(I12="AI",'Start Here'!$B$7,'Start Here'!$B$8))=1),1,0) -> 0 | R12: =IF(AND(R$5>=IF(I12="Core",C12,IF(I12="AI",Assumptions!$H$24,Assumptions!$H$25)),R$5<=IF(I12="Core",D12,IF(I12="AI",Assumptions!$H$24,Assumptions!$H$25)+D12-C12),IF(I12="Core",1,IF(I12="AI",'Start Here'!$B$7,'Start Here'!$B$8))=1),1,0) -> 0 | S12: =IF(AND(S$5>=IF(I12="Core",C12,IF(I12="AI",Assumptions!$H$24,Assumptions!$H$25)),S$5<=IF(I12="Core",D12,IF(I12="AI",Assumptions!$H$24,Assumptions!$H$25)+D12-C12),IF(I12="Core",1,IF(I12="AI",'Start Here'!$B$7,'Start Here'!$B$8))=1),1,0) -> 0 | T12: =IF(AND(T$5>=IF(I12="Core",C12,IF(I12="AI",Assumptions!$H$24,Assumptions!$H$25)),T$5<=IF(I12="Core",D12,IF(I12="AI",Assumptions!$H$24,Assumptions!$H$25)+D12-C12),IF(I12="Core",1,IF(I12="AI",'Start Here'!$B$7,'Start Here'!$B$8))=1),1,0) -> 0 | U12: =IF(AND(U$5>=IF(I12="Core",C12,IF(I12="AI",Assumptions!$H$24,Assumptions!$H$25)),U$5<=IF(I12="Core",D12,IF(I12="AI",Assumptions!$H$24,Assumptions!$H$25)+D12-C12),IF(I12="Core",1,IF(I12="AI",'Start Here'!$B$7,'Start Here'!$B$8))=1),1,0) -> 0 | V12: =IF(AND(V$5>=IF(I12="Core",C12,IF(I12="AI",Assumptions!$H$24,Assumptions!$H$25)),V$5<=IF(I12="Core",D12,IF(I12="AI",Assumptions!$H$24,Assumptions!$H$25)+D12-C12),IF(I12="Core",1,IF(I12="AI",'Start Here'!$B$7,'Start Here'!$B$8))=1),1,0) -> 0 | W12: =IF(AND(W$5>=IF(I12="Core",C12,IF(I12="AI",Assumptions!$H$24,Assumptions!$H$25)),W$5<=IF(I12="Core",D12,IF(I12="AI",Assumptions!$H$24,Assumptions!$H$25)+D12-C12),IF(I12="Core",1,IF(I12="AI",'Start Here'!$B$7,'Start Here'!$B$8))=1),1,0) -> 0 | X12: =IF(AND(X$5>=IF(I12="Core",C12,IF(I12="AI",Assumptions!$H$24,Assumptions!$H$25)),X$5<=IF(I12="Core",D12,IF(I12="AI",Assumptions!$H$24,Assumptions!$H$25)+D12-C12),IF(I12="Core",1,IF(I12="AI",'Start Here'!$B$7,'Start Here'!$B$8))=1),1,0) -> 0 | Y12: =IF(AND(Y$5>=IF(I12="Core",C12,IF(I12="AI",Assumptions!$H$24,Assumptions!$H$25)),Y$5<=IF(I12="Core",D12,IF(I12="AI",Assumptions!$H$24,Assumptions!$H$25)+D12-C12),IF(I12="Core",1,IF(I12="AI",'Start Here'!$B$7,'Start Here'!$B$8))=1),1,0) -> 0 | Z12: =IF(AND(Z$5>=IF(I12="Core",C12,IF(I12="AI",Assumptions!$H$24,Assumptions!$H$25)),Z$5<=IF(I12="Core",D12,IF(I12="AI",Assumptions!$H$24,Assumptions!$H$25)+D12-C12),IF(I12="Core",1,IF(I12="AI",'Start Here'!$B$7,'Start Here'!$B$8))=1),1,0) -> 0 | AA12: =IF(AND(AA$5>=IF(I12="Core",C12,IF(I12="AI",Assumptions!$H$24,Assumptions!$H$25)),AA$5<=IF(I12="Core",D12,IF(I12="AI",Assumptions!$H$24,Assumptions!$H$25)+D12-C12),IF(I12="Core",1,IF(I12="AI",'Start Here'!$B$7,'Start Here'!$B$8))=1),1,0) -> 0 | AB12: =IF(AND(AB$5>=IF(I12="Core",C12,IF(I12="AI",Assumptions!$H$24,Assumptions!$H$25)),AB$5<=IF(I12="Core",D12,IF(I12="AI",Assumptions!$H$24,Assumptions!$H$25)+D12-C12),IF(I12="Core",1,IF(I12="AI",'Start Here'!$B$7,'Start Here'!$B$8))=1),1,0) -> 0 | AC12: =IF(AND(AC$5>=IF(I12="Core",C12,IF(I12="AI",Assumptions!$H$24,Assumptions!$H$25)),AC$5<=IF(I12="Core",D12,IF(I12="AI",Assumptions!$H$24,Assumptions!$H$25)+D12-C12),IF(I12="Core",1,IF(I12="AI",'Start Here'!$B$7,'Start Here'!$B$8))=1),1,0) -> 0 | AD12: =IF(AND(AD$5>=IF(I12="Core",C12,IF(I12="AI",Assumptions!$H$24,Assumptions!$H$25)),AD$5<=IF(I12="Core",D12,IF(I12="AI",Assumptions!$H$24,Assumptions!$H$25)+D12-C12),IF(I12="Core",1,IF(I12="AI",'Start Here'!$B$7,'Start Here'!$B$8))=1),1,0) -> 0 | AE12: =IF(AND(AE$5>=IF(I12="Core",C12,IF(I12="AI",Assumptions!$H$24,Assumptions!$H$25)),AE$5<=IF(I12="Core",D12,IF(I12="AI",Assumptions!$H$24,Assumptions!$H$25)+D12-C12),IF(I12="Core",1,IF(I12="AI",'Start Here'!$B$7,'Start Here'!$B$8))=1),1,0) -> 0 | AF12: =IF(AND(AF$5>=IF(I12="Core",C12,IF(I12="AI",Assumptions!$H$24,Assumptions!$H$25)),AF$5<=IF(I12="Core",D12,IF(I12="AI",Assumptions!$H$24,Assumptions!$H$25)+D12-C12),IF(I12="Core",1,IF(I12="AI",'Start Here'!$B$7,'Start Here'!$B$8))=1),1,0) -> 0 | AG12: =IF(AND(AG$5>=IF(I12="Core",C12,IF(I12="AI",Assumptions!$H$24,Assumptions!$H$25)),AG$5<=IF(I12="Core",D12,IF(I12="AI",Assumptions!$H$24,Assumptions!$H$25)+D12-C12),IF(I12="Core",1,IF(I12="AI",'Start Here'!$B$7,'Start Here'!$B$8))=1),1,0) -> 0 | AH12: =IF(AND(AH$5>=IF(I12="Core",C12,IF(I12="AI",Assumptions!$H$24,Assumptions!$H$25)),AH$5<=IF(I12="Core",D12,IF(I12="AI",Assumptions!$H$24,Assumptions!$H$25)+D12-C12),IF(I12="Core",1,IF(I12="AI",'Start Here'!$B$7,'Start Here'!$B$8))=1),1,0) -> 0 | AI12: =IF(AND(AI$5>=IF(I12="Core",C12,IF(I12="AI",Assumptions!$H$24,Assumptions!$H$25)),AI$5<=IF(I12="Core",D12,IF(I12="AI",Assumptions!$H$24,Assumptions!$H$25)+D12-C12),IF(I12="Core",1,IF(I12="AI",'Start Here'!$B$7,'Start Here'!$B$8))=1),1,0) -> 0 | AJ12: =IF(AND(AJ$5>=IF(I12="Core",C12,IF(I12="AI",Assumptions!$H$24,Assumptions!$H$25)),AJ$5<=IF(I12="Core",D12,IF(I12="AI",Assumptions!$H$24,Assumptions!$H$25)+D12-C12),IF(I12="Core",1,IF(I12="AI",'Start Here'!$B$7,'Start Here'!$B$8))=1),1,0) -> 0 | AK12: =IF(AND(AK$5>=IF(I12="Core",C12,IF(I12="AI",Assumptions!$H$24,Assumptions!$H$25)),AK$5<=IF(I12="Core",D12,IF(I12="AI",Assumptions!$H$24,Assumptions!$H$25)+D12-C12),IF(I12="Core",1,IF(I12="AI",'Start Here'!$B$7,'Start Here'!$B$8))=1),1,0) -> 0 | AL12: =IF(AND(AL$5>=IF(I12="Core",C12,IF(I12="AI",Assumptions!$H$24,Assumptions!$H$25)),AL$5<=IF(I12="Core",D12,IF(I12="AI",Assumptions!$H$24,Assumptions!$H$25)+D12-C12),IF(I12="Core",1,IF(I12="AI",'Start Here'!$B$7,'Start Here'!$B$8))=1),1,0) -> 0 | AM12: =IF(AND(AM$5>=IF(I12="Core",C12,IF(I12="AI",Assumptions!$H$24,Assumptions!$H$25)),AM$5<=IF(I12="Core",D12,IF(I12="AI",Assumptions!$H$24,Assumptions!$H$25)+D12-C12),IF(I12="Core",1,IF(I12="AI",'Start Here'!$B$7,'Start Here'!$B$8))=1),1,0) -> 0 | AN12: =IF(AND(AN$5>=IF(I12="Core",C12,IF(I12="AI",Assumptions!$H$24,Assumptions!$H$25)),AN$5<=IF(I12="Core",D12,IF(I12="AI",Assumptions!$H$24,Assumptions!$H$25)+D12-C12),IF(I12="Core",1,IF(I12="AI",'Start Here'!$B$7,'Start Here'!$B$8))=1),1,0) -> 0 | AO12: =IF(AND(AO$5>=IF(I12="Core",C12,IF(I12="AI",Assumptions!$H$24,Assumptions!$H$25)),AO$5<=IF(I12="Core",D12,IF(I12="AI",Assumptions!$H$24,Assumptions!$H$25)+D12-C12),IF(I12="Core",1,IF(I12="AI",'Start Here'!$B$7,'Start Here'!$B$8))=1),1,0) -> 0 | AP12: =IF(AND(AP$5>=IF(I12="Core",C12,IF(I12="AI",Assumptions!$H$24,Assumptions!$H$25)),AP$5<=IF(I12="Core",D12,IF(I12="AI",Assumptions!$H$24,Assumptions!$H$25)+D12-C12),IF(I12="Core",1,IF(I12="AI",'Start Here'!$B$7,'Start Here'!$B$8))=1),1,0) -> 0 | AQ12: =IF(AND(AQ$5>=IF(I12="Core",C12,IF(I12="AI",Assumptions!$H$24,Assumptions!$H$25)),AQ$5<=IF(I12="Core",D12,IF(I12="AI",Assumptions!$H$24,Assumptions!$H$25)+D12-C12),IF(I12="Core",1,IF(I12="AI",'Start Here'!$B$7,'Start Here'!$B$8))=1),1,0) -> 0 | AR12: =IF(AND(AR$5>=IF(I12="Core",C12,IF(I12="AI",Assumptions!$H$24,Assumptions!$H$25)),AR$5<=IF(I12="Core",D12,IF(I12="AI",Assumptions!$H$24,Assumptions!$H$25)+D12-C12),IF(I12="Core",1,IF(I12="AI",'Start Here'!$B$7,'Start Here'!$B$8))=1),1,0) -> 0 | AS12: =IF(AND(AS$5>=IF(I12="Core",C12,IF(I12="AI",Assumptions!$H$24,Assumptions!$H$25)),AS$5<=IF(I12="Core",D12,IF(I12="AI",Assumptions!$H$24,Assumptions!$H$25)+D12-C12),IF(I12="Core",1,IF(I12="AI",'Start Here'!$B$7,'Start Here'!$B$8))=1),1,0) -> 0 | AT12: =IF(AND(AT$5>=IF(I12="Core",C12,IF(I12="AI",Assumptions!$H$24,Assumptions!$H$25)),AT$5<=IF(I12="Core",D12,IF(I12="AI",Assumptions!$H$24,Assumptions!$H$25)+D12-C12),IF(I12="Core",1,IF(I12="AI",'Start Here'!$B$7,'Start Here'!$B$8))=1),1,0) -> 0 | AU12: =IF(AND(AU$5>=IF(I12="Core",C12,IF(I12="AI",Assumptions!$H$24,Assumptions!$H$25)),AU$5<=IF(I12="Core",D12,IF(I12="AI",Assumptions!$H$24,Assumptions!$H$25)+D12-C12),IF(I12="Core",1,IF(I12="AI",'Start Here'!$B$7,'Start Here'!$B$8))=1),1,0) -> 0 | AV12: =IF(AND(AV$5>=IF(I12="Core",C12,IF(I12="AI",Assumptions!$H$24,Assumptions!$H$25)),AV$5<=IF(I12="Core",D12,IF(I12="AI",Assumptions!$H$24,Assumptions!$H$25)+D12-C12),IF(I12="Core",1,IF(I12="AI",'Start Here'!$B$7,'Start Here'!$B$8))=1),1,0) -> 0 | AW12: =IF(AND(AW$5>=IF(I12="Core",C12,IF(I12="AI",Assumptions!$H$24,Assumptions!$H$25)),AW$5<=IF(I12="Core",D12,IF(I12="AI",Assumptions!$H$24,Assumptions!$H$25)+D12-C12),IF(I12="Core",1,IF(I12="AI",'Start Here'!$B$7,'Start Here'!$B$8))=1),1,0) -> 0 | AX12: =IF(AND(AX$5>=IF(I12="Core",C12,IF(I12="AI",Assumptions!$H$24,Assumptions!$H$25)),AX$5<=IF(I12="Core",D12,IF(I12="AI",Assumptions!$H$24,Assumptions!$H$25)+D12-C12),IF(I12="Core",1,IF(I12="AI",'Start Here'!$B$7,'Start Here'!$B$8))=1),1,0) -> 0 | AY12: =IF(AND(AY$5>=IF(I12="Core",C12,IF(I12="AI",Assumptions!$H$24,Assumptions!$H$25)),AY$5<=IF(I12="Core",D12,IF(I12="AI",Assumptions!$H$24,Assumptions!$H$25)+D12-C12),IF(I12="Core",1,IF(I12="AI",'Start Here'!$B$7,'Start Here'!$B$8))=1),1,0) -> 0 | AZ12: =IF(AND(AZ$5>=IF(I12="Core",C12,IF(I12="AI",Assumptions!$H$24,Assumptions!$H$25)),AZ$5<=IF(I12="Core",D12,IF(I12="AI",Assumptions!$H$24,Assumptions!$H$25)+D12-C12),IF(I12="Core",1,IF(I12="AI",'Start Here'!$B$7,'Start Here'!$B$8))=1),1,0) -> 0 | BA12: =IF(AND(BA$5>=IF(I12="Core",C12,IF(I12="AI",Assumptions!$H$24,Assumptions!$H$25)),BA$5<=IF(I12="Core",D12,IF(I12="AI",Assumptions!$H$24,Assumptions!$H$25)+D12-C12),IF(I12="Core",1,IF(I12="AI",'Start Here'!$B$7,'Start Here'!$B$8))=1),1,0) -> 0 | BB12: =IF(AND(BB$5>=IF(I12="Core",C12,IF(I12="AI",Assumptions!$H$24,Assumptions!$H$25)),BB$5<=IF(I12="Core",D12,IF(I12="AI",Assumptions!$H$24,Assumptions!$H$25)+D12-C12),IF(I12="Core",1,IF(I12="AI",'Start Here'!$B$7,'Start Here'!$B$8))=1),1,0) -> 0 | BC12: =IF(AND(BC$5>=IF(I12="Core",C12,IF(I12="AI",Assumptions!$H$24,Assumptions!$H$25)),BC$5<=IF(I12="Core",D12,IF(I12="AI",Assumptions!$H$24,Assumptions!$H$25)+D12-C12),IF(I12="Core",1,IF(I12="AI",'Start Here'!$B$7,'Start Here'!$B$8))=1),1,0) -> 0 | BD12: =IF(AND(BD$5>=IF(I12="Core",C12,IF(I12="AI",Assumptions!$H$24,Assumptions!$H$25)),BD$5<=IF(I12="Core",D12,IF(I12="AI",Assumptions!$H$24,Assumptions!$H$25)+D12-C12),IF(I12="Core",1,IF(I12="AI",'Start Here'!$B$7,'Start Here'!$B$8))=1),1,0) -> 0 | BE12: =IF(AND(BE$5>=IF(I12="Core",C12,IF(I12="AI",Assumptions!$H$24,Assumptions!$H$25)),BE$5<=IF(I12="Core",D12,IF(I12="AI",Assumptions!$H$24,Assumptions!$H$25)+D12-C12),IF(I12="Core",1,IF(I12="AI",'Start Here'!$B$7,'Start Here'!$B$8))=1),1,0) -> 0 | BF12: =IF(AND(BF$5>=IF(I12="Core",C12,IF(I12="AI",Assumptions!$H$24,Assumptions!$H$25)),BF$5<=IF(I12="Core",D12,IF(I12="AI",Assumptions!$H$24,Assumptions!$H$25)+D12-C12),IF(I12="Core",1,IF(I12="AI",'Start Here'!$B$7,'Start Here'!$B$8))=1),1,0) -> 0 | BG12: =IF(AND(BG$5>=IF(I12="Core",C12,IF(I12="AI",Assumptions!$H$24,Assumptions!$H$25)),BG$5<=IF(I12="Core",D12,IF(I12="AI",Assumptions!$H$24,Assumptions!$H$25)+D12-C12),IF(I12="Core",1,IF(I12="AI",'Start Here'!$B$7,'Start Here'!$B$8))=1),1,0) -> 0 | BH12: =IF(AND(BH$5>=IF(I12="Core",C12,IF(I12="AI",Assumptions!$H$24,Assumptions!$H$25)),BH$5<=IF(I12="Core",D12,IF(I12="AI",Assumptions!$H$24,Assumptions!$H$25)+D12-C12),IF(I12="Core",1,IF(I12="AI",'Start Here'!$B$7,'Start Here'!$B$8))=1),1,0) -> 0 | BI12: =IF(AND(BI$5>=IF(I12="Core",C12,IF(I12="AI",Assumptions!$H$24,Assumptions!$H$25)),BI$5<=IF(I12="Core",D12,IF(I12="AI",Assumptions!$H$24,Assumptions!$H$25)+D12-C12),IF(I12="Core",1,IF(I12="AI",'Start Here'!$B$7,'Start Here'!$B$8))=1),1,0) -> 0 | BJ12: =IF(AND(BJ$5>=IF(I12="Core",C12,IF(I12="AI",Assumptions!$H$24,Assumptions!$H$25)),BJ$5<=IF(I12="Core",D12,IF(I12="AI",Assumptions!$H$24,Assumptions!$H$25)+D12-C12),IF(I12="Core",1,IF(I12="AI",'Start Here'!$B$7,'Start Here'!$B$8))=1),1,0) -> 0 | BK12: =IF(AND(BK$5>=IF(I12="Core",C12,IF(I12="AI",Assumptions!$H$24,Assumptions!$H$25)),BK$5<=IF(I12="Core",D12,IF(I12="AI",Assumptions!$H$24,Assumptions!$H$25)+D12-C12),IF(I12="Core",1,IF(I12="AI",'Start Here'!$B$7,'Start Here'!$B$8))=1),1,0) -> 0 | BL12: =IF(AND(BL$5>=IF(I12="Core",C12,IF(I12="AI",Assumptions!$H$24,Assumptions!$H$25)),BL$5<=IF(I12="Core",D12,IF(I12="AI",Assumptions!$H$24,Assumptions!$H$25)+D12-C12),IF(I12="Core",1,IF(I12="AI",'Start Here'!$B$7,'Start Here'!$B$8))=1),1,0) -> 0 | BM12: =IF(AND(BM$5>=IF(I12="Core",C12,IF(I12="AI",Assumptions!$H$24,Assumptions!$H$25)),BM$5<=IF(I12="Core",D12,IF(I12="AI",Assumptions!$H$24,Assumptions!$H$25)+D12-C12),IF(I12="Core",1,IF(I12="AI",'Start Here'!$B$7,'Start Here'!$B$8))=1),1,0) -> 0 | BN12: =IF(AND(BN$5>=IF(I12="Core",C12,IF(I12="AI",Assumptions!$H$24,Assumptions!$H$25)),BN$5<=IF(I12="Core",D12,IF(I12="AI",Assumptions!$H$24,Assumptions!$H$25)+D12-C12),IF(I12="Core",1,IF(I12="AI",'Start Here'!$B$7,'Start Here'!$B$8))=1),1,0) -> 0 | BO12: =IF(AND(BO$5>=IF(I12="Core",C12,IF(I12="AI",Assumptions!$H$24,Assumptions!$H$25)),BO$5<=IF(I12="Core",D12,IF(I12="AI",Assumptions!$H$24,Assumptions!$H$25)+D12-C12),IF(I12="Core",1,IF(I12="AI",'Start Here'!$B$7,'Start Here'!$B$8))=1),1,0) -> 0 | BP12: =IF(AND(BP$5>=IF(I12="Core",C12,IF(I12="AI",Assumptions!$H$24,Assumptions!$H$25)),BP$5<=IF(I12="Core",D12,IF(I12="AI",Assumptions!$H$24,Assumptions!$H$25)+D12-C12),IF(I12="Core",1,IF(I12="AI",'Start Here'!$B$7,'Start Here'!$B$8))=1),1,0) -> 0 | BQ12: =IF(AND(BQ$5>=IF(I12="Core",C12,IF(I12="AI",Assumptions!$H$24,Assumptions!$H$25)),BQ$5<=IF(I12="Core",D12,IF(I12="AI",Assumptions!$H$24,Assumptions!$H$25)+D12-C12),IF(I12="Core",1,IF(I12="AI",'Start Here'!$B$7,'Start Here'!$B$8))=1),1,0) -> 0 | BR12: =IF(AND(BR$5>=IF(I12="Core",C12,IF(I12="AI",Assumptions!$H$24,Assumptions!$H$25)),BR$5<=IF(I12="Core",D12,IF(I12="AI",Assumptions!$H$24,Assumptions!$H$25)+D12-C12),IF(I12="Core",1,IF(I12="AI",'Start Here'!$B$7,'Start Here'!$B$8))=1),1,0) -> 0
A13: G-CTMS | B13: Optional CTMS discovery → research synthetic pilot | C13: 25 | D13: 42 | E13: G5 plus new product investment case | F13: Research domain / validation | G13: Start follows scenario CTMS month, 18-month planning window; study/site schema, partner integrations and validation decision. | H13: Low; −3/+12 months | I13: CTMS | J13: Separate buyers, integration rights and regulatory applicability | K13: =IF(AND(K$5>=IF(I13="Core",C13,IF(I13="AI",Assumptions!$H$24,Assumptions!$H$25)),K$5<=IF(I13="Core",D13,IF(I13="AI",Assumptions!$H$24,Assumptions!$H$25)+D13-C13),IF(I13="Core",1,IF(I13="AI",'Start Here'!$B$7,'Start Here'!$B$8))=1),1,0) -> 0 | L13: =IF(AND(L$5>=IF(I13="Core",C13,IF(I13="AI",Assumptions!$H$24,Assumptions!$H$25)),L$5<=IF(I13="Core",D13,IF(I13="AI",Assumptions!$H$24,Assumptions!$H$25)+D13-C13),IF(I13="Core",1,IF(I13="AI",'Start Here'!$B$7,'Start Here'!$B$8))=1),1,0) -> 0 | M13: =IF(AND(M$5>=IF(I13="Core",C13,IF(I13="AI",Assumptions!$H$24,Assumptions!$H$25)),M$5<=IF(I13="Core",D13,IF(I13="AI",Assumptions!$H$24,Assumptions!$H$25)+D13-C13),IF(I13="Core",1,IF(I13="AI",'Start Here'!$B$7,'Start Here'!$B$8))=1),1,0) -> 0 | N13: =IF(AND(N$5>=IF(I13="Core",C13,IF(I13="AI",Assumptions!$H$24,Assumptions!$H$25)),N$5<=IF(I13="Core",D13,IF(I13="AI",Assumptions!$H$24,Assumptions!$H$25)+D13-C13),IF(I13="Core",1,IF(I13="AI",'Start Here'!$B$7,'Start Here'!$B$8))=1),1,0) -> 0 | O13: =IF(AND(O$5>=IF(I13="Core",C13,IF(I13="AI",Assumptions!$H$24,Assumptions!$H$25)),O$5<=IF(I13="Core",D13,IF(I13="AI",Assumptions!$H$24,Assumptions!$H$25)+D13-C13),IF(I13="Core",1,IF(I13="AI",'Start Here'!$B$7,'Start Here'!$B$8))=1),1,0) -> 0 | P13: =IF(AND(P$5>=IF(I13="Core",C13,IF(I13="AI",Assumptions!$H$24,Assumptions!$H$25)),P$5<=IF(I13="Core",D13,IF(I13="AI",Assumptions!$H$24,Assumptions!$H$25)+D13-C13),IF(I13="Core",1,IF(I13="AI",'Start Here'!$B$7,'Start Here'!$B$8))=1),1,0) -> 0 | Q13: =IF(AND(Q$5>=IF(I13="Core",C13,IF(I13="AI",Assumptions!$H$24,Assumptions!$H$25)),Q$5<=IF(I13="Core",D13,IF(I13="AI",Assumptions!$H$24,Assumptions!$H$25)+D13-C13),IF(I13="Core",1,IF(I13="AI",'Start Here'!$B$7,'Start Here'!$B$8))=1),1,0) -> 0 | R13: =IF(AND(R$5>=IF(I13="Core",C13,IF(I13="AI",Assumptions!$H$24,Assumptions!$H$25)),R$5<=IF(I13="Core",D13,IF(I13="AI",Assumptions!$H$24,Assumptions!$H$25)+D13-C13),IF(I13="Core",1,IF(I13="AI",'Start Here'!$B$7,'Start Here'!$B$8))=1),1,0) -> 0 | S13: =IF(AND(S$5>=IF(I13="Core",C13,IF(I13="AI",Assumptions!$H$24,Assumptions!$H$25)),S$5<=IF(I13="Core",D13,IF(I13="AI",Assumptions!$H$24,Assumptions!$H$25)+D13-C13),IF(I13="Core",1,IF(I13="AI",'Start Here'!$B$7,'Start Here'!$B$8))=1),1,0) -> 0 | T13: =IF(AND(T$5>=IF(I13="Core",C13,IF(I13="AI",Assumptions!$H$24,Assumptions!$H$25)),T$5<=IF(I13="Core",D13,IF(I13="AI",Assumptions!$H$24,Assumptions!$H$25)+D13-C13),IF(I13="Core",1,IF(I13="AI",'Start Here'!$B$7,'Start Here'!$B$8))=1),1,0) -> 0 | U13: =IF(AND(U$5>=IF(I13="Core",C13,IF(I13="AI",Assumptions!$H$24,Assumptions!$H$25)),U$5<=IF(I13="Core",D13,IF(I13="AI",Assumptions!$H$24,Assumptions!$H$25)+D13-C13),IF(I13="Core",1,IF(I13="AI",'Start Here'!$B$7,'Start Here'!$B$8))=1),1,0) -> 0 | V13: =IF(AND(V$5>=IF(I13="Core",C13,IF(I13="AI",Assumptions!$H$24,Assumptions!$H$25)),V$5<=IF(I13="Core",D13,IF(I13="AI",Assumptions!$H$24,Assumptions!$H$25)+D13-C13),IF(I13="Core",1,IF(I13="AI",'Start Here'!$B$7,'Start Here'!$B$8))=1),1,0) -> 0 | W13: =IF(AND(W$5>=IF(I13="Core",C13,IF(I13="AI",Assumptions!$H$24,Assumptions!$H$25)),W$5<=IF(I13="Core",D13,IF(I13="AI",Assumptions!$H$24,Assumptions!$H$25)+D13-C13),IF(I13="Core",1,IF(I13="AI",'Start Here'!$B$7,'Start Here'!$B$8))=1),1,0) -> 0 | X13: =IF(AND(X$5>=IF(I13="Core",C13,IF(I13="AI",Assumptions!$H$24,Assumptions!$H$25)),X$5<=IF(I13="Core",D13,IF(I13="AI",Assumptions!$H$24,Assumptions!$H$25)+D13-C13),IF(I13="Core",1,IF(I13="AI",'Start Here'!$B$7,'Start Here'!$B$8))=1),1,0) -> 0 | Y13: =IF(AND(Y$5>=IF(I13="Core",C13,IF(I13="AI",Assumptions!$H$24,Assumptions!$H$25)),Y$5<=IF(I13="Core",D13,IF(I13="AI",Assumptions!$H$24,Assumptions!$H$25)+D13-C13),IF(I13="Core",1,IF(I13="AI",'Start Here'!$B$7,'Start Here'!$B$8))=1),1,0) -> 0 | Z13: =IF(AND(Z$5>=IF(I13="Core",C13,IF(I13="AI",Assumptions!$H$24,Assumptions!$H$25)),Z$5<=IF(I13="Core",D13,IF(I13="AI",Assumptions!$H$24,Assumptions!$H$25)+D13-C13),IF(I13="Core",1,IF(I13="AI",'Start Here'!$B$7,'Start Here'!$B$8))=1),1,0) -> 0 | AA13: =IF(AND(AA$5>=IF(I13="Core",C13,IF(I13="AI",Assumptions!$H$24,Assumptions!$H$25)),AA$5<=IF(I13="Core",D13,IF(I13="AI",Assumptions!$H$24,Assumptions!$H$25)+D13-C13),IF(I13="Core",1,IF(I13="AI",'Start Here'!$B$7,'Start Here'!$B$8))=1),1,0) -> 0 | AB13: =IF(AND(AB$5>=IF(I13="Core",C13,IF(I13="AI",Assumptions!$H$24,Assumptions!$H$25)),AB$5<=IF(I13="Core",D13,IF(I13="AI",Assumptions!$H$24,Assumptions!$H$25)+D13-C13),IF(I13="Core",1,IF(I13="AI",'Start Here'!$B$7,'Start Here'!$B$8))=1),1,0) -> 0 | AC13: =IF(AND(AC$5>=IF(I13="Core",C13,IF(I13="AI",Assumptions!$H$24,Assumptions!$H$25)),AC$5<=IF(I13="Core",D13,IF(I13="AI",Assumptions!$H$24,Assumptions!$H$25)+D13-C13),IF(I13="Core",1,IF(I13="AI",'Start Here'!$B$7,'Start Here'!$B$8))=1),1,0) -> 0 | AD13: =IF(AND(AD$5>=IF(I13="Core",C13,IF(I13="AI",Assumptions!$H$24,Assumptions!$H$25)),AD$5<=IF(I13="Core",D13,IF(I13="AI",Assumptions!$H$24,Assumptions!$H$25)+D13-C13),IF(I13="Core",1,IF(I13="AI",'Start Here'!$B$7,'Start Here'!$B$8))=1),1,0) -> 0 | AE13: =IF(AND(AE$5>=IF(I13="Core",C13,IF(I13="AI",Assumptions!$H$24,Assumptions!$H$25)),AE$5<=IF(I13="Core",D13,IF(I13="AI",Assumptions!$H$24,Assumptions!$H$25)+D13-C13),IF(I13="Core",1,IF(I13="AI",'Start Here'!$B$7,'Start Here'!$B$8))=1),1,0) -> 0 | AF13: =IF(AND(AF$5>=IF(I13="Core",C13,IF(I13="AI",Assumptions!$H$24,Assumptions!$H$25)),AF$5<=IF(I13="Core",D13,IF(I13="AI",Assumptions!$H$24,Assumptions!$H$25)+D13-C13),IF(I13="Core",1,IF(I13="AI",'Start Here'!$B$7,'Start Here'!$B$8))=1),1,0) -> 0 | AG13: =IF(AND(AG$5>=IF(I13="Core",C13,IF(I13="AI",Assumptions!$H$24,Assumptions!$H$25)),AG$5<=IF(I13="Core",D13,IF(I13="AI",Assumptions!$H$24,Assumptions!$H$25)+D13-C13),IF(I13="Core",1,IF(I13="AI",'Start Here'!$B$7,'Start Here'!$B$8))=1),1,0) -> 0 | AH13: =IF(AND(AH$5>=IF(I13="Core",C13,IF(I13="AI",Assumptions!$H$24,Assumptions!$H$25)),AH$5<=IF(I13="Core",D13,IF(I13="AI",Assumptions!$H$24,Assumptions!$H$25)+D13-C13),IF(I13="Core",1,IF(I13="AI",'Start Here'!$B$7,'Start Here'!$B$8))=1),1,0) -> 0 | AI13: =IF(AND(AI$5>=IF(I13="Core",C13,IF(I13="AI",Assumptions!$H$24,Assumptions!$H$25)),AI$5<=IF(I13="Core",D13,IF(I13="AI",Assumptions!$H$24,Assumptions!$H$25)+D13-C13),IF(I13="Core",1,IF(I13="AI",'Start Here'!$B$7,'Start Here'!$B$8))=1),1,0) -> 0 | AJ13: =IF(AND(AJ$5>=IF(I13="Core",C13,IF(I13="AI",Assumptions!$H$24,Assumptions!$H$25)),AJ$5<=IF(I13="Core",D13,IF(I13="AI",Assumptions!$H$24,Assumptions!$H$25)+D13-C13),IF(I13="Core",1,IF(I13="AI",'Start Here'!$B$7,'Start Here'!$B$8))=1),1,0) -> 0 | AK13: =IF(AND(AK$5>=IF(I13="Core",C13,IF(I13="AI",Assumptions!$H$24,Assumptions!$H$25)),AK$5<=IF(I13="Core",D13,IF(I13="AI",Assumptions!$H$24,Assumptions!$H$25)+D13-C13),IF(I13="Core",1,IF(I13="AI",'Start Here'!$B$7,'Start Here'!$B$8))=1),1,0) -> 0 | AL13: =IF(AND(AL$5>=IF(I13="Core",C13,IF(I13="AI",Assumptions!$H$24,Assumptions!$H$25)),AL$5<=IF(I13="Core",D13,IF(I13="AI",Assumptions!$H$24,Assumptions!$H$25)+D13-C13),IF(I13="Core",1,IF(I13="AI",'Start Here'!$B$7,'Start Here'!$B$8))=1),1,0) -> 0 | AM13: =IF(AND(AM$5>=IF(I13="Core",C13,IF(I13="AI",Assumptions!$H$24,Assumptions!$H$25)),AM$5<=IF(I13="Core",D13,IF(I13="AI",Assumptions!$H$24,Assumptions!$H$25)+D13-C13),IF(I13="Core",1,IF(I13="AI",'Start Here'!$B$7,'Start Here'!$B$8))=1),1,0) -> 0 | AN13: =IF(AND(AN$5>=IF(I13="Core",C13,IF(I13="AI",Assumptions!$H$24,Assumptions!$H$25)),AN$5<=IF(I13="Core",D13,IF(I13="AI",Assumptions!$H$24,Assumptions!$H$25)+D13-C13),IF(I13="Core",1,IF(I13="AI",'Start Here'!$B$7,'Start Here'!$B$8))=1),1,0) -> 0 | AO13: =IF(AND(AO$5>=IF(I13="Core",C13,IF(I13="AI",Assumptions!$H$24,Assumptions!$H$25)),AO$5<=IF(I13="Core",D13,IF(I13="AI",Assumptions!$H$24,Assumptions!$H$25)+D13-C13),IF(I13="Core",1,IF(I13="AI",'Start Here'!$B$7,'Start Here'!$B$8))=1),1,0) -> 0 | AP13: =IF(AND(AP$5>=IF(I13="Core",C13,IF(I13="AI",Assumptions!$H$24,Assumptions!$H$25)),AP$5<=IF(I13="Core",D13,IF(I13="AI",Assumptions!$H$24,Assumptions!$H$25)+D13-C13),IF(I13="Core",1,IF(I13="AI",'Start Here'!$B$7,'Start Here'!$B$8))=1),1,0) -> 0 | AQ13: =IF(AND(AQ$5>=IF(I13="Core",C13,IF(I13="AI",Assumptions!$H$24,Assumptions!$H$25)),AQ$5<=IF(I13="Core",D13,IF(I13="AI",Assumptions!$H$24,Assumptions!$H$25)+D13-C13),IF(I13="Core",1,IF(I13="AI",'Start Here'!$B$7,'Start Here'!$B$8))=1),1,0) -> 0 | AR13: =IF(AND(AR$5>=IF(I13="Core",C13,IF(I13="AI",Assumptions!$H$24,Assumptions!$H$25)),AR$5<=IF(I13="Core",D13,IF(I13="AI",Assumptions!$H$24,Assumptions!$H$25)+D13-C13),IF(I13="Core",1,IF(I13="AI",'Start Here'!$B$7,'Start Here'!$B$8))=1),1,0) -> 0 | AS13: =IF(AND(AS$5>=IF(I13="Core",C13,IF(I13="AI",Assumptions!$H$24,Assumptions!$H$25)),AS$5<=IF(I13="Core",D13,IF(I13="AI",Assumptions!$H$24,Assumptions!$H$25)+D13-C13),IF(I13="Core",1,IF(I13="AI",'Start Here'!$B$7,'Start Here'!$B$8))=1),1,0) -> 0 | AT13: =IF(AND(AT$5>=IF(I13="Core",C13,IF(I13="AI",Assumptions!$H$24,Assumptions!$H$25)),AT$5<=IF(I13="Core",D13,IF(I13="AI",Assumptions!$H$24,Assumptions!$H$25)+D13-C13),IF(I13="Core",1,IF(I13="AI",'Start Here'!$B$7,'Start Here'!$B$8))=1),1,0) -> 0 | AU13: =IF(AND(AU$5>=IF(I13="Core",C13,IF(I13="AI",Assumptions!$H$24,Assumptions!$H$25)),AU$5<=IF(I13="Core",D13,IF(I13="AI",Assumptions!$H$24,Assumptions!$H$25)+D13-C13),IF(I13="Core",1,IF(I13="AI",'Start Here'!$B$7,'Start Here'!$B$8))=1),1,0) -> 0 | AV13: =IF(AND(AV$5>=IF(I13="Core",C13,IF(I13="AI",Assumptions!$H$24,Assumptions!$H$25)),AV$5<=IF(I13="Core",D13,IF(I13="AI",Assumptions!$H$24,Assumptions!$H$25)+D13-C13),IF(I13="Core",1,IF(I13="AI",'Start Here'!$B$7,'Start Here'!$B$8))=1),1,0) -> 0 | AW13: =IF(AND(AW$5>=IF(I13="Core",C13,IF(I13="AI",Assumptions!$H$24,Assumptions!$H$25)),AW$5<=IF(I13="Core",D13,IF(I13="AI",Assumptions!$H$24,Assumptions!$H$25)+D13-C13),IF(I13="Core",1,IF(I13="AI",'Start Here'!$B$7,'Start Here'!$B$8))=1),1,0) -> 0 | AX13: =IF(AND(AX$5>=IF(I13="Core",C13,IF(I13="AI",Assumptions!$H$24,Assumptions!$H$25)),AX$5<=IF(I13="Core",D13,IF(I13="AI",Assumptions!$H$24,Assumptions!$H$25)+D13-C13),IF(I13="Core",1,IF(I13="AI",'Start Here'!$B$7,'Start Here'!$B$8))=1),1,0) -> 0 | AY13: =IF(AND(AY$5>=IF(I13="Core",C13,IF(I13="AI",Assumptions!$H$24,Assumptions!$H$25)),AY$5<=IF(I13="Core",D13,IF(I13="AI",Assumptions!$H$24,Assumptions!$H$25)+D13-C13),IF(I13="Core",1,IF(I13="AI",'Start Here'!$B$7,'Start Here'!$B$8))=1),1,0) -> 0 | AZ13: =IF(AND(AZ$5>=IF(I13="Core",C13,IF(I13="AI",Assumptions!$H$24,Assumptions!$H$25)),AZ$5<=IF(I13="Core",D13,IF(I13="AI",Assumptions!$H$24,Assumptions!$H$25)+D13-C13),IF(I13="Core",1,IF(I13="AI",'Start Here'!$B$7,'Start Here'!$B$8))=1),1,0) -> 0 | BA13: =IF(AND(BA$5>=IF(I13="Core",C13,IF(I13="AI",Assumptions!$H$24,Assumptions!$H$25)),BA$5<=IF(I13="Core",D13,IF(I13="AI",Assumptions!$H$24,Assumptions!$H$25)+D13-C13),IF(I13="Core",1,IF(I13="AI",'Start Here'!$B$7,'Start Here'!$B$8))=1),1,0) -> 0 | BB13: =IF(AND(BB$5>=IF(I13="Core",C13,IF(I13="AI",Assumptions!$H$24,Assumptions!$H$25)),BB$5<=IF(I13="Core",D13,IF(I13="AI",Assumptions!$H$24,Assumptions!$H$25)+D13-C13),IF(I13="Core",1,IF(I13="AI",'Start Here'!$B$7,'Start Here'!$B$8))=1),1,0) -> 0 | BC13: =IF(AND(BC$5>=IF(I13="Core",C13,IF(I13="AI",Assumptions!$H$24,Assumptions!$H$25)),BC$5<=IF(I13="Core",D13,IF(I13="AI",Assumptions!$H$24,Assumptions!$H$25)+D13-C13),IF(I13="Core",1,IF(I13="AI",'Start Here'!$B$7,'Start Here'!$B$8))=1),1,0) -> 0 | BD13: =IF(AND(BD$5>=IF(I13="Core",C13,IF(I13="AI",Assumptions!$H$24,Assumptions!$H$25)),BD$5<=IF(I13="Core",D13,IF(I13="AI",Assumptions!$H$24,Assumptions!$H$25)+D13-C13),IF(I13="Core",1,IF(I13="AI",'Start Here'!$B$7,'Start Here'!$B$8))=1),1,0) -> 0 | BE13: =IF(AND(BE$5>=IF(I13="Core",C13,IF(I13="AI",Assumptions!$H$24,Assumptions!$H$25)),BE$5<=IF(I13="Core",D13,IF(I13="AI",Assumptions!$H$24,Assumptions!$H$25)+D13-C13),IF(I13="Core",1,IF(I13="AI",'Start Here'!$B$7,'Start Here'!$B$8))=1),1,0) -> 0 | BF13: =IF(AND(BF$5>=IF(I13="Core",C13,IF(I13="AI",Assumptions!$H$24,Assumptions!$H$25)),BF$5<=IF(I13="Core",D13,IF(I13="AI",Assumptions!$H$24,Assumptions!$H$25)+D13-C13),IF(I13="Core",1,IF(I13="AI",'Start Here'!$B$7,'Start Here'!$B$8))=1),1,0) -> 0 | BG13: =IF(AND(BG$5>=IF(I13="Core",C13,IF(I13="AI",Assumptions!$H$24,Assumptions!$H$25)),BG$5<=IF(I13="Core",D13,IF(I13="AI",Assumptions!$H$24,Assumptions!$H$25)+D13-C13),IF(I13="Core",1,IF(I13="AI",'Start Here'!$B$7,'Start Here'!$B$8))=1),1,0) -> 0 | BH13: =IF(AND(BH$5>=IF(I13="Core",C13,IF(I13="AI",Assumptions!$H$24,Assumptions!$H$25)),BH$5<=IF(I13="Core",D13,IF(I13="AI",Assumptions!$H$24,Assumptions!$H$25)+D13-C13),IF(I13="Core",1,IF(I13="AI",'Start Here'!$B$7,'Start Here'!$B$8))=1),1,0) -> 0 | BI13: =IF(AND(BI$5>=IF(I13="Core",C13,IF(I13="AI",Assumptions!$H$24,Assumptions!$H$25)),BI$5<=IF(I13="Core",D13,IF(I13="AI",Assumptions!$H$24,Assumptions!$H$25)+D13-C13),IF(I13="Core",1,IF(I13="AI",'Start Here'!$B$7,'Start Here'!$B$8))=1),1,0) -> 0 | BJ13: =IF(AND(BJ$5>=IF(I13="Core",C13,IF(I13="AI",Assumptions!$H$24,Assumptions!$H$25)),BJ$5<=IF(I13="Core",D13,IF(I13="AI",Assumptions!$H$24,Assumptions!$H$25)+D13-C13),IF(I13="Core",1,IF(I13="AI",'Start Here'!$B$7,'Start Here'!$B$8))=1),1,0) -> 0 | BK13: =IF(AND(BK$5>=IF(I13="Core",C13,IF(I13="AI",Assumptions!$H$24,Assumptions!$H$25)),BK$5<=IF(I13="Core",D13,IF(I13="AI",Assumptions!$H$24,Assumptions!$H$25)+D13-C13),IF(I13="Core",1,IF(I13="AI",'Start Here'!$B$7,'Start Here'!$B$8))=1),1,0) -> 0 | BL13: =IF(AND(BL$5>=IF(I13="Core",C13,IF(I13="AI",Assumptions!$H$24,Assumptions!$H$25)),BL$5<=IF(I13="Core",D13,IF(I13="AI",Assumptions!$H$24,Assumptions!$H$25)+D13-C13),IF(I13="Core",1,IF(I13="AI",'Start Here'!$B$7,'Start Here'!$B$8))=1),1,0) -> 0 | BM13: =IF(AND(BM$5>=IF(I13="Core",C13,IF(I13="AI",Assumptions!$H$24,Assumptions!$H$25)),BM$5<=IF(I13="Core",D13,IF(I13="AI",Assumptions!$H$24,Assumptions!$H$25)+D13-C13),IF(I13="Core",1,IF(I13="AI",'Start Here'!$B$7,'Start Here'!$B$8))=1),1,0) -> 0 | BN13: =IF(AND(BN$5>=IF(I13="Core",C13,IF(I13="AI",Assumptions!$H$24,Assumptions!$H$25)),BN$5<=IF(I13="Core",D13,IF(I13="AI",Assumptions!$H$24,Assumptions!$H$25)+D13-C13),IF(I13="Core",1,IF(I13="AI",'Start Here'!$B$7,'Start Here'!$B$8))=1),1,0) -> 0 | BO13: =IF(AND(BO$5>=IF(I13="Core",C13,IF(I13="AI",Assumptions!$H$24,Assumptions!$H$25)),BO$5<=IF(I13="Core",D13,IF(I13="AI",Assumptions!$H$24,Assumptions!$H$25)+D13-C13),IF(I13="Core",1,IF(I13="AI",'Start Here'!$B$7,'Start Here'!$B$8))=1),1,0) -> 0 | BP13: =IF(AND(BP$5>=IF(I13="Core",C13,IF(I13="AI",Assumptions!$H$24,Assumptions!$H$25)),BP$5<=IF(I13="Core",D13,IF(I13="AI",Assumptions!$H$24,Assumptions!$H$25)+D13-C13),IF(I13="Core",1,IF(I13="AI",'Start Here'!$B$7,'Start Here'!$B$8))=1),1,0) -> 0 | BQ13: =IF(AND(BQ$5>=IF(I13="Core",C13,IF(I13="AI",Assumptions!$H$24,Assumptions!$H$25)),BQ$5<=IF(I13="Core",D13,IF(I13="AI",Assumptions!$H$24,Assumptions!$H$25)+D13-C13),IF(I13="Core",1,IF(I13="AI",'Start Here'!$B$7,'Start Here'!$B$8))=1),1,0) -> 0 | BR13: =IF(AND(BR$5>=IF(I13="Core",C13,IF(I13="AI",Assumptions!$H$24,Assumptions!$H$25)),BR$5<=IF(I13="Core",D13,IF(I13="AI",Assumptions!$H$24,Assumptions!$H$25)+D13-C13),IF(I13="Core",1,IF(I13="AI",'Start Here'!$B$7,'Start Here'!$B$8))=1),1,0) -> 0

Sheet Risks and Funding
A1: Risks, decisions and funding gates
A2: Qualified specialists must assess HIPAA/BAA eligibility, clinical safety, intended use and research validation/e-signature rules. SOX is not assumed. No cloud product makes the application compliant.
A3: ← Start Here
A5: Id | B5: Risk | C5: Owner | D5: Mitigation | E5: Gate | F5: Cost | G5: Likelihood
A6: K1 | B6: Wrong first buyer or scope; rounding/CTMS conflation | C6: Founder | D6: Paid-pilot problem discovery; separate CTMS investment case; no valuation reverse engineering | E6: G1 and quarterly | F6: STAFF; contingency already included once | G6: High
A7: K2 | B7: Cross-tenant access or identity boundary failure | C7: Security / backend | D7: Trusted auth, per-resource checks, negative isolation tests, independent review and incident drills | E7: G2/G3/G4 | F7: STAFF / SECURITY | G7: High impact; likelihood unmeasured
A8: K3 | B8: Migration data loss or hidden field incompatibility | C8: Implementation / QA | D8: Schema manifest, synthetic rehearsal, count/hash/field reconciliation, write pause, staged cutover and rollback | E8: G3/G4 per tenant | F8: STAFF / ONBOARD | G8: Medium assumption
A9: K4 | B9: Clinical safety or validation evidence insufficient | C9: Clinical / validation | D9: Intended-use scope, synthetic edge cases, clinician acceptance, customer approval and stop rules | E9: G4; every material release | F9: STAFF / COMPLIANCE | G9: High impact; unmeasured
A10: K5 | B10: Incorrect regulatory applicability / contracts / cloud eligibility | C10: Qualified legal / validation specialist | D10: Review HIPAA/BAA/service eligibility and state privacy rules; SOX not assumed; research e-signature/validation scope-specific | E10: Before PHI or optional research/AI | F10: LEGAL / COMPLIANCE | G10: Unresolved
A11: K6 | B11: Hiring timing, blended roles and key-person dependence | C11: Founder / tech lead | D11: Confirm actual availability, contractor agreements and onboarding; capacity-level WBS before commitment; dates do not automatically compress | E11: Each hire / G2 | F11: STAFF / EQUIPMENT; recruiting modeled per incremental FTE | G11: Medium assumption
A12: K7 | B12: Sales procurement/onboarding lead time and churn exceed forecasts | C12: Founder / success / sales | D12: Track cohorts and buying process; zero-revenue cash sensitivity; quarterly reforecast before growth hires | E12: G4/G5/G6 | F12: MARKETING / ONBOARD / STAFF | G12: High
A13: K8 | B13: Unpriced infrastructure/security/legal/insurance services | C13: DevOps / founder | D13: Resolve amber catalog sources; exact SKUs/region/meters/renewal and independent quotes; do not treat allowances as vendor commitments | E13: G2 architecture / before contracts | F13: INFRA / LEGAL / SECURITY / INSURANCE | G13: Known gap
A14: K9 | B14: Vendor dependency, outage, backup failure and unexpected data egress | C14: DevOps | D14: Portable API/schema, export and restore drills, alert caps; choose one stack; review second-region recovery pricing | E14: G3 and quarterly | F14: INFRA / STAFF | G14: Medium assumption
A15: K10 | B15: Optional AI hallucination, privacy exposure, evaluation or provider changes | C15: AI / clinical / security | D15: Default off, synthetic evaluation, human approval, privacy/contract and model-version gates, token budgets and fallback | E15: G-AI | F15: AI / STAFF | G15: Unresolved optional
A16: K11 | B16: CTMS scope, partner rights and research validation underestimate | C16: Research domain / validation | D16: Separate study/site model, EDC/eTMF permissions, stakeholder evidence and scope-specific specialist review | E16: G-CTMS | F16: CTMS / STAFF | G16: High optional
A17: K12 | B17: Funding unavailable despite forecast receipts | C17: Founder | D17: Financing events are uncommitted; fund before first negative month, review stage cash needs and contingency; no valuation promise | E17: Every stage; monthly cash review | F17: Contingency is expense reserve, financing excluded from spend | G17: Unresolved
A20: Funding by core stage (selected scenario; spend includes contingency)
A21: Stage | B21: From | C21: Through | D21: Stage gross spend | E21: Cumulative gross spend | F21: Cumulative net need before cash/financing | G21: Maximum gap to date
A22: Assessment | B22: 1 | C22: 3 | D22: =SUM('Monthly Model'!AC6:AC8) -> 167832.15 | E22: =SUM('Monthly Model'!AC6:AC8) -> 167832.15 | F22: ='Monthly Model'!AP8 -> 167832.15 | G22: =MAX('Monthly Model'!AK6:AK8) -> 0
A23: Foundation | B23: 4 | C23: 8 | D23: =SUM('Monthly Model'!AC9:AC13) -> 419124.78 | E23: =SUM('Monthly Model'!AC6:AC13) -> 586956.93 | F23: ='Monthly Model'!AP13 -> 586956.93 | G23: =MAX('Monthly Model'!AK6:AK13) -> 0
A24: Synthetic pilot | B24: 9 | C24: 11 | D24: =SUM('Monthly Model'!AC14:AC16) -> 343367 | E24: =SUM('Monthly Model'!AC6:AC16) -> 930323.93 | F24: ='Monthly Model'!AP16 -> 930323.93 | G24: =MAX('Monthly Model'!AK6:AK16) -> 0
A25: Approved pilot | B25: 12 | C25: 15 | D25: =SUM('Monthly Model'!AC17:AC20) -> 416116.13 | E25: =SUM('Monthly Model'!AC6:AC20) -> 1346440.1 | F25: ='Monthly Model'!AP20 -> 1341076 | G25: =MAX('Monthly Model'!AK6:AK20) -> 27452.55
A26: Repeatable delivery | B26: 16 | C26: 24 | D26: =SUM('Monthly Model'!AC21:AC29) -> 1370392.4 | E26: =SUM('Monthly Model'!AC6:AC29) -> 2716832.5 | F26: ='Monthly Model'!AP29 -> 2649143.3 | G26: =MAX('Monthly Model'!AK6:AK29) -> 27452.55
A27: Growth | B27: 25 | C27: 60 | D27: =SUM('Monthly Model'!AC30:AC65) -> 8190417.6 | E27: =SUM('Monthly Model'!AC6:AC65) -> 10907250 | F27: ='Monthly Model'!AP65 -> 9465729.5 | G27: =MAX('Monthly Model'!AK6:AK65) -> 5465729.5

Sheet Staff Months
A1: Staffing monthly calculation detail
A2: Formula audit trail: date-bounded capacity; positive incremental FTE triggers recruiting/equipment. Only employees receive wage-based burden. Fractional headcount slots are ceiling(FTE), not confirmed people.
A3: ← Start Here
A5: Scenario | B5: Role ID | C5: Month | D5: Date | E5: FTE | F5: Salary cash | G5: Employer burden cash | H5: Loaded cash | I5: Unpaid founder economic | J5: Recruiting | K5: Equipment | L5: Headcount slots
A6: Lean | B6: FOUNDER | C6: 1 | D6: =EDATE('Start Here'!$B$6,C6-1) -> 46327 | E6: =IF(AND(C6>=Staffing!$F$6,C6<=Staffing!$G$6,1=1),IF(C6<=6,Staffing!$H$6,IF(C6<=15,Staffing!$I$6,IF(C6<=30,Staffing!$J$6,Staffing!$K$6))),0) -> 0.75 | F6: =E6*Assumptions!$C$26/12*(1+Assumptions!$C$10)^INT((C6-1)/12)*'Start Here'!$B$10 -> 0 | G6: =F6*Staffing!$N$6 -> 0 | H6: =F6+G6 -> 0 | I6: =E6*Assumptions!$C$26/12*(1+Assumptions!$C$10)^INT((C6-1)/12)*(1-'Start Here'!$B$10) -> 9375 | J6: =MAX(0,E6-0)*Staffing!$O$6 -> 0 | K6: =MAX(0,E6-0)*Staffing!$P$6 -> 1875 | L6: =ROUNDUP(E6,0) -> 1
A7: Lean | B7: FOUNDER | C7: 2 | D7: =EDATE('Start Here'!$B$6,C7-1) -> 46357 | E7: =IF(AND(C7>=Staffing!$F$6,C7<=Staffing!$G$6,1=1),IF(C7<=6,Staffing!$H$6,IF(C7<=15,Staffing!$I$6,IF(C7<=30,Staffing!$J$6,Staffing!$K$6))),0) -> 0.75 | F7: =E7*Assumptions!$C$26/12*(1+Assumptions!$C$10)^INT((C7-1)/12)*'Start Here'!$B$10 -> 0 | G7: =F7*Staffing!$N$6 -> 0 | H7: =F7+G7 -> 0 | I7: =E7*Assumptions!$C$26/12*(1+Assumptions!$C$10)^INT((C7-1)/12)*(1-'Start Here'!$B$10) -> 9375 | J7: =MAX(0,E7-E6)*Staffing!$O$6 -> 0 | K7: =MAX(0,E7-E6)*Staffing!$P$6 -> 0 | L7: =ROUNDUP(E7,0) -> 1
A8: Lean | B8: FOUNDER | C8: 3 | D8: =EDATE('Start Here'!$B$6,C8-1) -> 46388 | E8: =IF(AND(C8>=Staffing!$F$6,C8<=Staffing!$G$6,1=1),IF(C8<=6,Staffing!$H$6,IF(C8<=15,Staffing!$I$6,IF(C8<=30,Staffing!$J$6,Staffing!$K$6))),0) -> 0.75 | F8: =E8*Assumptions!$C$26/12*(1+Assumptions!$C$10)^INT((C8-1)/12)*'Start Here'!$B$10 -> 0 | G8: =F8*Staffing!$N$6 -> 0 | H8: =F8+G8 -> 0 | I8: =E8*Assumptions!$C$26/12*(1+Assumptions!$C$10)^INT((C8-1)/12)*(1-'Start Here'!$B$10) -> 9375 | J8: =MAX(0,E8-E7)*Staffing!$O$6 -> 0 | K8: =MAX(0,E8-E7)*Staffing!$P$6 -> 0 | L8: =ROUNDUP(E8,0) -> 1
A9: Lean | B9: FOUNDER | C9: 4 | D9: =EDATE('Start Here'!$B$6,C9-1) -> 46419 | E9: =IF(AND(C9>=Staffing!$F$6,C9<=Staffing!$G$6,1=1),IF(C9<=6,Staffing!$H$6,IF(C9<=15,Staffing!$I$6,IF(C9<=30,Staffing!$J$6,Staffing!$K$6))),0) -> 0.75 | F9: =E9*Assumptions!$C$26/12*(1+Assumptions!$C$10)^INT((C9-1)/12)*'Start Here'!$B$10 -> 0 | G9: =F9*Staffing!$N$6 -> 0 | H9: =F9+G9 -> 0 | I9: =E9*Assumptions!$C$26/12*(1+Assumptions!$C$10)^INT((C9-1)/12)*(1-'Start Here'!$B$10) -> 9375 | J9: =MAX(0,E9-E8)*Staffing!$O$6 -> 0 | K9: =MAX(0,E9-E8)*Staffing!$P$6 -> 0 | L9: =ROUNDUP(E9,0) -> 1
A10: Lean | B10: FOUNDER | C10: 5 | D10: =EDATE('Start Here'!$B$6,C10-1) -> 46447 | E10: =IF(AND(C10>=Staffing!$F$6,C10<=Staffing!$G$6,1=1),IF(C10<=6,Staffing!$H$6,IF(C10<=15,Staffing!$I$6,IF(C10<=30,Staffing!$J$6,Staffing!$K$6))),0) -> 0.75 | F10: =E10*Assumptions!$C$26/12*(1+Assumptions!$C$10)^INT((C10-1)/12)*'Start Here'!$B$10 -> 0 | G10: =F10*Staffing!$N$6 -> 0 | H10: =F10+G10 -> 0 | I10: =E10*Assumptions!$C$26/12*(1+Assumptions!$C$10)^INT((C10-1)/12)*(1-'Start Here'!$B$10) -> 9375 | J10: =MAX(0,E10-E9)*Staffing!$O$6 -> 0 | K10: =MAX(0,E10-E9)*Staffing!$P$6 -> 0 | L10: =ROUNDUP(E10,0) -> 1
A11: Lean | B11: FOUNDER | C11: 6 | D11: =EDATE('Start Here'!$B$6,C11-1) -> 46478 | E11: =IF(AND(C11>=Staffing!$F$6,C11<=Staffing!$G$6,1=1),IF(C11<=6,Staffing!$H$6,IF(C11<=15,Staffing!$I$6,IF(C11<=30,Staffing!$J$6,Staffing!$K$6))),0) -> 0.75 | F11: =E11*Assumptions!$C$26/12*(1+Assumptions!$C$10)^INT((C11-1)/12)*'Start Here'!$B$10 -> 0 | G11: =F11*Staffing!$N$6 -> 0 | H11: =F11+G11 -> 0 | I11: =E11*Assumptions!$C$26/12*(1+Assumptions!$C$10)^INT((C11-1)/12)*(1-'Start Here'!$B$10) -> 9375 | J11: =MAX(0,E11-E10)*Staffing!$O$6 -> 0 | K11: =MAX(0,E11-E10)*Staffing!$P$6 -> 0 | L11: =ROUNDUP(E11,0) -> 1
A12: Lean | B12: FOUNDER | C12: 7 | D12: =EDATE('Start Here'!$B$6,C12-1) -> 46508 | E12: =IF(AND(C12>=Staffing!$F$6,C12<=Staffing!$G$6,1=1),IF(C12<=6,Staffing!$H$6,IF(C12<=15,Staffing!$I$6,IF(C12<=30,Staffing!$J$6,Staffing!$K$6))),0) -> 0.75 | F12: =E12*Assumptions!$C$26/12*(1+Assumptions!$C$10)^INT((C12-1)/12)*'Start Here'!$B$10 -> 0 | G12: =F12*Staffing!$N$6 -> 0 | H12: =F12+G12 -> 0 | I12: =E12*Assumptions!$C$26/12*(1+Assumptions!$C$10)^INT((C12-1)/12)*(1-'Start Here'!$B$10) -> 9375 | J12: =MAX(0,E12-E11)*Staffing!$O$6 -> 0 | K12: =MAX(0,E12-E11)*Staffing!$P$6 -> 0 | L12: =ROUNDUP(E12,0) -> 1
A13: Lean | B13: FOUNDER | C13: 8 | D13: =EDATE('Start Here'!$B$6,C13-1) -> 46539 | E13: =IF(AND(C13>=Staffing!$F$6,C13<=Staffing!$G$6,1=1),IF(C13<=6,Staffing!$H$6,IF(C13<=15,Staffing!$I$6,IF(C13<=30,Staffing!$J$6,Staffing!$K$6))),0) -> 0.75 | F13: =E13*Assumptions!$C$26/12*(1+Assumptions!$C$10)^INT((C13-1)/12)*'Start Here'!$B$10 -> 0 | G13: =F13*Staffing!$N$6 -> 0 | H13: =F13+G13 -> 0 | I13: =E13*Assumptions!$C$26/12*(1+Assumptions!$C$10)^INT((C13-1)/12)*(1-'Start Here'!$B$10) -> 9375 | J13: =MAX(0,E13-E12)*Staffing!$O$6 -> 0 | K13: =MAX(0,E13-E12)*Staffing!$P$6 -> 0 | L13: =ROUNDUP(E13,0) -> 1
A14: Lean | B14: FOUNDER | C14: 9 | D14: =EDATE('Start Here'!$B$6,C14-1) -> 46569 | E14: =IF(AND(C14>=Staffing!$F$6,C14<=Staffing!$G$6,1=1),IF(C14<=6,Staffing!$H$6,IF(C14<=15,Staffing!$I$6,IF(C14<=30,Staffing!$J$6,Staffing!$K$6))),0) -> 0.75 | F14: =E14*Assumptions!$C$26/12*(1+Assumptions!$C$10)^INT((C14-1)/12)*'Start Here'!$B$10 -> 0 | G14: =F14*Staffing!$N$6 -> 0 | H14: =F14+G14 -> 0 | I14: =E14*Assumptions!$C$26/12*(1+Assumptions!$C$10)^INT((C14-1)/12)*(1-'Start Here'!$B$10) -> 9375 | J14: =MAX(0,E14-E13)*Staffing!$O$6 -> 0 | K14: =MAX(0,E14-E13)*Staffing!$P$6 -> 0 | L14: =ROUNDUP(E14,0) -> 1
A15: Lean | B15: FOUNDER | C15: 10 | D15: =EDATE('Start Here'!$B$6,C15-1) -> 46600 | E15: =IF(AND(C15>=Staffing!$F$6,C15<=Staffing!$G$6,1=1),IF(C15<=6,Staffing!$H$6,IF(C15<=15,Staffing!$I$6,IF(C15<=30,Staffing!$J$6,Staffing!$K$6))),0) -> 0.75 | F15: =E15*Assumptions!$C$26/12*(1+Assumptions!$C$10)^INT((C15-1)/12)*'Start Here'!$B$10 -> 0 | G15: =F15*Staffing!$N$6 -> 0 | H15: =F15+G15 -> 0 | I15: =E15*Assumptions!$C$26/12*(1+Assumptions!$C$10)^INT((C15-1)/12)*(1-'Start Here'!$B$10) -> 9375 | J15: =MAX(0,E15-E14)*Staffing!$O$6 -> 0 | K15: =MAX(0,E15-E14)*Staffing!$P$6 -> 0 | L15: =ROUNDUP(E15,0) -> 1
A16: Lean | B16: FOUNDER | C16: 11 | D16: =EDATE('Start Here'!$B$6,C16-1) -> 46631 | E16: =IF(AND(C16>=Staffing!$F$6,C16<=Staffing!$G$6,1=1),IF(C16<=6,Staffing!$H$6,IF(C16<=15,Staffing!$I$6,IF(C16<=30,Staffing!$J$6,Staffing!$K$6))),0) -> 0.75 | F16: =E16*Assumptions!$C$26/12*(1+Assumptions!$C$10)^INT((C16-1)/12)*'Start Here'!$B$10 -> 0 | G16: =F16*Staffing!$N$6 -> 0 | H16: =F16+G16 -> 0 | I16: =E16*Assumptions!$C$26/12*(1+Assumptions!$C$10)^INT((C16-1)/12)*(1-'Start Here'!$B$10) -> 9375 | J16: =MAX(0,E16-E15)*Staffing!$O$6 -> 0 | K16: =MAX(0,E16-E15)*Staffing!$P$6 -> 0 | L16: =ROUNDUP(E16,0) -> 1
A17: Lean | B17: FOUNDER | C17: 12 | D17: =EDATE('Start Here'!$B$6,C17-1) -> 46661 | E17: =IF(AND(C17>=Staffing!$F$6,C17<=Staffing!$G$6,1=1),IF(C17<=6,Staffing!$H$6,IF(C17<=15,Staffing!$I$6,IF(C17<=30,Staffing!$J$6,Staffing!$K$6))),0) -> 0.75 | F17: =E17*Assumptions!$C$26/12*(1+Assumptions!$C$10)^INT((C17-1)/12)*'Start Here'!$B$10 -> 0 | G17: =F17*Staffing!$N$6 -> 0 | H17: =F17+G17 -> 0 | I17: =E17*Assumptions!$C$26/12*(1+Assumptions!$C$10)^INT((C17-1)/12)*(1-'Start Here'!$B$10) -> 9375 | J17: =MAX(0,E17-E16)*Staffing!$O$6 -> 0 | K17: =MAX(0,E17-E16)*Staffing!$P$6 -> 0 | L17: =ROUNDUP(E17,0) -> 1
A18: Lean | B18: FOUNDER | C18: 13 | D18: =EDATE('Start Here'!$B$6,C18-1) -> 46692 | E18: =IF(AND(C18>=Staffing!$F$6,C18<=Staffing!$G$6,1=1),IF(C18<=6,Staffing!$H$6,IF(C18<=15,Staffing!$I$6,IF(C18<=30,Staffing!$J$6,Staffing!$K$6))),0) -> 0.75 | F18: =E18*Assumptions!$C$26/12*(1+Assumptions!$C$10)^INT((C18-1)/12)*'Start Here'!$B$10 -> 0 | G18: =F18*Staffing!$N$6 -> 0 | H18: =F18+G18 -> 0 | I18: =E18*Assumptions!$C$26/12*(1+Assumptions!$C$10)^INT((C18-1)/12)*(1-'Start Here'!$B$10) -> 9656.25 | J18: =MAX(0,E18-E17)*Staffing!$O$6 -> 0 | K18: =MAX(0,E18-E17)*Staffing!$P$6 -> 0 | L18: =ROUNDUP(E18,0) -> 1
... A65: Lean | B65: FOUNDER | C65: 60 | D65: =EDATE('Start Here'!$B$6,C65-1) -> 48122 | E65: =IF(AND(C65>=Staffing!$F$6,C65<=Staffing!$G$6,1=1),IF(C65<=6,Staffing!$H$6,IF(C65<=15,Staffing!$I$6,IF(C65<=30,Staffing!$J$6,Staffing!$K$6))),0) -> 0.75 | F65: =E65*Assumptions!$C$26/12*(1+Assumptions!$C$10)^INT((C65-1)/12)*'Start Here'!$B$10 -> 0 | G65: =F65*Staffing!$N$6 -> 0 | H65: =F65+G65 -> 0 | I65: =E65*Assumptions!$C$26/12*(1+Assumptions!$C$10)^INT((C65-1)/12)*(1-'Start Here'!$B$10) -> 10551.645 | J65: =MAX(0,E65-E64)*Staffing!$O$6 -> 0 | K65: =MAX(0,E65-E64)*Staffing!$P$6 -> 0 | L65: =ROUNDUP(E65,0) -> 1
A66: Lean | B66: LEAD | C66: 1 | D66: =EDATE('Start Here'!$B$6,C66-1) -> 46327 | E66: =IF(AND(C66>=Staffing!$F$7,C66<=Staffing!$G$7,1=1),IF(C66<=6,Staffing!$H$7,IF(C66<=15,Staffing!$I$7,IF(C66<=30,Staffing!$J$7,Staffing!$K$7))),0) -> 1 | F66: =E66*Staffing!$L$7/12*(1+Assumptions!$C$10)^INT((C66-1)/12)*1 -> 13750 | G66: =F66*Staffing!$N$7 -> 5500 | H66: =F66+G66 -> 19250 | I66: =0 -> 0 | J66: =MAX(0,E66-0)*Staffing!$O$7 -> 5000 | K66: =MAX(0,E66-0)*Staffing!$P$7 -> 2500 | L66: =ROUNDUP(E66,0) -> 1
A67: Lean | B67: LEAD | C67: 2 | D67: =EDATE('Start Here'!$B$6,C67-1) -> 46357 | E67: =IF(AND(C67>=Staffing!$F$7,C67<=Staffing!$G$7,1=1),IF(C67<=6,Staffing!$H$7,IF(C67<=15,Staffing!$I$7,IF(C67<=30,Staffing!$J$7,Staffing!$K$7))),0) -> 1 | F67: =E67*Staffing!$L$7/12*(1+Assumptions!$C$10)^INT((C67-1)/12)*1 -> 13750 | G67: =F67*Staffing!$N$7 -> 5500 | H67: =F67+G67 -> 19250 | I67: =0 -> 0 | J67: =MAX(0,E67-E66)*Staffing!$O$7 -> 0 | K67: =MAX(0,E67-E66)*Staffing!$P$7 -> 0 | L67: =ROUNDUP(E67,0) -> 1
A68: Lean | B68: LEAD | C68: 3 | D68: =EDATE('Start Here'!$B$6,C68-1) -> 46388 | E68: =IF(AND(C68>=Staffing!$F$7,C68<=Staffing!$G$7,1=1),IF(C68<=6,Staffing!$H$7,IF(C68<=15,Staffing!$I$7,IF(C68<=30,Staffing!$J$7,Staffing!$K$7))),0) -> 1 | F68: =E68*Staffing!$L$7/12*(1+Assumptions!$C$10)^INT((C68-1)/12)*1 -> 13750 | G68: =F68*Staffing!$N$7 -> 5500 | H68: =F68+G68 -> 19250 | I68: =0 -> 0 | J68: =MAX(0,E68-E67)*Staffing!$O$7 -> 0 | K68: =MAX(0,E68-E67)*Staffing!$P$7 -> 0 | L68: =ROUNDUP(E68,0) -> 1
A69: Lean | B69: LEAD | C69: 4 | D69: =EDATE('Start Here'!$B$6,C69-1) -> 46419 | E69: =IF(AND(C69>=Staffing!$F$7,C69<=Staffing!$G$7,1=1),IF(C69<=6,Staffing!$H$7,IF(C69<=15,Staffing!$I$7,IF(C69<=30,Staffing!$J$7,Staffing!$K$7))),0) -> 1 | F69: =E69*Staffing!$L$7/12*(1+Assumptions!$C$10)^INT((C69-1)/12)*1 -> 13750 | G69: =F69*Staffing!$N$7 -> 5500 | H69: =F69+G69 -> 19250 | I69: =0 -> 0 | J69: =MAX(0,E69-E68)*Staffing!$O$7 -> 0 | K69: =MAX(0,E69-E68)*Staffing!$P$7 -> 0 | L69: =ROUNDUP(E69,0) -> 1
A70: Lean | B70: LEAD | C70: 5 | D70: =EDATE('Start Here'!$B$6,C70-1) -> 46447 | E70: =IF(AND(C70>=Staffing!$F$7,C70<=Staffing!$G$7,1=1),IF(C70<=6,Staffing!$H$7,IF(C70<=15,Staffing!$I$7,IF(C70<=30,Staffing!$J$7,Staffing!$K$7))),0) -> 1 | F70: =E70*Staffing!$L$7/12*(1+Assumptions!$C$10)^INT((C70-1)/12)*1 -> 13750 | G70: =F70*Staffing!$N$7 -> 5500 | H70: =F70+G70 -> 19250 | I70: =0 -> 0 | J70: =MAX(0,E70-E69)*Staffing!$O$7 -> 0 | K70: =MAX(0,E70-E69)*Staffing!$P$7 -> 0 | L70: =ROUNDUP(E70,0) -> 1
A71: Lean | B71: LEAD | C71: 6 | D71: =EDATE('Start Here'!$B$6,C71-1) -> 46478 | E71: =IF(AND(C71>=Staffing!$F$7,C71<=Staffing!$G$7,1=1),IF(C71<=6,Staffing!$H$7,IF(C71<=15,Staffing!$I$7,IF(C71<=30,Staffing!$J$7,Staffing!$K$7))),0) -> 1 | F71: =E71*Staffing!$L$7/12*(1+Assumptions!$C$10)^INT((C71-1)/12)*1 -> 13750 | G71: =F71*Staffing!$N$7 -> 5500 | H71: =F71+G71 -> 19250 | I71: =0 -> 0 | J71: =MAX(0,E71-E70)*Staffing!$O$7 -> 0 | K71: =MAX(0,E71-E70)*Staffing!$P$7 -> 0 | L71: =ROUNDUP(E71,0) -> 1
A72: Lean | B72: LEAD | C72: 7 | D72: =EDATE('Start Here'!$B$6,C72-1) -> 46508 | E72: =IF(AND(C72>=Staffing!$F$7,C72<=Staffing!$G$7,1=1),IF(C72<=6,Staffing!$H$7,IF(C72<=15,Staffing!$I$7,IF(C72<=30,Staffing!$J$7,Staffing!$K$7))),0) -> 1 | F72: =E72*Staffing!$L$7/12*(1+Assumptions!$C$10)^INT((C72-1)/12)*1 -> 13750 | G72: =F72*Staffing!$N$7 -> 5500 | H72: =F72+G72 -> 19250 | I72: =0 -> 0 | J72: =MAX(0,E72-E71)*Staffing!$O$7 -> 0 | K72: =MAX(0,E72-E71)*Staffing!$P$7 -> 0 | L72: =ROUNDUP(E72,0) -> 1
A73: Lean | B73: LEAD | C73: 8 | D73: =EDATE('Start Here'!$B$6,C73-1) -> 46539 | E73: =IF(AND(C73>=Staffing!$F$7,C73<=Staffing!$G$7,1=1),IF(C73<=6,Staffing!$H$7,IF(C73<=15,Staffing!$I$7,IF(C73<=30,Staffing!$J$7,Staffing!$K$7))),0) -> 1 | F73: =E73*Staffing!$L$7/12*(1+Assumptions!$C$10)^INT((C73-1)/12)*1 -> 13750 | G73: =F73*Staffing!$N$7 -> 5500 | H73: =F73+G73 -> 19250 | I73: =0 -> 0 | J73: =MAX(0,E73-E72)*Staffing!$O$7 -> 0 | K73: =MAX(0,E73-E72)*Staffing!$P$7 -> 0 | L73: =ROUNDUP(E73,0) -> 1
A74: Lean | B74: LEAD | C74: 9 | D74: =EDATE('Start Here'!$B$6,C74-1) -> 46569 | E74: =IF(AND(C74>=Staffing!$F$7,C74<=Staffing!$G$7,1=1),IF(C74<=6,Staffing!$H$7,IF(C74<=15,Staffing!$I$7,IF(C74<=30,Staffing!$J$7,Staffing!$K$7))),0) -> 1 | F74: =E74*Staffing!$L$7/12*(1+Assumptions!$C$10)^INT((C74-1)/12)*1 -> 13750 | G74: =F74*Staffing!$N$7 -> 5500 | H74: =F74+G74 -> 19250 | I74: =0 -> 0 | J74: =MAX(0,E74-E73)*Staffing!$O$7 -> 0 | K74: =MAX(0,E74-E73)*Staffing!$P$7 -> 0 | L74: =ROUNDUP(E74,0) -> 1
A75: Lean | B75: LEAD | C75: 10 | D75: =EDATE('Start Here'!$B$6,C75-1) -> 46600 | E75: =IF(AND(C75>=Staffing!$F$7,C75<=Staffing!$G$7,1=1),IF(C75<=6,Staffing!$H$7,IF(C75<=15,Staffing!$I$7,IF(C75<=30,Staffing!$J$7,Staffing!$K$7))),0) -> 1 | F75: =E75*Staffing!$L$7/12*(1+Assumptions!$C$10)^INT((C75-1)/12)*1 -> 13750 | G75: =F75*Staffing!$N$7 -> 5500 | H75: =F75+G75 -> 19250 | I75: =0 -> 0 | J75: =MAX(0,E75-E74)*Staffing!$O$7 -> 0 | K75: =MAX(0,E75-E74)*Staffing!$P$7 -> 0 | L75: =ROUNDUP(E75,0) -> 1
A76: Lean | B76: LEAD | C76: 11 | D76: =EDATE('Start Here'!$B$6,C76-1) -> 46631 | E76: =IF(AND(C76>=Staffing!$F$7,C76<=Staffing!$G$7,1=1),IF(C76<=6,Staffing!$H$7,IF(C76<=15,Staffing!$I$7,IF(C76<=30,Staffing!$J$7,Staffing!$K$7))),0) -> 1 | F76: =E76*Staffing!$L$7/12*(1+Assumptions!$C$10)^INT((C76-1)/12)*1 -> 13750 | G76: =F76*Staffing!$N$7 -> 5500 | H76: =F76+G76 -> 19250 | I76: =0 -> 0 | J76: =MAX(0,E76-E75)*Staffing!$O$7 -> 0 | K76: =MAX(0,E76-E75)*Staffing!$P$7 -> 0 | L76: =ROUNDUP(E76,0) -> 1
A77: Lean | B77: LEAD | C77: 12 | D77: =EDATE('Start Here'!$B$6,C77-1) -> 46661 | E77: =IF(AND(C77>=Staffing!$F$7,C77<=Staffing!$G$7,1=1),IF(C77<=6,Staffing!$H$7,IF(C77<=15,Staffing!$I$7,IF(C77<=30,Staffing!$J$7,Staffing!$K$7))),0) -> 1 | F77: =E77*Staffing!$L$7/12*(1+Assumptions!$C$10)^INT((C77-1)/12)*1 -> 13750 | G77: =F77*Staffing!$N$7 -> 5500 | H77: =F77+G77 -> 19250 | I77: =0 -> 0 | J77: =MAX(0,E77-E76)*Staffing!$O$7 -> 0 | K77: =MAX(0,E77-E76)*Staffing!$P$7 -> 0 | L77: =ROUNDUP(E77,0) -> 1
A78: Lean | B78: LEAD | C78: 13 | D78: =EDATE('Start Here'!$B$6,C78-1) -> 46692 | E78: =IF(AND(C78>=Staffing!$F$7,C78<=Staffing!$G$7,1=1),IF(C78<=6,Staffing!$H$7,IF(C78<=15,Staffing!$I$7,IF(C78<=30,Staffing!$J$7,Staffing!$K$7))),0) -> 1 | F78: =E78*Staffing!$L$7/12*(1+Assumptions!$C$10)^INT((C78-1)/12)*1 -> 14162.5 | G78: =F78*Staffing!$N$7 -> 5665 | H78: =F78+G78 -> 19827.5 | I78: =0 -> 0 | J78: =MAX(0,E78-E77)*Staffing!$O$7 -> 0 | K78: =MAX(0,E78-E77)*Staffing!$P$7 -> 0 | L78: =ROUNDUP(E78,0) -> 1
... A125: Lean | B125: LEAD | C125: 60 | D125: =EDATE('Start Here'!$B$6,C125-1) -> 48122 | E125: =IF(AND(C125>=Staffing!$F$7,C125<=Staffing!$G$7,1=1),IF(C125<=6,Staffing!$H$7,IF(C125<=15,Staffing!$I$7,IF(C125<=30,Staffing!$J$7,Staffing!$K$7))),0) -> 1 | F125: =E125*Staffing!$L$7/12*(1+Assumptions!$C$10)^INT((C125-1)/12)*1 -> 15475.746 | G125: =F125*Staffing!$N$7 -> 6190.2985 | H125: =F125+G125 -> 21666.045 | I125: =0 -> 0 | J125: =MAX(0,E125-E124)*Staffing!$O$7 -> 0 | K125: =MAX(0,E125-E124)*Staffing!$P$7 -> 0 | L125: =ROUNDUP(E125,0) -> 1
A126: Lean | B126: BACKEND | C126: 1 | D126: =EDATE('Start Here'!$B$6,C126-1) -> 46327 | E126: =IF(AND(C126>=Staffing!$F$8,C126<=Staffing!$G$8,1=1),IF(C126<=6,Staffing!$H$8,IF(C126<=15,Staffing!$I$8,IF(C126<=30,Staffing!$J$8,Staffing!$K$8))),0) -> 0 | F126: =E126*Staffing!$L$8/12*(1+Assumptions!$C$10)^INT((C126-1)/12)*1 -> 0 | G126: =F126*Staffing!$N$8 -> 0 | H126: =F126+G126 -> 0 | I126: =0 -> 0 | J126: =MAX(0,E126-0)*Staffing!$O$8 -> 0 | K126: =MAX(0,E126-0)*Staffing!$P$8 -> 0 | L126: =ROUNDUP(E126,0) -> 0
A127: Lean | B127: BACKEND | C127: 2 | D127: =EDATE('Start Here'!$B$6,C127-1) -> 46357 | E127: =IF(AND(C127>=Staffing!$F$8,C127<=Staffing!$G$8,1=1),IF(C127<=6,Staffing!$H$8,IF(C127<=15,Staffing!$I$8,IF(C127<=30,Staffing!$J$8,Staffing!$K$8))),0) -> 0 | F127: =E127*Staffing!$L$8/12*(1+Assumptions!$C$10)^INT((C127-1)/12)*1 -> 0 | G127: =F127*Staffing!$N$8 -> 0 | H127: =F127+G127 -> 0 | I127: =0 -> 0 | J127: =MAX(0,E127-E126)*Staffing!$O$8 -> 0 | K127: =MAX(0,E127-E126)*Staffing!$P$8 -> 0 | L127: =ROUNDUP(E127,0) -> 0
A128: Lean | B128: BACKEND | C128: 3 | D128: =EDATE('Start Here'!$B$6,C128-1) -> 46388 | E128: =IF(AND(C128>=Staffing!$F$8,C128<=Staffing!$G$8,1=1),IF(C128<=6,Staffing!$H$8,IF(C128<=15,Staffing!$I$8,IF(C128<=30,Staffing!$J$8,Staffing!$K$8))),0) -> 0 | F128: =E128*Staffing!$L$8/12*(1+Assumptions!$C$10)^INT((C128-1)/12)*1 -> 0 | G128: =F128*Staffing!$N$8 -> 0 | H128: =F128+G128 -> 0 | I128: =0 -> 0 | J128: =MAX(0,E128-E127)*Staffing!$O$8 -> 0 | K128: =MAX(0,E128-E127)*Staffing!$P$8 -> 0 | L128: =ROUNDUP(E128,0) -> 0
